Workbook
Name Buick: Lists!$C$2:$C$3
Name Chevy: Lists!$C$4:$C$10
Name Chrysler: Lists!$C$11:$C$12
Name Fiat: Lists!$C$13:$C$14
Name Ford: Lists!$C$15:$C$18
Name Honda: Lists!$C$19:$C$23
Name Hyundai: Lists!$C$24:$C$29
Name Jeep: Lists!$C$30:$C$30
Name Kia: Lists!$C$31:$C$36
Name Mazda: Lists!$C$37:$C$39
Name Mini: Lists!$C$40:$C$41
Name Nissan: Lists!$C$42:$C$43
Name Porsche: Lists!$C$44:$C$45
Name Subaru: Lists!$C$46:$C$48
Name Tesla: Lists!$C$49:$C$49
Name Toyota: Lists!$C$50:$C$64
Name VW: Lists!$C$65:$C$69
Name Volvo: Lists!$C$70:$C$72
Name MAKES: Lists!$N$2:$N$19
Name YEARS: Lists!$O$2:$O$23
Name CARS: Lists!$A$2:$A$72

Sheet Start here
B2: TRUE COST OF OWNERSHIP — how this workbook is built, in four layers
B4: The goal: the true lifetime cost of owning each car, in cost-per-mile, driven to end-of-life. Everything is discounted at 7% real — the S&P 500 long-run return — so the money you sink into a car is charged its market opportunity cost. Costs come from a Monte-Carlo simulation (N=1,100 runs per car), so every number carries a measured uncertainty and the rankings come with a statistical-significance test.
B8: LAYER 1 — SURVEY
B9: → tab(s): Sweet-spot heat map
B10: A wide survey of EVERY model×year×odometer combination inside a broad filter. For each vehicle it maps $/mile across the whole odometer range and finds the cost-optimal buy point. This is the raw field the rankings are drawn from.
B13: LAYER 2 — RANKINGS
B14: → tab(s): Ranking (hardened)
B15: The best buy of each model pulled from the survey, ranked by median $/mile. Now with STATISTICAL TIE TIERS (cars you cannot tell apart), a 90% outcome band, the probability each car beats the next, and the market opportunity cost of the cash tied up.
B18: LAYER 3 — DEAL ANALYZER
B19: → tab(s): Any-Car Calculator
B20: Found a real listing? Type in its year, odometer and asking price (or pick from the dropdown) and it drops that exact car onto the ranked table — so you can see whether a specific deal beats the idealised picks above.
B23: LAYER 4 — ANALYSIS SUITE
... B33: Your basis: 13,000 mi/yr · USAA active-duty insurance · Florida registration · Fresno CA garaging · gas $5.455 / elec $0.32. Edit the yellow cells anywhere to re-run for different assumptions.

Sheet Sweet-spot heat map
A1: SWEET-SPOT HEAT MAP — median $/mile vs PURCHASE ODOMETER (California prices). Each column shows both the odometer AND the ≈ model year it implies at 13k mi/yr. Green = cheaper. Grey ▒ = infeasible (too few miles left before end-of-life, or that odometer would imply a year before the model existed). ★ = each vehicle's cheapest column; ◆ = pinned buy. LIVE: every cell is a formula tied to that car's editable Purchase $ on the Ranking tab — fix a price there and this whole row re-scales and re-colors. Every $/mile cell also links to a cars.com search at that odometer/price band so you can verify the price behind it.
A3: Vehicle | B3: 10k mi | C3: 20k mi | D3: 40k mi | E3: 60k mi | F3: 80k mi | G3: 100k mi | H3: 120k mi | I3: 150k mi | J3: 180k mi | K3: Lowest $/mi (newest) | L3: Buy pick ◆ (least cash) | M3: Pinned $/mi (live) | N3: Stat. tier | O3: 90% band $/mi (at pinned buy) | P3: Capital opp cost $/mi newest → oldest
A4: (cells link to cars.com; values live off Ranking price) | B4: ≈ 2025 | C4: ≈ 2024 | D4: ≈ 2023 | E4: ≈ 2021 | F4: ≈ 2020 | G4: ≈ 2018 | H4: ≈ 2017 | I4: ≈ 2014 | J4: ≈ 2012 | K4: ↓ cheapest per-mile | L4: ◆ least $ up-front · = Ranking | M4: (updates w/ your price) | N4: (tie group) | O4: (P5–P95 outcome) | P4: (scales w/ price: high when new)
A5: Chevy Bolt EV | B5: ▒ | C5: ▒ | D5: =0.22026+0.099429*'Ranking (hardened)'!$F$6/15643 | E5: =0.23874+0.105462*'Ranking (hardened)'!$F$6/15643 | F5: =0.24938+0.116473*'Ranking (hardened)'!$F$6/15643 | G5: =0.26201+0.133067*'Ranking (hardened)'!$F$6/15643 | H5: =0.27194+0.157107*'Ranking (hardened)'!$F$6/15643 | I5: ▒ | J5: ▒ | K5: ↓ 40k · ≈2023 | L5: ◆ 45k · ≈2023 · $15,643 | M5: =0.22331+0.100792*'Ranking (hardened)'!$F$6/15643 | N5: 1 | O5: $0.289–$0.389 | P5: $0.129 → $0.081
A6: Chevy Volt | B6: ▒ | C6: ▒ | D6: ▒ | E6: ▒ | F6: ▒ | G6: =0.26688+0.12475*'Ranking (hardened)'!$F$7/15143 | H6: =0.27719+0.143392*'Ranking (hardened)'!$F$7/15143 | I6: ▒ | J6: ▒ | K6: ↓ 100k · ≈2018 | L6: ◆ 55k · ≈2019 · $15,143 | M6: =0.23564+0.10429*'Ranking (hardened)'!$F$7/15143 | N6: 1 | O6: $0.307–$0.385 | P6: $0.085 → $0.074
A7: Toyota Prius (hybrid) | B7: =0.21025+0.116861*'Ranking (hardened)'!$F$8/26000 | C7: =0.21645+0.120209*'Ranking (hardened)'!$F$8/26000 | D7: =0.22881+0.124046*'Ranking (hardened)'!$F$8/26000 | E7: =0.24294+0.130098*'Ranking (hardened)'!$F$8/26000 | F7: =0.2564+0.133648*'Ranking (hardened)'!$F$8/26000 | G7: =0.26655+0.13369*'Ranking (hardened)'!$F$8/26000 | H7: =0.28486+0.133745*'Ranking (hardened)'!$F$8/26000 | I7: =0.29692+0.145582*'Ranking (hardened)'!$F$8/26000 | J7: =0.31285+0.175287*'Ranking (hardened)'!$F$8/26000 | K7: ↓ 10k · ≈2025 | L7: ◆ 40k · ≈2023 · $26,000 | M7: =0.22881+0.124046*'Ranking (hardened)'!$F$8/26000 | N7: 1 | O7: $0.321–$0.387 | P7: $0.290 → $0.077
A8: Toyota Prius Prime | B8: =0.2178+0.133156*'Ranking (hardened)'!$F$9/15000 | C8: =0.22364+0.130051*'Ranking (hardened)'!$F$9/15000 | D8: =0.2348+0.114354*'Ranking (hardened)'!$F$9/15000 | E8: =0.24502+0.108386*'Ranking (hardened)'!$F$9/15000 | F8: =0.2577+0.105173*'Ranking (hardened)'!$F$9/15000 | G8: =0.27185+0.105937*'Ranking (hardened)'!$F$9/15000 | H8: =0.30505+0.112749*'Ranking (hardened)'!$F$9/15000 | I8: ▒ | J8: ▒ | K8: ↓ 40k · ≈2023 | L8: ◆ 90k · ≈2019 · $15,000 | M8: =0.26449+0.103235*'Ranking (hardened)'!$F$9/15000 | N8: 2 | O8: $0.330–$0.415 | P8: $0.297 → $0.093
A9: Toyota Corolla | B9: =0.25+0.100167*'Ranking (hardened)'!$F$10/17659 | C9: =0.25644+0.093809*'Ranking (hardened)'!$F$10/17659 | D9: =0.27818+0.089695*'Ranking (hardened)'!$F$10/17659 | E9: =0.28315+0.091341*'Ranking (hardened)'!$F$10/17659 | F9: =0.31268+0.095603*'Ranking (hardened)'!$F$10/17659 | G9: =0.31611+0.10361*'Ranking (hardened)'!$F$10/17659 | H9: =0.33306+0.106739*'Ranking (hardened)'!$F$10/17659 | I9: =0.37744+0.115462*'Ranking (hardened)'!$F$10/17659 | J9: =0.38134+0.133621*'Ranking (hardened)'!$F$10/17659 | K9: ↓ 10k · ≈2025 | L9: ◆ 55k · ≈2022 · $17,659 | M9: =0.27875+0.090746*'Ranking (hardened)'!$F$10/17659 | N9: 2 | O9: $0.339–$0.402 | P9: $0.248 → $0.058
A10: Toyota Camry Hybrid | B10: =0.22903+0.129382*'Ranking (hardened)'!$F$11/16500 | C10: =0.23529+0.126307*'Ranking (hardened)'!$F$11/16500 | D10: =0.24704+0.105643*'Ranking (hardened)'!$F$11/16500 | E10: =0.25816+0.098704*'Ranking (hardened)'!$F$11/16500 | F10: =0.27228+0.097288*'Ranking (hardened)'!$F$11/16500 | G10: =0.30566+0.10361*'Ranking (hardened)'!$F$11/16500 | H10: =0.30892+0.110597*'Ranking (hardened)'!$F$11/16500 | I10: =0.32463+0.122992*'Ranking (hardened)'!$F$11/16500 | J10: =0.34563+0.143678*'Ranking (hardened)'!$F$11/16500 | K10: ↓ 40k · ≈2023 | L10: ◆ 80k · ≈2020 · $16,500 | M10: =0.27228+0.097288*'Ranking (hardened)'!$F$11/16500 | N10: 2 | O10: $0.335–$0.411 | P10: $0.321 → $0.063
A11: Honda Civic | B11: =0.24981+0.110963*'Ranking (hardened)'!$F$12/23789 | C11: =0.25693+0.114161*'Ranking (hardened)'!$F$12/23789 | D11: =0.27136+0.120462*'Ranking (hardened)'!$F$12/23789 | E11: =0.28444+0.127638*'Ranking (hardened)'!$F$12/23789 | F11: =0.29935+0.130393*'Ranking (hardened)'!$F$12/23789 | G11: =0.31548+0.133038*'Ranking (hardened)'!$F$12/23789 | H11: =0.3356+0.138768*'Ranking (hardened)'!$F$12/23789 | I11: =0.35046+0.152403*'Ranking (hardened)'!$F$12/23789 | J11: =0.36578+0.180832*'Ranking (hardened)'!$F$12/23789 | K11: ↓ 10k · ≈2025 | L11: ◆ 35k · ≈2023 · $23,789 | M11: =0.26782+0.118769*'Ranking (hardened)'!$F$12/23789 | N11: 2 | O11: $0.357–$0.417 | P11: $0.247 → $0.060
A12: Nissan Leaf | B12: =0.24918+0.145706*'Ranking (hardened)'!$F$13/11667 | C12: =0.25528+0.137585*'Ranking (hardened)'!$F$13/11667 | D12: =0.2651+0.117862*'Ranking (hardened)'!$F$13/11667 | E12: =0.27948+0.138889*'Ranking (hardened)'!$F$13/11667 | F12: =0.29131+0.167928*'Ranking (hardened)'!$F$13/11667 | G12: =0.32324+0.222772*'Ranking (hardened)'!$F$13/11667 | H12: ▒ | I12: ▒ | J12: ▒ | K12: ↓ 40k · ≈2023 | L12: ◆ 45k · ≈2023 · $11,667 | M12: =0.27075+0.122292*'Ranking (hardened)'!$F$13/11667 | N12: 2 | O12: $0.339–$0.473 | P12: $0.142 → $0.052
A13: Hyundai Elantra | B13: =0.25719+0.105152*'Ranking (hardened)'!$F$14/16000 | C13: =0.26681+0.105197*'Ranking (hardened)'!$F$14/16000 | D13: =0.28207+0.102996*'Ranking (hardened)'!$F$14/16000 | E13: =0.29856+0.103424*'Ranking (hardened)'!$F$14/16000 | F13: =0.31405+0.103993*'Ranking (hardened)'!$F$14/16000 | G13: =0.33223+0.105503*'Ranking (hardened)'!$F$14/16000 | H13: =0.38062+0.110438*'Ranking (hardened)'!$F$14/16000 | I13: =0.37007+0.130905*'Ranking (hardened)'!$F$14/16000 | J13: =0.35405+0.272277*'Ranking (hardened)'!$F$14/16000 | K13: ↓ 10k · ≈2025 | L13: ◆ 45k · ≈2023 · $16,000 | M13: =0.28879+0.103093*'Ranking (hardened)'!$F$14/16000 | N13: 2 | O13: $0.357–$0.432 | P13: $0.178 → $0.030
A14: Honda Accord | B14: =0.25436+0.121475*'Ranking (hardened)'!$F$15/16143 | C14: =0.26071+0.115322*'Ranking (hardened)'!$F$15/16143 | D14: =0.27439+0.094763*'Ranking (hardened)'!$F$15/16143 | E14: =0.28624+0.094183*'Ranking (hardened)'!$F$15/16143 | F14: =0.30262+0.096128*'Ranking (hardened)'!$F$15/16143 | G14: =0.33599+0.099644*'Ranking (hardened)'!$F$15/16143 | H14: =0.33226+0.107884*'Ranking (hardened)'!$F$15/16143 | I14: =0.35849+0.124309*'Ranking (hardened)'!$F$15/16143 | J14: =0.36236+0.14876*'Ranking (hardened)'!$F$15/16143 | K14: ↓ 40k · ≈2023 | L14: ◆ 70k · ≈2021 · $16,143 | M14: =0.29392+0.09468*'Ranking (hardened)'!$F$15/16143 | N14: 2 | O14: $0.355–$0.425 | P14: $0.282 → $0.055
A15: Kia K4 | B15: =0.27346+0.114016*'Ranking (hardened)'!$F$16/20125 | C15: ▒ | D15: ▒ | E15: ▒ | F15: ▒ | G15: ▒ | H15: ▒ | I15: ▒ | J15: ▒ | K15: ↓ 10k · ≈2025 | L15: ◆ 18k · ≈2025 · $20,125 | M15: =0.28088+0.117142*'Ranking (hardened)'!$F$16/20125 | N15: 2 | O15: $0.369–$0.436 | P15: $0.177 → $0.177
A16: Mazda3 (SkyActiv) | B16: =0.259+0.119641*'Ranking (hardened)'!$F$17/15000 | C16: =0.26691+0.114675*'Ranking (hardened)'!$F$17/15000 | D16: =0.27892+0.096717*'Ranking (hardened)'!$F$17/15000 | E16: =0.29015+0.101594*'Ranking (hardened)'!$F$17/15000 | F16: =0.30896+0.101072*'Ranking (hardened)'!$F$17/15000 | G16: =0.31679+0.097197*'Ranking (hardened)'!$F$17/15000 | H16: =0.33057+0.096578*'Ranking (hardened)'!$F$17/15000 | I16: =0.36053+0.115512*'Ranking (hardened)'!$F$17/15000 | J16: =0.29861+0.179739*'Ranking (hardened)'!$F$17/15000 | K16: ↓ 40k · ≈2023 | L16: ◆ 65k · ≈2021 · $15,000 | M16: =0.2945+0.103022*'Ranking (hardened)'!$F$17/15000 | N16: 2 | O16: $0.364–$0.441 | P16: $0.220 → $0.031
A17: Toyota Camry | B17: =0.2552+0.114379*'Ranking (hardened)'!$F$18/22400 | C17: =0.26255+0.114767*'Ranking (hardened)'!$F$18/22400 | D17: =0.27754+0.113202*'Ranking (hardened)'!$F$18/22400 | E17: =0.29121+0.11191*'Ranking (hardened)'!$F$18/22400 | F17: =0.30781+0.110984*'Ranking (hardened)'!$F$18/22400 | G17: =0.34363+0.109819*'Ranking (hardened)'!$F$18/22400 | H17: =0.34534+0.111276*'Ranking (hardened)'!$F$18/22400 | I17: =0.37945+0.119275*'Ranking (hardened)'!$F$18/22400 | J17: =0.40875+0.13369*'Ranking (hardened)'!$F$18/22400 | K17: ↓ 10k · ≈2025 | L17: ◆ 55k · ≈2022 · $22,400 | M17: =0.28655+0.112112*'Ranking (hardened)'!$F$18/22400 | N17: 2 | O17: $0.363–$0.436 | P17: $0.295 → $0.064
A18: Toyota RAV4 Hybrid | B18: =0.23144+0.145051*'Ranking (hardened)'!$F$19/30444 | C18: =0.23767+0.147059*'Ranking (hardened)'!$F$19/30444 | D18: =0.25008+0.148945*'Ranking (hardened)'!$F$19/30444 | E18: =0.2614+0.159074*'Ranking (hardened)'!$F$19/30444 | F18: =0.27797+0.162206*'Ranking (hardened)'!$F$19/30444 | G18: =0.28833+0.166205*'Ranking (hardened)'!$F$19/30444 | H18: =0.30144+0.17283*'Ranking (hardened)'!$F$19/30444 | I18: ▒ | J18: ▒ | K18: ↓ 10k · ≈2025 | L18: ◆ 40k · ≈2023 · $30,444 | M18: =0.25008+0.148945*'Ranking (hardened)'!$F$19/30444 | N18: 2 | O18: $0.359–$0.437 | P18: $0.346 → $0.157
A19: Kia Niro (hybrid) | B19: =0.24178+0.13306*'Ranking (hardened)'!$F$20/17000 | C19: =0.25024+0.134844*'Ranking (hardened)'!$F$20/17000 | D19: =0.2661+0.126965*'Ranking (hardened)'!$F$20/17000 | E19: =0.28137+0.122421*'Ranking (hardened)'!$F$20/17000 | F19: =0.29945+0.123604*'Ranking (hardened)'!$F$20/17000 | G19: =0.32224+0.126502*'Ranking (hardened)'!$F$20/17000 | H19: =0.37213+0.124902*'Ranking (hardened)'!$F$20/17000 | I19: ▒ | J19: ▒ | K19: ↓ 10k · ≈2025 | L19: ◆ 65k · ≈2021 · $17,000 | M19: =0.28517+0.121083*'Ranking (hardened)'!$F$20/17000 | N19: 3 | O19: $0.367–$0.460 | P19: $0.235 → $0.070
A20: Tesla Model 3 | B20: =0.2568+0.154475*'Ranking (hardened)'!$F$21/21500 | C20: =0.26453+0.153668*'Ranking (hardened)'!$F$21/21500 | D20: =0.27518+0.133764*'Ranking (hardened)'!$F$21/21500 | E20: =0.29316+0.126396*'Ranking (hardened)'!$F$21/21500 | F20: =0.31136+0.133245*'Ranking (hardened)'!$F$21/21500 | G20: =0.35548+0.138355*'Ranking (hardened)'!$F$21/21500 | H20: ▒ | I20: ▒ | J20: ▒ | K20: ↓ 40k · ≈2023 | L20: ◆ 60k · ≈2021 · $21,500 | M20: =0.29316+0.126396*'Ranking (hardened)'!$F$21/21500 | N20: 3 | O20: $0.367–$0.503 | P20: $0.331 → $0.134
A21: Hyundai Sonata | B21: =0.2727+0.118919*'Ranking (hardened)'!$F$22/15333 | C21: =0.28104+0.121143*'Ranking (hardened)'!$F$22/15333 | D21: =0.29615+0.116129*'Ranking (hardened)'!$F$22/15333 | E21: =0.31268+0.11358*'Ranking (hardened)'!$F$22/15333 | F21: =0.32753+0.113043*'Ranking (hardened)'!$F$22/15333 | G21: =0.34994+0.115789*'Ranking (hardened)'!$F$22/15333 | H21: =0.37026+0.12381*'Ranking (hardened)'!$F$22/15333 | I21: =0.43761+0.153968*'Ranking (hardened)'!$F$22/15333 | J21: ▒ | K21: ↓ 10k · ≈2025 | L21: ◆ 60k · ≈2021 · $15,333 | M21: =0.31268+0.11358*'Ranking (hardened)'!$F$22/15333 | N21: 3 | O21: $0.387–$0.478 | P21: $0.193 → $0.041
A22: Toyota RAV4 | B22: =0.25799+0.143167*'Ranking (hardened)'!$F$23/20600 | C22: =0.26438+0.14059*'Ranking (hardened)'!$F$23/20600 | D22: =0.27779+0.142643*'Ranking (hardened)'!$F$23/20600 | E22: =0.28915+0.134349*'Ranking (hardened)'!$F$23/20600 | F22: =0.3058+0.128349*'Ranking (hardened)'!$F$23/20600 | G22: =0.31761+0.128114*'Ranking (hardened)'!$F$23/20600 | H22: =0.33231+0.13278*'Ranking (hardened)'!$F$23/20600 | I22: =0.3954+0.160835*'Ranking (hardened)'!$F$23/20600 | J22: ▒ | K22: ↓ 10k · ≈2025 | L22: ◆ 80k · ≈2020 · $20,600 | M22: =0.3058+0.128349*'Ranking (hardened)'!$F$23/20600 | N22: 3 | O22: $0.396–$0.477 | P22: $0.332 → $0.097
A23: Fiat 500 | B23: ▒ | C23: ▒ | D23: ▒ | E23: ▒ | F23: ▒ | G23: =0.45103+0.094602*'Ranking (hardened)'!$F$24/10200 | H23: =0.4914+0.112782*'Ranking (hardened)'!$F$24/10200 | I23: ▒ | J23: ▒ | K23: ↓ 100k · ≈2018 | L23: ◆ 40k · ≈2019 · $10,200 | M23: =0.35714+0.085071*'Ranking (hardened)'!$F$24/10200 | N23: 3 | O23: $0.409–$0.496 | P23: $0.035 → $0.026
A24: Honda CR-V | B24: =0.26686+0.13449*'Ranking (hardened)'!$F$25/20500 | C24: =0.27439+0.135407*'Ranking (hardened)'!$F$25/20500 | D24: =0.28897+0.126113*'Ranking (hardened)'!$F$25/20500 | E24: =0.30214+0.121884*'Ranking (hardened)'!$F$25/20500 | F24: =0.31835+0.124611*'Ranking (hardened)'!$F$25/20500 | G24: =0.37734+0.128114*'Ranking (hardened)'!$F$25/20500 | H24: =0.40007+0.13278*'Ranking (hardened)'!$F$25/20500 | I24: =0.38336+0.145225*'Ranking (hardened)'!$F$25/20500 | J24: =0.40085+0.173554*'Ranking (hardened)'!$F$25/20500 | K24: ↓ 10k · ≈2025 | L24: ◆ 75k · ≈2020 · $20,500 | M24: =0.31464+0.123867*'Ranking (hardened)'!$F$25/20500 | N24: 3 | O24: $0.400–$0.480 | P24: $0.312 → $0.064
A25: VW ID.4 (AWD avail) | B25: =0.26709+0.162162*'Ranking (hardened)'!$F$26/22500 | C25: =0.27233+0.16*'Ranking (hardened)'!$F$26/22500 | D25: =0.28599+0.148387*'Ranking (hardened)'!$F$26/22500 | E25: =0.32399+0.155556*'Ranking (hardened)'!$F$26/22500 | F25: ▒ | G25: ▒ | H25: ▒ | I25: ▒ | J25: ▒ | K25: ↓ 10k · ≈2025 | L25: ◆ 45k · ≈2023 · $22,500 | M25: =0.29271+0.15*'Ranking (hardened)'!$F$26/22500 | N25: 3 | O25: $0.389–$0.529 | P25: $0.263 → $0.159
A26: Toyota RAV4 Prime | B26: =0.22684+0.186418*'Ranking (hardened)'!$F$27/35000 | C26: =0.23238+0.190432*'Ranking (hardened)'!$F$27/35000 | D26: =0.23982+0.189452*'Ranking (hardened)'!$F$27/35000 | E26: =0.26381+0.195855*'Ranking (hardened)'!$F$27/35000 | F26: ▒ | G26: ▒ | H26: ▒ | I26: ▒ | J26: ▒ | K26: ↓ 10k · ≈2025 | L26: ◆ 55k · ≈2022 · $35,000 | M26: =0.24778+0.194121*'Ranking (hardened)'!$F$27/35000 | N26: 3 | O26: $0.402–$0.484 | P26: $0.416 → $0.292
A27: Kia Soul | B27: =0.2868+0.126002*'Ranking (hardened)'!$F$28/14500 | C27: =0.29493+0.123092*'Ranking (hardened)'!$F$28/14500 | D27: =0.31221+0.114108*'Ranking (hardened)'!$F$28/14500 | E27: =0.32682+0.116372*'Ranking (hardened)'!$F$28/14500 | F27: =0.36584+0.119503*'Ranking (hardened)'!$F$28/14500 | G27: =0.36289+0.124113*'Ranking (hardened)'!$F$28/14500 | H27: =0.38085+0.131579*'Ranking (hardened)'!$F$28/14500 | I27: =0.42533+0.179604*'Ranking (hardened)'!$F$28/14500 | J27: ▒ | K27: ↓ 10k · ≈2025 | L27: ◆ 60k · ≈2021 · $14,500 | M27: =0.32682+0.116372*'Ranking (hardened)'!$F$28/14500 | N27: 3 | O27: $0.406–$0.494 | P27: $0.187 → $0.035
A28: VW Passat | B28: ▒ | C28: ▒ | D28: ▒ | E28: =0.35502+0.104777*'Ranking (hardened)'!$F$29/14200 | F28: =0.37334+0.104736*'Ranking (hardened)'!$F$29/14200 | G28: =0.39384+0.107381*'Ranking (hardened)'!$F$29/14200 | H28: =0.40994+0.117683*'Ranking (hardened)'!$F$29/14200 | I28: =0.41646+0.152548*'Ranking (hardened)'!$F$29/14200 | J28: ▒ | K28: ↓ 60k · ≈2021 | L28: ◆ 55k · ≈2022 · $14,200 | M28: =0.34606+0.105341*'Ranking (hardened)'!$F$29/14200 | N28: 4 | O28: $0.412–$0.507 | P28: $0.101 → $0.035
A29: Buick Encore | B29: =0.29909+0.120846*'Ranking (hardened)'!$F$30/14800 | C29: =0.30803+0.123473*'Ranking (hardened)'!$F$30/14800 | D29: =0.32656+0.118081*'Ranking (hardened)'!$F$30/14800 | E29: =0.34619+0.117749*'Ranking (hardened)'!$F$30/14800 | F29: =0.36053+0.120419*'Ranking (hardened)'!$F$30/14800 | G29: =0.37754+0.126932*'Ranking (hardened)'!$F$30/14800 | H29: =0.39436+0.142643*'Ranking (hardened)'!$F$30/14800 | I29: =0.38774+0.212418*'Ranking (hardened)'!$F$30/14800 | J29: ▒ | K29: ↓ 10k · ≈2025 | L29: ◆ 50k · ≈2022 · $14,800 | M29: =0.33631+0.117928*'Ranking (hardened)'!$F$30/14800 | N29: 4 | O29: $0.419–$0.499 | P29: $0.165 → $0.030
A30: Hyundai Kona | B30: =0.28665+0.137457*'Ranking (hardened)'!$F$31/15000 | C30: =0.29584+0.139733*'Ranking (hardened)'!$F$31/15000 | D30: =0.31274+0.131397*'Ranking (hardened)'!$F$31/15000 | E30: =0.32914+0.126806*'Ranking (hardened)'!$F$31/15000 | F30: =0.34724+0.129063*'Ranking (hardened)'!$F$31/15000 | G30: =0.39379+0.135934*'Ranking (hardened)'!$F$31/15000 | H30: ▒ | I30: ▒ | J30: ▒ | K30: ↓ 10k · ≈2025 | L30: ◆ 65k · ≈2021 · $15,000 | M30: =0.33293+0.125418*'Ranking (hardened)'!$F$31/15000 | N30: 4 | O30: $0.423–$0.504 | P30: $0.204 → $0.075
A31: Mazda CX-5 | B31: =0.28425+0.141809*'Ranking (hardened)'!$F$32/20600 | C31: =0.29216+0.143959*'Ranking (hardened)'!$F$32/20600 | D31: =0.3074+0.137536*'Ranking (hardened)'!$F$32/20600 | E31: =0.32085+0.137217*'Ranking (hardened)'!$F$32/20600 | F31: =0.33642+0.137546*'Ranking (hardened)'!$F$32/20600 | G31: =0.35779+0.136827*'Ranking (hardened)'!$F$32/20600 | H31: =0.36711+0.137566*'Ranking (hardened)'!$F$32/20600 | I31: =0.40607+0.166667*'Ranking (hardened)'!$F$32/20600 | J31: ▒ | K31: ↓ 10k · ≈2025 | L31: ◆ 65k · ≈2021 · $20,600 | M31: =0.32463+0.137793*'Ranking (hardened)'!$F$32/20600 | N31: 4 | O31: $0.427–$0.505 | P31: $0.269 → $0.066
A32: Toyota Highlander Hybrid | B32: =0.25617+0.183447*'Ranking (hardened)'!$F$33/32000 | C32: =0.2635+0.186275*'Ranking (hardened)'!$F$33/32000 | D32: =0.2777+0.181018*'Ranking (hardened)'!$F$33/32000 | E32: =0.29029+0.178959*'Ranking (hardened)'!$F$33/32000 | F32: =0.32199+0.176399*'Ranking (hardened)'!$F$33/32000 | G32: =0.32249+0.175439*'Ranking (hardened)'!$F$33/32000 | H32: =0.33938+0.176849*'Ranking (hardened)'!$F$33/32000 | I32: =0.36172+0.180085*'Ranking (hardened)'!$F$33/32000 | J32: =0.38535+0.205745*'Ranking (hardened)'!$F$33/32000 | K32: ↓ 10k · ≈2025 | L32: ◆ 65k · ≈2021 · $32,000 | M32: =0.29392+0.178372*'Ranking (hardened)'!$F$33/32000 | N32: 4 | O32: $0.425–$0.524 | P32: $0.438 → $0.082
A33: Subaru Outback | B33: =0.28367+0.159521*'Ranking (hardened)'!$F$34/18800 | C33: =0.29235+0.160021*'Ranking (hardened)'!$F$34/18800 | D33: =0.30799+0.143611*'Ranking (hardened)'!$F$34/18800 | E33: =0.32314+0.138778*'Ranking (hardened)'!$F$34/18800 | F33: =0.3405+0.139357*'Ranking (hardened)'!$F$34/18800 | G33: =0.36783+0.144665*'Ranking (hardened)'!$F$34/18800 | H33: =0.38743+0.152318*'Ranking (hardened)'!$F$34/18800 | I33: =0.46688+0.178218*'Ranking (hardened)'!$F$34/18800 | J33: =0.43223+0.281046*'Ranking (hardened)'!$F$34/18800 | K33: ↓ 10k · ≈2025 | L33: ◆ 75k · ≈2020 · $18,800 | M33: =0.337+0.138643*'Ranking (hardened)'!$F$34/18800 | N33: 4 | O33: $0.432–$0.538 | P33: $0.294 → $0.049
A34: Subaru Forester | B34: =0.28754+0.152471*'Ranking (hardened)'!$F$35/22200 | C34: =0.29644+0.155383*'Ranking (hardened)'!$F$35/22200 | D34: =0.31281+0.149813*'Ranking (hardened)'!$F$35/22200 | E34: =0.32847+0.154066*'Ranking (hardened)'!$F$35/22200 | F34: =0.34614+0.166389*'Ranking (hardened)'!$F$35/22200 | G34: =0.37379+0.182136*'Ranking (hardened)'!$F$35/22200 | H34: =0.39163+0.19015*'Ranking (hardened)'!$F$35/22200 | I34: =0.46595+0.229084*'Ranking (hardened)'!$F$35/22200 | J34: =0.33705+0.442794*'Ranking (hardened)'!$F$35/22200 | K34: ↓ 10k · ≈2025 | L34: ◆ 55k · ≈2022 · $22,200 | M34: =0.32222+0.152893*'Ranking (hardened)'!$F$35/22200 | N34: 4 | O34: $0.439–$0.523 | P34: $0.258 → $0.049
A35: Toyota Sienna Hybrid | B35: =0.25138+0.187713*'Ranking (hardened)'!$F$36/35000 | C35: =0.25891+0.190508*'Ranking (hardened)'!$F$36/35000 | D35: =0.27374+0.18591*'Ranking (hardened)'!$F$36/35000 | E35: =0.29085+0.184382*'Ranking (hardened)'!$F$36/35000 | F35: ▒ | G35: ▒ | H35: ▒ | I35: ▒ | J35: ▒ | K35: ↓ 10k · ≈2025 | L35: ◆ 55k · ≈2022 · $35,000 | M35: =0.28603+0.184794*'Ranking (hardened)'!$F$36/35000 | N35: 4 | O35: $0.416–$0.525 | P35: $0.448 → $0.297
A36: Toyota Tacoma | B36: =0.29764+0.146481*'Ranking (hardened)'!$F$37/29333 | C36: =0.30457+0.143263*'Ranking (hardened)'!$F$37/29333 | D36: =0.31869+0.136054*'Ranking (hardened)'!$F$37/29333 | E36: =0.33158+0.136291*'Ranking (hardened)'!$F$37/29333 | F36: =0.34705+0.136573*'Ranking (hardened)'!$F$37/29333 | G36: =0.36387+0.136914*'Ranking (hardened)'!$F$37/29333 | H36: =0.38532+0.137336*'Ranking (hardened)'!$F$37/29333 | I36: =0.40434+0.138194*'Ranking (hardened)'!$F$37/29333 | J36: =0.42587+0.145587*'Ranking (hardened)'!$F$37/29333 | K36: ↓ 10k · ≈2025 | L36: ◆ 75k · ≈2020 · $29,333 | M36: =0.34342+0.136498*'Ranking (hardened)'!$F$37/29333 | N36: 4 | O36: $0.440–$0.531 | P36: $0.482 → $0.112
A37: Nissan Rogue | B37: =0.29397+0.168434*'Ranking (hardened)'!$F$38/18800 | C37: =0.30318+0.170326*'Ranking (hardened)'!$F$38/18800 | D37: =0.3182+0.153492*'Ranking (hardened)'!$F$38/18800 | E37: =0.33568+0.166818*'Ranking (hardened)'!$F$38/18800 | F37: =0.37189+0.172757*'Ranking (hardened)'!$F$38/18800 | G37: =0.42966+0.177809*'Ranking (hardened)'!$F$38/18800 | H37: =0.45221+0.202783*'Ranking (hardened)'!$F$38/18800 | I37: =0.36726+0.369458*'Ranking (hardened)'!$F$38/18800 | J37: ▒ | K37: ↓ 10k · ≈2025 | L37: ◆ 55k · ≈2022 · $18,800 | M37: =0.32801+0.163053*'Ranking (hardened)'!$F$38/18800 | N37: 4 | O37: $0.451–$0.541 | P37: $0.219 → $0.041
A38: Chevy Equinox | B38: =0.31135+0.151057*'Ranking (hardened)'!$F$39/17200 | C38: =0.32162+0.153055*'Ranking (hardened)'!$F$39/17200 | D38: =0.33912+0.140221*'Ranking (hardened)'!$F$39/17200 | E38: =0.35802+0.143723*'Ranking (hardened)'!$F$39/17200 | F38: =0.40063+0.158564*'Ranking (hardened)'!$F$39/17200 | G38: =0.43188+0.18543*'Ranking (hardened)'!$F$39/17200 | H38: =0.41867+0.198198*'Ranking (hardened)'!$F$39/17200 | I38: =0.37242+0.303922*'Ranking (hardened)'!$F$39/17200 | J38: ▒ | K38: ↓ 10k · ≈2025 | L38: ◆ 55k · ≈2022 · $17,200 | M38: =0.34983+0.142739*'Ranking (hardened)'!$F$39/17200 | N38: 5 | O38: $0.455–$0.546 | P38: $0.206 → $0.043
A39: Toyota Sienna (V6) | B39: ▒ | C39: ▒ | D39: ▒ | E39: ▒ | F39: =0.38606+0.123682*'Ranking (hardened)'!$F$40/22333 | G39: =0.40839+0.122345*'Ranking (hardened)'!$F$40/22333 | H39: =0.44641+0.120579*'Ranking (hardened)'!$F$40/22333 | I39: =0.46542+0.127119*'Ranking (hardened)'!$F$40/22333 | J39: =0.49857+0.139752*'Ranking (hardened)'!$F$40/22333 | K39: ↓ 80k · ≈2020 | L39: ◆ 65k · ≈2020 · $22,333 | M39: =0.37071+0.124489*'Ranking (hardened)'!$F$40/22333 | N39: 5 | O39: $0.457–$0.533 | P39: $0.167 → $0.056
A40: Mini Cooper | B40: =0.31558+0.145015*'Ranking (hardened)'!$F$41/18200 | C40: =0.32715+0.14791*'Ranking (hardened)'!$F$41/18200 | D40: =0.34956+0.140221*'Ranking (hardened)'!$F$41/18200 | E40: =0.37643+0.136797*'Ranking (hardened)'!$F$41/18200 | F40: =0.40169+0.136126*'Ranking (hardened)'!$F$41/18200 | G40: =0.4223+0.139073*'Ranking (hardened)'!$F$41/18200 | H40: =0.45057+0.153153*'Ranking (hardened)'!$F$41/18200 | I40: =0.44344+0.243697*'Ranking (hardened)'!$F$41/18200 | J40: ▒ | K40: ↓ 10k · ≈2025 | L40: ◆ 45k · ≈2023 · $18,200 | M40: =0.35712+0.139464*'Ranking (hardened)'!$F$41/18200 | N40: 5 | O40: $0.451–$0.566 | P40: $0.198 → $0.035
A41: Ford Ranger (old compact) | B41: ▒ | C41: ▒ | D41: ▒ | E41: ▒ | F41: ▒ | G41: ▒ | H41: ▒ | I41: ▒ | J41: ▒ | K41: — | L41: ◆ 55k · ≈2011 · $11,500 | M41: =0.42824+0.0721*'Ranking (hardened)'!$F$42/11500 | N41: 5 | O41: $0.467–$0.547 | P41: —
A42: Fiat 500X | B42: ▒ | C42: ▒ | D42: =0.3705+0.13516*'Ranking (hardened)'!$F$43/14800 | E42: =0.39803+0.136313*'Ranking (hardened)'!$F$43/14800 | F42: =0.41002+0.143885*'Ranking (hardened)'!$F$43/14800 | G42: =0.46875+0.163636*'Ranking (hardened)'!$F$43/14800 | H42: =0.47554+0.220339*'Ranking (hardened)'!$F$43/14800 | I42: ▒ | J42: ▒ | K42: ↓ 40k · ≈2023 | L42: ◆ 40k · ≈2023 · $14,800 | M42: =0.3705+0.13516*'Ranking (hardened)'!$F$43/14800 | N42: 5 | O42: $0.475–$0.549 | P42: $0.104 → $0.037
A43: VW GTI | B43: =0.31201+0.156757*'Ranking (hardened)'!$F$44/19000 | C43: =0.3228+0.158857*'Ranking (hardened)'!$F$44/19000 | D43: =0.34288+0.148387*'Ranking (hardened)'!$F$44/19000 | E43: =0.36768+0.140741*'Ranking (hardened)'!$F$44/19000 | F43: =0.39048+0.13913*'Ranking (hardened)'!$F$44/19000 | G43: =0.41175+0.140351*'Ranking (hardened)'!$F$44/19000 | H43: =0.43707+0.142222*'Ranking (hardened)'!$F$44/19000 | I43: ▒ | J43: ▒ | K43: ↓ 10k · ≈2025 | L43: ◆ 60k · ≈2021 · $19,000 | M43: =0.36768+0.140741*'Ranking (hardened)'!$F$44/19000 | N43: 5 | O43: $0.464–$0.574 | P43: $0.254 → $0.068
A44: Kia Sportage | B44: =0.30826+0.154639*'Ranking (hardened)'!$F$45/15667 | C44: =0.31776+0.157959*'Ranking (hardened)'!$F$45/15667 | D44: =0.33148+0.152144*'Ranking (hardened)'!$F$45/15667 | E44: =0.35162+0.144462*'Ranking (hardened)'!$F$45/15667 | F44: =0.36942+0.143403*'Ranking (hardened)'!$F$45/15667 | G44: =0.39697+0.147754*'Ranking (hardened)'!$F$45/15667 | H44: =0.4363+0.162539*'Ranking (hardened)'!$F$45/15667 | I44: =0.40313+0.227085*'Ranking (hardened)'!$F$45/15667 | J44: ▒ | K44: ↓ 10k · ≈2025 | L44: ◆ 75k · ≈2020 · $15,667 | M44: =0.36603+0.142944*'Ranking (hardened)'!$F$45/15667 | N44: 5 | O44: $0.468–$0.571 | P44: $0.229 → $0.045
A45: Ford Escape | B45: =0.31795+0.162196*'Ranking (hardened)'!$F$46/15000 | C45: =0.32982+0.163007*'Ranking (hardened)'!$F$46/15000 | D45: =0.34565+0.14198*'Ranking (hardened)'!$F$46/15000 | E45: =0.36222+0.142339*'Ranking (hardened)'!$F$46/15000 | F45: =0.40539+0.146179*'Ranking (hardened)'!$F$46/15000 | G45: =0.40098+0.152916*'Ranking (hardened)'!$F$46/15000 | H45: =0.41666+0.168986*'Ranking (hardened)'!$F$46/15000 | I45: =0.41656+0.320197*'Ranking (hardened)'!$F$46/15000 | J45: ▒ | K45: ↓ 10k · ≈2025 | L45: ◆ 65k · ≈2021 · $15,000 | M45: =0.367+0.14245*'Ranking (hardened)'!$F$46/15000 | N45: 5 | O45: $0.462–$0.574 | P45: $0.211 → $0.036
A46: Toyota Highlander | B46: =0.29747+0.170648*'Ranking (hardened)'!$F$47/25000 | C46: =0.30557+0.172906*'Ranking (hardened)'!$F$47/25000 | D46: =0.32135+0.166341*'Ranking (hardened)'!$F$47/25000 | E46: =0.33556+0.16269*'Ranking (hardened)'!$F$47/25000 | F46: =0.36889+0.158151*'Ranking (hardened)'!$F$47/25000 | G46: =0.371+0.154663*'Ranking (hardened)'!$F$47/25000 | H46: =0.3894+0.152733*'Ranking (hardened)'!$F$47/25000 | I46: =0.41421+0.158898*'Ranking (hardened)'!$F$47/25000 | J46: =0.43888+0.186335*'Ranking (hardened)'!$F$47/25000 | K46: ↓ 10k · ≈2025 | L46: ◆ 85k · ≈2019 · $25,000 | M46: =0.3575+0.156838*'Ranking (hardened)'!$F$47/25000 | N46: 5 | O46: $0.467–$0.571 | P46: $0.407 → $0.074
A47: Hyundai Tucson | B47: =0.31822+0.174672*'Ranking (hardened)'!$F$48/19541 | C47: =0.32815+0.176979*'Ranking (hardened)'!$F$48/19541 | D47: =0.34469+0.161167*'Ranking (hardened)'!$F$48/19541 | E47: =0.3633+0.172748*'Ranking (hardened)'!$F$48/19541 | F47: =0.38089+0.190107*'Ranking (hardened)'!$F$48/19541 | G47: =0.41119+0.221411*'Ranking (hardened)'!$F$48/19541 | H47: =0.42559+0.271313*'Ranking (hardened)'!$F$48/19541 | I47: =0.32513+0.431034*'Ranking (hardened)'!$F$48/19541 | J47: ▒ | K47: ↓ 10k · ≈2025 | L47: ◆ 55k · ≈2022 · $19,541 | M47: =0.35531+0.169476*'Ranking (hardened)'!$F$48/19541 | N47: 5 | O47: $0.491–$0.579 | P47: $0.228 → $0.048
A48: Toyota 4Runner | B48: =0.32411+0.157199*'Ranking (hardened)'!$F$49/36333 | C48: =0.32997+0.163023*'Ranking (hardened)'!$F$49/36333 | D48: =0.34624+0.160064*'Ranking (hardened)'!$F$49/36333 | E48: =0.36427+0.15804*'Ranking (hardened)'!$F$49/36333 | F48: =0.38238+0.157218*'Ranking (hardened)'!$F$49/36333 | G48: =0.40221+0.157978*'Ranking (hardened)'!$F$49/36333 | H48: =0.42242+0.158917*'Ranking (hardened)'!$F$49/36333 | I48: =0.45203+0.160829*'Ranking (hardened)'!$F$49/36333 | J48: =0.48096+0.168335*'Ranking (hardened)'!$F$49/36333 | K48: ↓ 10k · ≈2025 | L48: ◆ 60k · ≈2021 · $36,333 | M48: =0.36427+0.15804*'Ranking (hardened)'!$F$49/36333 | N48: 5 | O48: $0.473–$0.570 | P48: $0.517 → $0.130
A49: Honda Odyssey | B49: =0.31836+0.16752*'Ranking (hardened)'!$F$50/20333 | C49: =0.32881+0.175695*'Ranking (hardened)'!$F$50/20333 | D49: =0.34745+0.160087*'Ranking (hardened)'!$F$50/20333 | E49: =0.37012+0.147968*'Ranking (hardened)'!$F$50/20333 | F49: =0.38735+0.140327*'Ranking (hardened)'!$F$50/20333 | G49: =0.4376+0.136109*'Ranking (hardened)'!$F$50/20333 | H49: =0.44116+0.136638*'Ranking (hardened)'!$F$50/20333 | I49: =0.51002+0.143048*'Ranking (hardened)'!$F$50/20333 | J49: =0.52235+0.200445*'Ranking (hardened)'!$F$50/20333 | K49: ↓ 10k · ≈2025 | L49: ◆ 80k · ≈2020 · $20,333 | M49: =0.38735+0.140327*'Ranking (hardened)'!$F$50/20333 | N49: 5 | O49: $0.472–$0.580 | P49: $0.345 → $0.053
A50: Kia Sorento | B50: =0.3192+0.157729*'Ranking (hardened)'!$F$51/18333 | C50: =0.32958+0.166482*'Ranking (hardened)'!$F$51/18333 | D50: =0.34814+0.157303*'Ranking (hardened)'!$F$51/18333 | E50: =0.36606+0.149786*'Ranking (hardened)'!$F$51/18333 | F50: =0.38645+0.146977*'Ranking (hardened)'!$F$51/18333 | G50: =0.41763+0.149701*'Ranking (hardened)'!$F$51/18333 | H50: =0.44188+0.153782*'Ranking (hardened)'!$F$51/18333 | I50: =0.52948+0.179283*'Ranking (hardened)'!$F$51/18333 | J50: =0.49072+0.371287*'Ranking (hardened)'!$F$51/18333 | K50: ↓ 10k · ≈2025 | L50: ◆ 75k · ≈2020 · $18,333 | M50: =0.38214+0.146432*'Ranking (hardened)'!$F$51/18333 | N50: 5 | O50: $0.482–$0.586 | P50: $0.267 → $0.041
A51: Hyundai Santa Fe | B51: =0.31489+0.16129*'Ranking (hardened)'!$F$52/16667 | C51: =0.32501+0.170789*'Ranking (hardened)'!$F$52/16667 | D51: =0.34266+0.161549*'Ranking (hardened)'!$F$52/16667 | E51: =0.35962+0.154083*'Ranking (hardened)'!$F$52/16667 | F51: =0.37814+0.151791*'Ranking (hardened)'!$F$52/16667 | G51: =0.4069+0.155902*'Ranking (hardened)'!$F$52/16667 | H51: =0.42651+0.162369*'Ranking (hardened)'!$F$52/16667 | I51: =0.49336+0.208184*'Ranking (hardened)'!$F$52/16667 | J51: ▒ | K51: ↓ 10k · ≈2025 | L51: ◆ 80k · ≈2020 · $16,667 | M51: =0.37814+0.151791*'Ranking (hardened)'!$F$52/16667 | N51: 5 | O51: $0.487–$0.594 | P51: $0.250 → $0.048
A52: VW Tiguan | B52: =0.34097+0.148912*'Ranking (hardened)'!$F$53/16800 | C52: =0.35285+0.150668*'Ranking (hardened)'!$F$53/16800 | D52: =0.37522+0.138313*'Ranking (hardened)'!$F$53/16800 | E52: =0.39811+0.134831*'Ranking (hardened)'!$F$53/16800 | F52: =0.42406+0.133843*'Ranking (hardened)'!$F$53/16800 | G52: =0.48707+0.134752*'Ranking (hardened)'!$F$53/16800 | H52: ▒ | I52: ▒ | J52: ▒ | K52: ↓ 10k · ≈2025 | L52: ◆ 60k · ≈2021 · $16,800 | M52: =0.39811+0.134831*'Ranking (hardened)'!$F$53/16800 | N52: 5 | O52: $0.482–$0.590 | P52: $0.221 → $0.075
A53: Chrysler Pacifica PHEV | B53: =0.29469+0.205438*'Ranking (hardened)'!$F$54/22000 | C53: =0.30563+0.21865*'Ranking (hardened)'!$F$54/22000 | D53: =0.32285+0.20369*'Ranking (hardened)'!$F$54/22000 | E53: =0.34107+0.199134*'Ranking (hardened)'!$F$54/22000 | F53: =0.36564+0.202443*'Ranking (hardened)'!$F$54/22000 | G53: =0.45223+0.211921*'Ranking (hardened)'!$F$54/22000 | H53: =0.48374+0.24024*'Ranking (hardened)'!$F$54/22000 | I53: ▒ | J53: ▒ | K53: ↓ 10k · ≈2025 | L53: ◆ 65k · ≈2021 · $22,000 | M53: =0.34457+0.199095*'Ranking (hardened)'!$F$54/22000 | N53: 6 | O53: $0.494–$0.619 | P53: $0.281 → $0.080
A54: Subaru Ascent | B54: =0.3292+0.171821*'Ranking (hardened)'!$F$55/23400 | C54: =0.33589+0.18226*'Ranking (hardened)'!$F$55/23400 | D54: =0.35262+0.179806*'Ranking (hardened)'!$F$55/23400 | E54: =0.37703+0.18138*'Ranking (hardened)'!$F$55/23400 | F54: =0.40958+0.188018*'Ranking (hardened)'!$F$55/23400 | G54: ▒ | H54: ▒ | I54: ▒ | J54: ▒ | K54: ↓ 10k · ≈2025 | L54: ◆ 55k · ≈2022 · $23,400 | M54: =0.36608+0.180556*'Ranking (hardened)'!$F$55/23400 | N54: 6 | O54: $0.506–$0.594 | P54: $0.254 → $0.136
A55: Ford Ranger (2019+ midsize) | B55: =0.35494+0.189274*'Ranking (hardened)'!$F$56/23000 | C55: =0.36515+0.190529*'Ranking (hardened)'!$F$56/23000 | D55: =0.37816+0.164378*'Ranking (hardened)'!$F$56/23000 | E55: =0.39957+0.160485*'Ranking (hardened)'!$F$56/23000 | F55: =0.42469+0.170549*'Ranking (hardened)'!$F$56/23000 | G55: ▒ | H55: ▒ | I55: ▒ | J55: ▒ | K55: ↓ 40k · ≈2023 | L55: ◆ 55k · ≈2022 · $23,000 | M55: =0.39272+0.158402*'Ranking (hardened)'!$F$56/23000 | N55: 6 | O55: $0.513–$0.597 | P55: $0.320 → $0.148
A56: Honda Pilot | B56: =0.32537+0.176826*'Ranking (hardened)'!$F$57/22500 | C56: =0.33419+0.178624*'Ranking (hardened)'!$F$57/22500 | D56: =0.35113+0.167658*'Ranking (hardened)'!$F$57/22500 | E56: =0.37044+0.163736*'Ranking (hardened)'!$F$57/22500 | F56: =0.38903+0.161031*'Ranking (hardened)'!$F$57/22500 | G56: =0.4042+0.160128*'Ranking (hardened)'!$F$57/22500 | H56: =0.42862+0.165237*'Ranking (hardened)'!$F$57/22500 | I56: =0.44487+0.178015*'Ranking (hardened)'!$F$57/22500 | J56: =0.44553+0.222717*'Ranking (hardened)'!$F$57/22500 | K56: ↓ 10k · ≈2025 | L56: ◆ 85k · ≈2019 · $22,500 | M56: =0.39014+0.160829*'Ranking (hardened)'!$F$57/22500 | N56: 6 | O56: $0.507–$0.605 | P56: $0.364 → $0.059
A57: Mini Countryman | B57: =0.34484+0.169184*'Ranking (hardened)'!$F$58/19000 | C57: =0.35752+0.172347*'Ranking (hardened)'!$F$58/19000 | D57: =0.37959+0.162362*'Ranking (hardened)'!$F$58/19000 | E57: =0.40909+0.155844*'Ranking (hardened)'!$F$58/19000 | F57: =0.42576+0.157068*'Ranking (hardened)'!$F$58/19000 | G57: =0.45889+0.163355*'Ranking (hardened)'!$F$58/19000 | H57: =0.52977+0.174174*'Ranking (hardened)'!$F$58/19000 | I57: =0.45718+0.282913*'Ranking (hardened)'!$F$58/19000 | J57: ▒ | K57: ↓ 10k · ≈2025 | L57: ◆ 55k · ≈2022 · $19,000 | M57: =0.39849+0.157676*'Ranking (hardened)'!$F$58/19000 | N57: 6 | O57: $0.509–$0.628 | P57: $0.231 → $0.040
A58: Toyota Sequoia | B58: =0.34808+0.144678*'Ranking (hardened)'!$F$59/32250 | C58: =0.35716+0.149839*'Ranking (hardened)'!$F$59/32250 | D58: =0.37543+0.153669*'Ranking (hardened)'!$F$59/32250 | E58: =0.39138+0.149813*'Ranking (hardened)'!$F$59/32250 | F58: =0.41071+0.146391*'Ranking (hardened)'!$F$59/32250 | G58: =0.43185+0.143535*'Ranking (hardened)'!$F$59/32250 | H58: =0.45371+0.141431*'Ranking (hardened)'!$F$59/32250 | I58: =0.48673+0.139721*'Ranking (hardened)'!$F$59/32250 | J58: =0.52083+0.143392*'Ranking (hardened)'!$F$59/32250 | K58: ↓ 10k · ≈2025 | L58: ◆ 80k · ≈2020 · $32,250 | M58: =0.41071+0.146391*'Ranking (hardened)'!$F$59/32250 | N58: 6 | O58: $0.508–$0.613 | P58: $0.511 → $0.125
A59: Hyundai Palisade | B59: =0.33587+0.189274*'Ranking (hardened)'!$F$60/31000 | C59: =0.34282+0.199778*'Ranking (hardened)'!$F$60/31000 | D59: =0.36074+0.19975*'Ranking (hardened)'!$F$60/31000 | E59: =0.38628+0.199715*'Ranking (hardened)'!$F$60/31000 | F59: =0.42134+0.205214*'Ranking (hardened)'!$F$60/31000 | G59: ▒ | H59: ▒ | I59: ▒ | J59: ▒ | K59: ↓ 10k · ≈2025 | L59: ◆ 45k · ≈2023 · $31,000 | M59: =0.36693+0.199742*'Ranking (hardened)'!$F$60/31000 | N59: 6 | O59: $0.523–$0.617 | P59: $0.320 → $0.178
A60: Chrysler Pacifica | B60: =0.34308+0.181269*'Ranking (hardened)'!$F$61/16333 | C60: =0.35491+0.192926*'Ranking (hardened)'!$F$61/16333 | D60: =0.37393+0.17417*'Ranking (hardened)'!$F$61/16333 | E60: =0.39917+0.164502*'Ranking (hardened)'!$F$61/16333 | F60: =0.41405+0.164049*'Ranking (hardened)'!$F$61/16333 | G60: =0.50843+0.172185*'Ranking (hardened)'!$F$61/16333 | H60: =0.54085+0.198198*'Ranking (hardened)'!$F$61/16333 | I60: ▒ | J60: ▒ | K60: ↓ 10k · ≈2025 | L60: ◆ 75k · ≈2020 · $16,333 | M60: =0.41072+0.162521*'Ranking (hardened)'!$F$61/16333 | N60: 6 | O60: $0.527–$0.652 | P60: $0.248 → $0.066
A61: Chevy Colorado | B61: =0.36592+0.194473*'Ranking (hardened)'!$F$62/23500 | C61: =0.37544+0.18069*'Ranking (hardened)'!$F$62/23500 | D61: =0.3944+0.15921*'Ranking (hardened)'!$F$62/23500 | E61: =0.41287+0.161623*'Ranking (hardened)'!$F$62/23500 | F61: =0.43345+0.170122*'Ranking (hardened)'!$F$62/23500 | G61: =0.46363+0.177103*'Ranking (hardened)'!$F$62/23500 | H61: =0.48306+0.187354*'Ranking (hardened)'!$F$62/23500 | I61: ▒ | J61: ▒ | K61: ↓ 40k · ≈2023 | L61: ◆ 60k · ≈2021 · $23,500 | M61: =0.41287+0.161623*'Ranking (hardened)'!$F$62/23500 | N61: 6 | O61: $0.535–$0.627 | P61: $0.343 → $0.105
A62: Kia Telluride | B62: =0.3327+0.19979*'Ranking (hardened)'!$F$63/33000 | C62: =0.33925+0.210877*'Ranking (hardened)'!$F$63/33000 | D62: =0.35619+0.212235*'Ranking (hardened)'!$F$63/33000 | E62: =0.41703+0.21398*'Ranking (hardened)'!$F$63/33000 | F62: =0.43976+0.221852*'Ranking (hardened)'!$F$63/33000 | G62: ▒ | H62: ▒ | I62: ▒ | J62: ▒ | K62: ↓ 10k · ≈2025 | L62: ◆ 45k · ≈2023 · $33,000 | M62: =0.36209+0.212629*'Ranking (hardened)'!$F$63/33000 | N62: 6 | O62: $0.530–$0.624 | P62: $0.338 → $0.193
A63: Mazda CX-90 | B63: =0.32207+0.236593*'Ranking (hardened)'!$F$64/38750 | C63: =0.3445+0.231225*'Ranking (hardened)'!$F$64/38750 | D63: ▒ | E63: ▒ | F63: ▒ | G63: ▒ | H63: ▒ | I63: ▒ | J63: ▒ | K63: ↓ 10k · ≈2025 | L63: ◆ 30k · ≈2024 · $38,750 | M63: =0.35551+0.227673*'Ranking (hardened)'!$F$64/38750 | N63: 6 | O63: $0.535–$0.632 | P63: $0.400 → $0.359
A64: Chevy Traverse | B64: =0.35043+0.183276*'Ranking (hardened)'!$F$65/20000 | C64: =0.36216+0.194411*'Ranking (hardened)'!$F$65/20000 | D64: =0.38176+0.182573*'Ranking (hardened)'!$F$65/20000 | E64: =0.40157+0.176565*'Ranking (hardened)'!$F$65/20000 | F64: =0.42227+0.178458*'Ranking (hardened)'!$F$65/20000 | G64: =0.47958+0.189125*'Ranking (hardened)'!$F$65/20000 | H64: ▒ | I64: ▒ | J64: ▒ | K64: ↓ 10k · ≈2025 | L64: ◆ 70k · ≈2021 · $20,000 | M64: =0.41459+0.17452*'Ranking (hardened)'!$F$65/20000 | N64: 6 | O64: $0.538–$0.659 | P64: $0.271 → $0.105
A65: VW Atlas | B65: =0.36242+0.177976*'Ranking (hardened)'!$F$66/21000 | C65: =0.37496+0.188457*'Ranking (hardened)'!$F$66/21000 | D65: =0.39267+0.176235*'Ranking (hardened)'!$F$66/21000 | E65: =0.41951+0.169492*'Ranking (hardened)'!$F$66/21000 | F65: =0.45072+0.16697*'Ranking (hardened)'!$F$66/21000 | G65: =0.50552+0.167038*'Ranking (hardened)'!$F$66/21000 | H65: ▒ | I65: ▒ | J65: ▒ | K65: ↓ 10k · ≈2025 | L65: ◆ 65k · ≈2021 · $21,000 | M65: =0.42487+0.168269*'Ranking (hardened)'!$F$66/21000 | N65: 6 | O65: $0.543–$0.656 | P65: $0.276 → $0.100
A66: Ford Explorer | B66: =0.35105+0.189003*'Ranking (hardened)'!$F$67/21000 | C66: =0.36264+0.200486*'Ranking (hardened)'!$F$67/21000 | D66: =0.38186+0.189488*'Ranking (hardened)'!$F$67/21000 | E66: =0.40112+0.184591*'Ranking (hardened)'!$F$67/21000 | F66: =0.44564+0.184831*'Ranking (hardened)'!$F$67/21000 | G66: =0.44597+0.189125*'Ranking (hardened)'!$F$67/21000 | H66: =0.47288+0.206398*'Ranking (hardened)'!$F$67/21000 | I66: =0.4419+0.297275*'Ranking (hardened)'!$F$67/21000 | J66: ▒ | K66: ↓ 10k · ≈2025 | L66: ◆ 70k · ≈2021 · $21,000 | M66: =0.41377+0.183246*'Ranking (hardened)'!$F$67/21000 | N66: 6 | O66: $0.542–$0.667 | P66: $0.280 → $0.059
A67: Buick Enclave | B67: =0.35258+0.194731*'Ranking (hardened)'!$F$68/16667 | C67: =0.36378+0.206561*'Ranking (hardened)'!$F$68/16667 | D67: =0.3827+0.190871*'Ranking (hardened)'!$F$68/16667 | E67: =0.40087+0.179775*'Ranking (hardened)'!$F$68/16667 | F67: =0.42048+0.175271*'Ranking (hardened)'!$F$68/16667 | G67: =0.46973+0.177305*'Ranking (hardened)'!$F$68/16667 | H67: =0.46966+0.190918*'Ranking (hardened)'!$F$68/16667 | I67: =0.45515+0.260116*'Ranking (hardened)'!$F$68/16667 | J67: ▒ | K67: ↓ 10k · ≈2025 | L67: ◆ 90k · ≈2019 · $16,667 | M67: =0.43191+0.17618*'Ranking (hardened)'!$F$68/16667 | N67: 7 | O67: $0.553–$0.684 | P67: $0.288 → $0.051
A68: Volvo XC60 | B68: =0.37026+0.19979*'Ranking (hardened)'!$F$69/25200 | C68: =0.38396+0.210877*'Ranking (hardened)'!$F$69/25200 | D68: =0.40841+0.197253*'Ranking (hardened)'!$F$69/25200 | E68: =0.43144+0.188302*'Ranking (hardened)'!$F$69/25200 | F68: =0.45851+0.183028*'Ranking (hardened)'!$F$69/25200 | G68: =0.52907+0.179641*'Ranking (hardened)'!$F$69/25200 | H68: ▒ | I68: ▒ | J68: ▒ | K68: ↓ 10k · ≈2025 | L68: ◆ 65k · ≈2021 · $25,200 | M68: =0.43731+0.186391*'Ranking (hardened)'!$F$69/25200 | N68: 7 | O68: $0.566–$0.690 | P68: $0.338 → $0.123
A69: Chevy Tahoe | B69: =0.37545+0.195228*'Ranking (hardened)'!$F$70/39375 | C69: =0.38641+0.204082*'Ranking (hardened)'!$F$70/39375 | D69: =0.40753+0.213217*'Ranking (hardened)'!$F$70/39375 | E69: =0.44547+0.211911*'Ranking (hardened)'!$F$70/39375 | F69: =0.44816+0.211838*'Ranking (hardened)'!$F$70/39375 | G69: =0.47346+0.213523*'Ranking (hardened)'!$F$70/39375 | H69: =0.49754+0.217842*'Ranking (hardened)'!$F$70/39375 | I69: ▒ | J69: ▒ | K69: ↓ 10k · ≈2025 | L69: ◆ 55k · ≈2022 · $39,375 | M69: =0.41958+0.212264*'Ranking (hardened)'!$F$70/39375 | N69: 7 | O69: $0.577–$0.685 | P69: $0.453 → $0.190
A70: Jeep Grand Cherokee L | B70: =0.37211+0.21764*'Ranking (hardened)'!$F$71/28600 | C70: =0.38416+0.230863*'Ranking (hardened)'!$F$71/28600 | D70: =0.39988+0.224066*'Ranking (hardened)'!$F$71/28600 | E70: =0.44592+0.219904*'Ranking (hardened)'!$F$71/28600 | F70: ▒ | G70: ▒ | H70: ▒ | I70: ▒ | J70: ▒ | K70: ↓ 10k · ≈2025 | L70: ◆ 55k · ≈2022 · $28,600 | M70: =0.41599+0.220679*'Ranking (hardened)'!$F$71/28600 | N70: 7 | O70: $0.591–$0.695 | P70: $0.322 → $0.201
A71: Volvo V90 Cross Country | B71: =0.35872+0.22082*'Ranking (hardened)'!$F$72/29800 | C71: =0.37214+0.233074*'Ranking (hardened)'!$F$72/29800 | D71: =0.39665+0.23221*'Ranking (hardened)'!$F$72/29800 | E71: =0.41867+0.222539*'Ranking (hardened)'!$F$72/29800 | F71: =0.44444+0.21492*'Ranking (hardened)'!$F$72/29800 | G71: =0.48584+0.211244*'Ranking (hardened)'!$F$72/29800 | H71: =0.55033+0.218204*'Ranking (hardened)'!$F$72/29800 | I71: ▒ | J71: ▒ | K71: ↓ 10k · ≈2025 | L71: ◆ 65k · ≈2021 · $29,800 | M71: =0.42427+0.220414*'Ranking (hardened)'!$F$72/29800 | N71: 7 | O71: $0.584–$0.715 | P71: $0.373 → $0.113
A72: Chevy Suburban | B72: =0.37565+0.204778*'Ranking (hardened)'!$F$73/42375 | C72: =0.38655+0.213904*'Ranking (hardened)'!$F$73/42375 | D72: =0.40764+0.223826*'Ranking (hardened)'!$F$73/42375 | E72: =0.44554+0.223698*'Ranking (hardened)'!$F$73/42375 | F72: =0.4481+0.22354*'Ranking (hardened)'!$F$73/42375 | G72: =0.47313+0.223338*'Ranking (hardened)'!$F$73/42375 | H72: =0.49708+0.22709*'Ranking (hardened)'!$F$73/42375 | I72: ▒ | J72: ▒ | K72: ↓ 10k · ≈2025 | L72: ◆ 55k · ≈2022 · $42,375 | M72: =0.41965+0.223733*'Ranking (hardened)'!$F$73/42375 | N72: 7 | O72: $0.589–$0.701 | P72: $0.489 → $0.207
A73: Volvo XC90 | B73: =0.38946+0.259459*'Ranking (hardened)'!$F$74/30000 | C73: =0.40441+0.274286*'Ranking (hardened)'!$F$74/30000 | D73: =0.4297+0.258065*'Ranking (hardened)'!$F$74/30000 | E73: =0.45476+0.245926*'Ranking (hardened)'!$F$74/30000 | F73: =0.48303+0.237681*'Ranking (hardened)'!$F$74/30000 | G73: =0.53157+0.231579*'Ranking (hardened)'!$F$74/30000 | H73: =0.60595+0.24*'Ranking (hardened)'!$F$74/30000 | I73: ▒ | J73: ▒ | K73: ↓ 10k · ≈2025 | L73: ◆ 70k · ≈2021 · $30,000 | M73: =0.47191+0.24*'Ranking (hardened)'!$F$74/30000 | N73: 8 | O73: $0.635–$0.811 | P73: $0.420 → $0.115
A75: HOW TO READ IT: each column is an odometer AND its ≈ model year (top two header rows) — e.g. 60k mi ≈ a 2021 at 13k mi/yr. Read along any row; click any $/mile cell to open the cars.com listings behind that price. THE BOLD cell in each row = the buy PICK (◆) — the SAME odometer→year shown on the Ranking tab. WHY THE BOLD CELL IS NOT THE GREENEST — and it is NOT because of opportunity cost: the 7% market opportunity cost is ALREADY inside every $/mile number here (via discounting). Even so, the $/mile curve still rises with odometer, so the cheapest-per-mile cell is ALWAYS the newest ("Lowest $/mi ↓"). The gap between the newest and the ◆ pick is only ~1-2¢/mile — what remains AFTER opportunity cost is charged — and that is inside the Monte-Carlo noise band, so these buy points are a STATISTICAL TIE on cost. Given the tie, the ◆ pick simply takes the option that needs the LEAST CASH up front (a few thousand dollars less), which a real buyer usually prefers. So: "↓ Lowest $/mi" = cheapest per mile (newest, most cash); "◆ Buy pick" = least cash among cost-ties (a bit older). Both shown on purpose — pick whichever fits your budget. LIVE UPDATES: every cell is a formula tied to that car's editable Purchase $ on the Ranking tab, so correcting a price rescales the whole row and recolors it. Grey ▒ = a year before the model existed. NOTE on the openpilot column (Ranking tab): that is the range of model YEARS openpilot/comma.ai supports for the car — a compatibility range, separate from the cost recommendation. It now checks the CURRENT recommended buy year automatically: "✓" = the recommended buy is openpilot-compatible; "OUTSIDE range" = it is not (e.g. a 2023 Prius is newer than openpilot's 2016–22 support), and it tells you which years would be. Cost and openpilot-compatibility can point at different model years — decide which matters more to you.

Sheet Ranking (hardened)
A1: LAYER 2 — RANKINGS. Drive-to-death cost per mile (P50 median), discounted at the market opportunity-cost rate (default 7% real S&P; ADJUSTABLE in the yellow "Opp-cost rate" cell — the last two columns re-price and re-rank live at your rate). Right-side columns show the STATISTICAL TIE TIER (cars in the same tier are not distinguishable), the 90% outcome band, the probability this car beats the next-ranked one, and the lifetime market growth you forgo by tying cash in the car. The far-right "v1 $/mi (old)" is the pre-audit model. Edit yellow gas/electricity + per-car Purchase $ to re-rank live.
B3: INPUTS → | C3: Gas $/gal | D3: 5.455 | E3: Electricity $/kWh | F3: 0.32 | H3: Presets: CA $5.455/$0.320 • US avg $3.86/$0.177 • cheap state $3.00/$0.120 • home-EV ~$0.11. N=1,100 Monte-Carlo draws; discount 7% real (S&P opportunity cost); EOL "maintained" (iSeeCars ×1.30). INSURANCE = USAA active-duty (~×0.8 of standard) + FLORIDA registration (home of record), not CA — see Method tab. | Q3: 0.07 | R3: (3–12% real; 7%=S&P long-run. Cols W,X = "$/mi @ your rate" + "Rank @ your rate", live. A HIGHER rate lowers every $/mi in present-value terms but re-ranks TOWARD cheaper-to-buy cars — watch the Rank column, not the absolute number.)
A5: Rank | B5: Vehicle | C5: Body | D5: Energy | E5: Buy odo → ~yr | F5: Purchase $ (EDIT ↓) | G5: TOTAL $/mi (P50) | H5: $/mi P75 | I5: $/mi P90 (bad luck) | J5: $/mi if EOL=empirical | K5: Energy $/mi | L5: Non-energy $/mi | M5: Insur. $/yr | N5: Verify — live listing (click) | O5: openpilot supported YEARS (comma.ai) | P5: v1 $/mi (old model) | Q5: Stat. tier | R5: 90% band low | S5: 90% band high | T5: Beats next rank (P) | U5: Capital opp cost $/mi | V5: Foregone mkt growth (life $) | W5: $/mi @ your rate | X5: Rank @ your rate
A6: 1 | B6: Chevy Bolt EV | C6: EV | D6: electric | E6: 45k mi → ~2023 | F6: 15643 | G6: =0.2429+(F6-15643)/155200+0.0*$D$3+0.22608*$F$3 | H6: =0.2701+(F6-15643)/155200+0.0*$D$3+0.22608*$F$3 | I6: =0.2992+(F6-15643)/155200+0.0*$D$3+0.22608*$F$3 | J6: =0.2626+(F6-15643)/109000+0.0*$D$3+0.22608*$F$3 | K6: =0.0*$D$3+0.22608*$F$3 | L6: =G6-K6 | M6: 1660 | N6: live listings ~45k mi, $13,000-$17,500 | O6: ✓ supported 2022–23 (buy ~2023 ✓) | P6: 0.338 | Q6: 1 | R6: 0.289 | S6: 0.389 | T6: 0.688 | U6: 0.125 | V6: 19441 | W6: =IFERROR(G6*INDEX('Charts data (helper)'!$BI$119:$DZ$128,MATCH($Q$3,'Charts data (helper)'!$BH$119:$BH$128,0),MATCH($B6,'Charts data (helper)'!$BI$118:$DZ$118,0))/INDEX('Charts data (helper)'!$BI$119:$DZ$128,MATCH(0.07,'Charts data (helper)'!$BH$119:$BH$128,0),MATCH($B6,'Charts data (helper)'!$BI$118:$DZ$118,0)),G6) | X6: =RANK(W6,$W$6:$W$76,1)
A7: 2 | B7: Chevy Volt | C7: PHEV | D7: plug-in | E7: 55k mi → ~2019 | F7: 15143 | G7: =0.2552+(F7-15143)/145200+0.00334*$D$3+0.19367*$F$3 | H7: =0.2731+(F7-15143)/145200+0.00334*$D$3+0.19367*$F$3 | I7: =0.2902+(F7-15143)/145200+0.00334*$D$3+0.19367*$F$3 | J7: =0.2787+(F7-15143)/99000+0.00334*$D$3+0.19367*$F$3 | K7: =0.00334*$D$3+0.19367*$F$3 | L7: =G7-K7 | M7: 1440 | N7: live listings ~55k mi, $12,500-$17,000 | O7: ✗ not on current list | P7: 0.35 | Q7: 1 | R7: 0.307 | S7: 0.385 | T7: 0.697 | U7: 0.118 | V7: 17098 | W7: =IFERROR(G7*INDEX('Charts data (helper)'!$BI$119:$DZ$128,MATCH($Q$3,'Charts data (helper)'!$BH$119:$BH$128,0),MATCH($B7,'Charts data (helper)'!$BI$118:$DZ$118,0))/INDEX('Charts data (helper)'!$BI$119:$DZ$128,MATCH(0.07,'Charts data (helper)'!$BH$119:$BH$128,0),MATCH($B7,'Charts data (helper)'!$BI$118:$DZ$118,0)),G7) | X7: =RANK(W7,$W$6:$W$76,1)
A8: 3 | B8: Toyota Prius (hybrid) | C8: Car | D8: hybrid | E8: 40k mi → ~2023 | F8: 26000 | G8: =0.2866+(F8-26000)/209600+0.01217*$D$3+0.0*$F$3 | H8: =0.2995+(F8-26000)/209600+0.01217*$D$3+0.0*$F$3 | I8: =0.312+(F8-26000)/209600+0.01217*$D$3+0.0*$F$3 | J8: =0.3239+(F8-26000)/152000+0.01217*$D$3+0.0*$F$3 | K8: =0.01217*$D$3+0.0*$F$3 | L8: =G8-K8 | M8: 1800 | N8: live listings ~40k mi, $22,000-$29,500 | O8: ◑ supported 2016–22 (buy ~2023 OUTSIDE range — pick a 2016-2022 example instead) | P8: 0.348 | Q8: 1 | R8: 0.321 | S8: 0.387 | T8: 0.65 | U8: 0.245 | V8: 51398 | W8: =IFERROR(G8*INDEX('Charts data (helper)'!$BI$119:$DZ$128,MATCH($Q$3,'Charts data (helper)'!$BH$119:$BH$128,0),MATCH($B8,'Charts data (helper)'!$BI$118:$DZ$118,0))/INDEX('Charts data (helper)'!$BI$119:$DZ$128,MATCH(0.07,'Charts data (helper)'!$BH$119:$BH$128,0),MATCH($B8,'Charts data (helper)'!$BI$118:$DZ$118,0)),G8) | X8: =RANK(W8,$W$6:$W$76,1)
A9: 4 | B9: Toyota Prius Prime | C9: PHEV | D9: plug-in | E9: 90k mi → ~2019 | F9: 15000 | G9: =0.298+(F9-15000)/145300+0.00585*$D$3+0.10735*$F$3 | H9: =0.3161+(F9-15000)/145300+0.00585*$D$3+0.10735*$F$3 | I9: =0.3355+(F9-15000)/145300+0.00585*$D$3+0.10735*$F$3 | J9: =0.3358+(F9-15000)/91000+0.00585*$D$3+0.10735*$F$3 | K9: =0.00585*$D$3+0.10735*$F$3 | L9: =G9-K9 | M9: 1920 | N9: live listings ~90k mi, $12,500-$17,000 | O9: ✓ supported 2017–22 (buy ~2019 ✓) | P9: 0.37 | Q9: 2 | R9: 0.33 | S9: 0.415 | T9: 0.549 | U9: 0.117 | V9: 16953 | W9: =IFERROR(G9*INDEX('Charts data (helper)'!$BI$119:$DZ$128,MATCH($Q$3,'Charts data (helper)'!$BH$119:$BH$128,0),MATCH($B9,'Charts data (helper)'!$BI$118:$DZ$118,0))/INDEX('Charts data (helper)'!$BI$119:$DZ$128,MATCH(0.07,'Charts data (helper)'!$BH$119:$BH$128,0),MATCH($B9,'Charts data (helper)'!$BI$118:$DZ$118,0)),G9) | X9: =RANK(W9,$W$6:$W$76,1)
A10: 5 | B10: Toyota Corolla | C10: Car | D10: gas | E10: 55k mi → ~2022 | F10: 17659 | G10: =0.2577+(F10-17659)/194600+0.02028*$D$3+0.0*$F$3 | H10: =0.2706+(F10-17659)/194600+0.02028*$D$3+0.0*$F$3 | I10: =0.2823+(F10-17659)/194600+0.02028*$D$3+0.0*$F$3 | J10: =0.2866+(F10-17659)/137000+0.02028*$D$3+0.0*$F$3 | K10: =0.02028*$D$3+0.0*$F$3 | L10: =G10-K10 | M10: 1920 | N10: live listings ~55k mi, $15,000-$20,000 | O10: ✓ supported 2017–22 (buy ~2022 ✓) | P10: 0.364 | Q10: 2 | R10: 0.339 | S10: 0.402 | T10: 0.502 | U10: 0.159 | V10: 30962 | W10: =IFERROR(G10*INDEX('Charts data (helper)'!$BI$119:$DZ$128,MATCH($Q$3,'Charts data (helper)'!$BH$119:$BH$128,0),MATCH($B10,'Charts data (helper)'!$BI$118:$DZ$118,0))/INDEX('Charts data (helper)'!$BI$119:$DZ$128,MATCH(0.07,'Charts data (helper)'!$BH$119:$BH$128,0),MATCH($B10,'Charts data (helper)'!$BI$118:$DZ$118,0)),G10) | X10: =RANK(W10,$W$6:$W$76,1)
A11: 6 | B11: Toyota Camry Hybrid | C11: Car | D11: hybrid | E11: 80k mi → ~2020 | F11: 16500 | G11: =0.2821+(F11-16500)/169600+0.01581*$D$3+0.0*$F$3 | H11: =0.2974+(F11-16500)/169600+0.01581*$D$3+0.0*$F$3 | I11: =0.3139+(F11-16500)/169600+0.01581*$D$3+0.0*$F$3 | J11: =0.3156+(F11-16500)/112000+0.01581*$D$3+0.0*$F$3 | K11: =0.01581*$D$3+0.0*$F$3 | L11: =G11-K11 | M11: 1920 | N11: live listings ~80k mi, $14,000-$18,500 | O11: ✓ supported 2018–24 (buy ~2020 ✓) | P11: 0.367 | Q11: 2 | R11: 0.335 | S11: 0.411 | T11: 0.711 | U11: 0.138 | V11: 23387 | W11: =IFERROR(G11*INDEX('Charts data (helper)'!$BI$119:$DZ$128,MATCH($Q$3,'Charts data (helper)'!$BH$119:$BH$128,0),MATCH($B11,'Charts data (helper)'!$BI$118:$DZ$118,0))/INDEX('Charts data (helper)'!$BI$119:$DZ$128,MATCH(0.07,'Charts data (helper)'!$BH$119:$BH$128,0),MATCH($B11,'Charts data (helper)'!$BI$118:$DZ$118,0)),G11) | X11: =RANK(W11,$W$6:$W$76,1)
A12: 7 | B12: Honda Civic | C12: Car | D12: gas | E12: 35k mi → ~2023 | F12: 23789 | G12: =0.2792+(F12-23789)/200300+0.0194*$D$3+0.0*$F$3 | H12: =0.2907+(F12-23789)/200300+0.0194*$D$3+0.0*$F$3 | I12: =0.3028+(F12-23789)/200300+0.0194*$D$3+0.0*$F$3 | J12: =0.314+(F12-23789)/146000+0.0194*$D$3+0.0*$F$3 | K12: =0.0194*$D$3+0.0*$F$3 | L12: =G12-K12 | M12: 1840 | N12: live listings ~35k mi, $20,000-$27,000 | O12: ✓ supported 2016–24 (buy ~2023 ✓) | P12: 0.38 | Q12: 2 | R12: 0.357 | S12: 0.417 | T12: 0.506 | U12: 0.218 | V12: 43682 | W12: =IFERROR(G12*INDEX('Charts data (helper)'!$BI$119:$DZ$128,MATCH($Q$3,'Charts data (helper)'!$BH$119:$BH$128,0),MATCH($B12,'Charts data (helper)'!$BI$118:$DZ$118,0))/INDEX('Charts data (helper)'!$BI$119:$DZ$128,MATCH(0.07,'Charts data (helper)'!$BH$119:$BH$128,0),MATCH($B12,'Charts data (helper)'!$BI$118:$DZ$118,0)),G12) | X12: =RANK(W12,$W$6:$W$76,1)
A13: 8 | B13: Nissan Leaf | C13: EV | D13: electric | E13: 45k mi → ~2023 | F13: 11667 | G13: =0.2967+(F13-11667)/95400+0.0*$D$3+0.27831*$F$3 | H13: =0.3333+(F13-11667)/95400+0.0*$D$3+0.27831*$F$3 | I13: =0.364+(F13-11667)/95400+0.0*$D$3+0.27831*$F$3 | J13: =0.3304+(F13-11667)/63000+0.0*$D$3+0.27831*$F$3 | K13: =0.0*$D$3+0.27831*$F$3 | L13: =G13-K13 | M13: 1760 | N13: live listings ~45k mi, $9,500-$13,000 | O13: ✓ supported 2018–23 (buy ~2023 ✓) | P13: 0.419 | Q13: 2 | R13: 0.339 | S13: 0.473 | T13: 0.537 | U13: 0.079 | V13: 7501 | W13: =IFERROR(G13*INDEX('Charts data (helper)'!$BI$119:$DZ$128,MATCH($Q$3,'Charts data (helper)'!$BH$119:$BH$128,0),MATCH($B13,'Charts data (helper)'!$BI$118:$DZ$118,0))/INDEX('Charts data (helper)'!$BI$119:$DZ$128,MATCH(0.07,'Charts data (helper)'!$BH$119:$BH$128,0),MATCH($B13,'Charts data (helper)'!$BI$118:$DZ$118,0)),G13) | X13: =RANK(W13,$W$6:$W$76,1)
A14: 9 | B14: Hyundai Elantra | C14: Car | D14: gas | E14: 45k mi → ~2023 | F14: 16000 | G14: =0.2829+(F14-16000)/155200+0.0196*$D$3+0.0*$F$3 | H14: =0.2992+(F14-16000)/155200+0.0196*$D$3+0.0*$F$3 | I14: =0.3156+(F14-16000)/155200+0.0196*$D$3+0.0*$F$3 | J14: =0.3125+(F14-16000)/109000+0.0196*$D$3+0.0*$F$3 | K14: =0.0196*$D$3+0.0*$F$3 | L14: =G14-K14 | M14: 1640 | N14: live listings ~45k mi, $13,500-$18,000 | O14: ◑ Hyundai/Kia SCC, select yrs | P14: 0.385 | Q14: 2 | R14: 0.357 | S14: 0.432 | T14: 0.477 | U14: 0.128 | V14: 19885 | W14: =IFERROR(G14*INDEX('Charts data (helper)'!$BI$119:$DZ$128,MATCH($Q$3,'Charts data (helper)'!$BH$119:$BH$128,0),MATCH($B14,'Charts data (helper)'!$BI$118:$DZ$118,0))/INDEX('Charts data (helper)'!$BI$119:$DZ$128,MATCH(0.07,'Charts data (helper)'!$BH$119:$BH$128,0),MATCH($B14,'Charts data (helper)'!$BI$118:$DZ$118,0)),G14) | X14: =RANK(W14,$W$6:$W$76,1)
A15: 10 | B15: Honda Accord | C15: Car | D15: gas | E15: 70k mi → ~2021 | F15: 16143 | G15: =0.2732+(F15-16143)/170500+0.02138*$D$3+0.0*$F$3 | H15: =0.2871+(F15-16143)/170500+0.02138*$D$3+0.0*$F$3 | I15: =0.3001+(F15-16143)/170500+0.02138*$D$3+0.0*$F$3 | J15: =0.3044+(F15-16143)/115000+0.02138*$D$3+0.0*$F$3 | K15: =0.02138*$D$3+0.0*$F$3 | L15: =G15-K15 | M15: 1840 | N15: live listings ~70k mi, $13,500-$18,500 | O15: ✓ supported 2018–25 (buy ~2021 ✓) | P15: 0.386 | Q15: 2 | R15: 0.355 | S15: 0.425 | T15: 0.613 | U15: 0.135 | V15: 23064 | W15: =IFERROR(G15*INDEX('Charts data (helper)'!$BI$119:$DZ$128,MATCH($Q$3,'Charts data (helper)'!$BH$119:$BH$128,0),MATCH($B15,'Charts data (helper)'!$BI$118:$DZ$118,0))/INDEX('Charts data (helper)'!$BI$119:$DZ$128,MATCH(0.07,'Charts data (helper)'!$BH$119:$BH$128,0),MATCH($B15,'Charts data (helper)'!$BI$118:$DZ$118,0)),G15) | X15: =RANK(W15,$W$6:$W$76,1)
A16: 11 | B16: Kia K4 | C16: Car | D16: gas | E16: 18k mi → ~2025 | F16: 20125 | G16: =0.2898+(F16-20125)/171800+0.01944*$D$3+0.0*$F$3 | H16: =0.3041+(F16-20125)/171800+0.01944*$D$3+0.0*$F$3 | I16: =0.319+(F16-20125)/171800+0.01944*$D$3+0.0*$F$3 | J16: =0.3175+(F16-20125)/128000+0.01944*$D$3+0.0*$F$3 | K16: =0.01944*$D$3+0.0*$F$3 | L16: =G16-K16 | M16: 1640 | N16: live listings ~18k mi, $17,000-$23,000 | O16: ✗ too new — not yet on the comma/openpilot list | P16: 0.391 | Q16: 2 | R16: 0.369 | S16: 0.436 | T16: 0.501 | U16: 0.169 | V16: 29085 | W16: =IFERROR(G16*INDEX('Charts data (helper)'!$BI$119:$DZ$128,MATCH($Q$3,'Charts data (helper)'!$BH$119:$BH$128,0),MATCH($B16,'Charts data (helper)'!$BI$118:$DZ$118,0))/INDEX('Charts data (helper)'!$BI$119:$DZ$128,MATCH(0.07,'Charts data (helper)'!$BH$119:$BH$128,0),MATCH($B16,'Charts data (helper)'!$BI$118:$DZ$118,0)),G16) | X16: =RANK(W16,$W$6:$W$76,1)
A17: 12 | B17: Mazda3 (SkyActiv) | C17: Car | D17: gas | E17: 65k mi → ~2021 | F17: 15000 | G17: =0.2687+(F17-15000)/145600+0.02337*$D$3+0.0*$F$3 | H17: =0.2869+(F17-15000)/145600+0.02337*$D$3+0.0*$F$3 | I17: =0.3042+(F17-15000)/145600+0.02337*$D$3+0.0*$F$3 | J17: =0.3131+(F17-15000)/97000+0.02337*$D$3+0.0*$F$3 | K17: =0.02337*$D$3+0.0*$F$3 | L17: =G17-K17 | M17: 1720 | N17: live listings ~65k mi, $12,500-$17,000 | O17: ✗ not on list (only CX-5/CX-9) | P17: 0.395 | Q17: 2 | R17: 0.364 | S17: 0.441 | T17: 0.494 | U17: 0.117 | V17: 17003 | W17: =IFERROR(G17*INDEX('Charts data (helper)'!$BI$119:$DZ$128,MATCH($Q$3,'Charts data (helper)'!$BH$119:$BH$128,0),MATCH($B17,'Charts data (helper)'!$BI$118:$DZ$118,0))/INDEX('Charts data (helper)'!$BI$119:$DZ$128,MATCH(0.07,'Charts data (helper)'!$BH$119:$BH$128,0),MATCH($B17,'Charts data (helper)'!$BI$118:$DZ$118,0)),G17) | X17: =RANK(W17,$W$6:$W$76,1)
A18: 13 | B18: Toyota Camry | C18: Car | D18: gas | E18: 55k mi → ~2022 | F18: 22400 | G18: =0.284+(F18-22400)/199800+0.02072*$D$3+0.0*$F$3 | H18: =0.2974+(F18-22400)/199800+0.02072*$D$3+0.0*$F$3 | I18: =0.3114+(F18-22400)/199800+0.02072*$D$3+0.0*$F$3 | J18: =0.322+(F18-22400)/141000+0.02072*$D$3+0.0*$F$3 | K18: =0.02072*$D$3+0.0*$F$3 | L18: =G18-K18 | M18: 1840 | N18: live listings ~55k mi, $19,000-$25,500 | O18: ✓ supported 2018–24 (buy ~2022 ✓) | P18: 0.388 | Q18: 2 | R18: 0.363 | S18: 0.436 | T18: 0.514 | U18: 0.205 | V18: 40966 | W18: =IFERROR(G18*INDEX('Charts data (helper)'!$BI$119:$DZ$128,MATCH($Q$3,'Charts data (helper)'!$BH$119:$BH$128,0),MATCH($B18,'Charts data (helper)'!$BI$118:$DZ$118,0))/INDEX('Charts data (helper)'!$BI$119:$DZ$128,MATCH(0.07,'Charts data (helper)'!$BH$119:$BH$128,0),MATCH($B18,'Charts data (helper)'!$BI$118:$DZ$118,0)),G18) | X18: =RANK(W18,$W$6:$W$76,1)
A19: 14 | B19: Toyota RAV4 Hybrid | C19: SUV AWD | D19: hybrid | E19: 40k mi → ~2023 | F19: 30444 | G19: =0.3143+(F19-30444)/204400+0.01539*$D$3+0.0*$F$3 | H19: =0.3306+(F19-30444)/204400+0.01539*$D$3+0.0*$F$3 | I19: =0.3438+(F19-30444)/204400+0.01539*$D$3+0.0*$F$3 | J19: =0.3546+(F19-30444)/148000+0.01539*$D$3+0.0*$F$3 | K19: =0.01539*$D$3+0.0*$F$3 | L19: =G19-K19 | M19: 1800 | N19: live listings ~40k mi, $25,500-$35,000 | O19: ✓ supported 2016–25 (buy ~2023 ✓) | P19: 0.395 | Q19: 2 | R19: 0.359 | S19: 0.437 | T19: 0.562 | U19: 0.283 | V19: 57764 | W19: =IFERROR(G19*INDEX('Charts data (helper)'!$BI$119:$DZ$128,MATCH($Q$3,'Charts data (helper)'!$BH$119:$BH$128,0),MATCH($B19,'Charts data (helper)'!$BI$118:$DZ$118,0))/INDEX('Charts data (helper)'!$BI$119:$DZ$128,MATCH(0.07,'Charts data (helper)'!$BH$119:$BH$128,0),MATCH($B19,'Charts data (helper)'!$BI$118:$DZ$118,0)),G19) | X19: =RANK(W19,$W$6:$W$76,1)
A20: 15 | B20: Kia Niro (hybrid) | C20: SUV | D20: hybrid | E20: 65k mi → ~2021 | F20: 17000 | G20: =0.3229+(F20-17000)/140400+0.01448*$D$3+0.0*$F$3 | H20: =0.3431+(F20-17000)/140400+0.01448*$D$3+0.0*$F$3 | I20: =0.3637+(F20-17000)/140400+0.01448*$D$3+0.0*$F$3 | J20: =0.3588+(F20-17000)/93000+0.01448*$D$3+0.0*$F$3 | K20: =0.01448*$D$3+0.0*$F$3 | L20: =G20-K20 | M20: 1680 | N20: live listings ~65k mi, $14,000-$19,500 | O20: ◑ Hyundai/Kia SCC, select yrs | P20: 0.399 | Q20: 3 | R20: 0.367 | S20: 0.46 | T20: 0.594 | U20: 0.13 | V20: 18302 | W20: =IFERROR(G20*INDEX('Charts data (helper)'!$BI$119:$DZ$128,MATCH($Q$3,'Charts data (helper)'!$BH$119:$BH$128,0),MATCH($B20,'Charts data (helper)'!$BI$118:$DZ$118,0))/INDEX('Charts data (helper)'!$BI$119:$DZ$128,MATCH(0.07,'Charts data (helper)'!$BH$119:$BH$128,0),MATCH($B20,'Charts data (helper)'!$BI$118:$DZ$118,0)),G20) | X20: =RANK(W20,$W$6:$W$76,1)
A21: 16 | B21: Tesla Model 3 | C21: EV | D21: electric | E21: 60k mi → ~2021 | F21: 21500 | G21: =0.3531+(F21-21500)/170100+0.0*$D$3+0.18743*$F$3 | H21: =0.3827+(F21-21500)/170100+0.0*$D$3+0.18743*$F$3 | I21: =0.417+(F21-21500)/170100+0.0*$D$3+0.18743*$F$3 | J21: =0.3883+(F21-21500)/117000+0.0*$D$3+0.18743*$F$3 | K21: =0.0*$D$3+0.18743*$F$3 | L21: =G21-K21 | M21: 2480 | N21: live listings ~60k mi, $18,000-$24,500 | O21: ✓ supported 2019–25 (buy ~2021 ✓) | P21: 0.416 | Q21: 3 | R21: 0.367 | S21: 0.503 | T21: 0.575 | U21: 0.18 | V21: 30609 | W21: =IFERROR(G21*INDEX('Charts data (helper)'!$BI$119:$DZ$128,MATCH($Q$3,'Charts data (helper)'!$BH$119:$BH$128,0),MATCH($B21,'Charts data (helper)'!$BI$118:$DZ$118,0))/INDEX('Charts data (helper)'!$BI$119:$DZ$128,MATCH(0.07,'Charts data (helper)'!$BH$119:$BH$128,0),MATCH($B21,'Charts data (helper)'!$BI$118:$DZ$118,0)),G21) | X21: =RANK(W21,$W$6:$W$76,1)
A22: 17 | B22: Hyundai Sonata | C22: Car | D22: gas | E22: 60k mi → ~2021 | F22: 15333 | G22: =0.2998+(F22-15333)/135000+0.02244*$D$3+0.0*$F$3 | H22: =0.319+(F22-15333)/135000+0.02244*$D$3+0.0*$F$3 | I22: =0.3381+(F22-15333)/135000+0.02244*$D$3+0.0*$F$3 | J22: =0.3359+(F22-15333)/90000+0.02244*$D$3+0.0*$F$3 | K22: =0.02244*$D$3+0.0*$F$3 | L22: =G22-K22 | M22: 1720 | N22: live listings ~60k mi, $13,000-$17,500 | O22: ◑ Hyundai/Kia SCC, select yrs | P22: 0.423 | Q22: 3 | R22: 0.387 | S22: 0.478 | T22: 0.604 | U22: 0.116 | V22: 15625 | W22: =IFERROR(G22*INDEX('Charts data (helper)'!$BI$119:$DZ$128,MATCH($Q$3,'Charts data (helper)'!$BH$119:$BH$128,0),MATCH($B22,'Charts data (helper)'!$BI$118:$DZ$118,0))/INDEX('Charts data (helper)'!$BI$119:$DZ$128,MATCH(0.07,'Charts data (helper)'!$BH$119:$BH$128,0),MATCH($B22,'Charts data (helper)'!$BI$118:$DZ$118,0)),G22) | X22: =RANK(W22,$W$6:$W$76,1)
A23: 18 | B23: Toyota RAV4 | C23: SUV | D23: gas | E23: 80k mi → ~2020 | F23: 20600 | G23: =0.2992+(F23-20600)/160500+0.02421*$D$3+0.0*$F$3 | H23: =0.3152+(F23-20600)/160500+0.02421*$D$3+0.0*$F$3 | I23: =0.3318+(F23-20600)/160500+0.02421*$D$3+0.0*$F$3 | J23: =0.3362+(F23-20600)/105000+0.02421*$D$3+0.0*$F$3 | K23: =0.02421*$D$3+0.0*$F$3 | L23: =G23-K23 | M23: 1720 | N23: live listings ~80k mi, $17,500-$23,500 | O23: ✓ supported 2016–25 (buy ~2020 ✓) | P23: 0.432 | Q23: 3 | R23: 0.396 | S23: 0.477 | T23: 0.564 | U23: 0.168 | V23: 26895 | W23: =IFERROR(G23*INDEX('Charts data (helper)'!$BI$119:$DZ$128,MATCH($Q$3,'Charts data (helper)'!$BH$119:$BH$128,0),MATCH($B23,'Charts data (helper)'!$BI$118:$DZ$118,0))/INDEX('Charts data (helper)'!$BI$119:$DZ$128,MATCH(0.07,'Charts data (helper)'!$BH$119:$BH$128,0),MATCH($B23,'Charts data (helper)'!$BI$118:$DZ$118,0)),G23) | X23: =RANK(W23,$W$6:$W$76,1)
A24: 19 | B24: Fiat 500 | C24: Car | D24: gas | E24: 40k mi → ~2019 | F24: 10200 | G24: =0.3115+(F24-10200)/119900+0.02254*$D$3+0.0*$F$3 | H24: =0.3313+(F24-10200)/119900+0.02254*$D$3+0.0*$F$3 | I24: =0.3598+(F24-10200)/119900+0.02254*$D$3+0.0*$F$3 | J24: =0.3282+(F24-10200)/83000+0.02254*$D$3+0.0*$F$3 | K24: =0.02254*$D$3+0.0*$F$3 | L24: =G24-K24 | M24: 1600 | N24: live listings ~40k mi, $8,500-$11,500 | O24: ✗ not on comma list | P24: 0.435 | Q24: 3 | R24: 0.409 | S24: 0.496 | T24: 0.499 | U24: 0.074 | V24: 8837 | W24: =IFERROR(G24*INDEX('Charts data (helper)'!$BI$119:$DZ$128,MATCH($Q$3,'Charts data (helper)'!$BH$119:$BH$128,0),MATCH($B24,'Charts data (helper)'!$BI$118:$DZ$118,0))/INDEX('Charts data (helper)'!$BI$119:$DZ$128,MATCH(0.07,'Charts data (helper)'!$BH$119:$BH$128,0),MATCH($B24,'Charts data (helper)'!$BI$118:$DZ$118,0)),G24) | X24: =RANK(W24,$W$6:$W$76,1)
A25: 20 | B25: Honda CR-V | C25: SUV | D25: gas | E25: 75k mi → ~2020 | F25: 20500 | G25: =0.3069+(F25-20500)/165500+0.02394*$D$3+0.0*$F$3 | H25: =0.323+(F25-20500)/165500+0.02394*$D$3+0.0*$F$3 | I25: =0.3388+(F25-20500)/165500+0.02394*$D$3+0.0*$F$3 | J25: =0.3421+(F25-20500)/110000+0.02394*$D$3+0.0*$F$3 | K25: =0.02394*$D$3+0.0*$F$3 | L25: =G25-K25 | M25: 1680 | N25: live listings ~75k mi, $17,000-$23,500 | O25: ✓ supported 2015–26 (buy ~2020 ✓) | P25: 0.432 | Q25: 3 | R25: 0.4 | S25: 0.48 | T25: 0.514 | U25: 0.169 | V25: 28010 | W25: =IFERROR(G25*INDEX('Charts data (helper)'!$BI$119:$DZ$128,MATCH($Q$3,'Charts data (helper)'!$BH$119:$BH$128,0),MATCH($B25,'Charts data (helper)'!$BI$118:$DZ$118,0))/INDEX('Charts data (helper)'!$BI$119:$DZ$128,MATCH(0.07,'Charts data (helper)'!$BH$119:$BH$128,0),MATCH($B25,'Charts data (helper)'!$BI$118:$DZ$118,0)),G25) | X25: =RANK(W25,$W$6:$W$76,1)
A26: 21 | B26: VW ID.4 (AWD avail) | C26: EV SUV | D26: electric | E26: 45k mi → ~2023 | F26: 22500 | G26: =0.3487+(F26-22500)/150000+0.0*$D$3+0.27778*$F$3 | H26: =0.3811+(F26-22500)/150000+0.0*$D$3+0.27778*$F$3 | I26: =0.4146+(F26-22500)/150000+0.0*$D$3+0.27778*$F$3 | J26: =0.3755+(F26-22500)/105000+0.0*$D$3+0.27778*$F$3 | K26: =0.0*$D$3+0.27778*$F$3 | L26: =G26-K26 | M26: 1920 | N26: live listings ~45k mi, $19,000-$25,500 | O26: ✗ not on list (no ID.4) | P26: 0.449 | Q26: 3 | R26: 0.389 | S26: 0.529 | T26: 0.513 | U26: 0.177 | V26: 26616 | W26: =IFERROR(G26*INDEX('Charts data (helper)'!$BI$119:$DZ$128,MATCH($Q$3,'Charts data (helper)'!$BH$119:$BH$128,0),MATCH($B26,'Charts data (helper)'!$BI$118:$DZ$118,0))/INDEX('Charts data (helper)'!$BI$119:$DZ$128,MATCH(0.07,'Charts data (helper)'!$BH$119:$BH$128,0),MATCH($B26,'Charts data (helper)'!$BI$118:$DZ$118,0)),G26) | X26: =RANK(W26,$W$6:$W$76,1)
A27: 22 | B27: Toyota RAV4 Prime | C27: PHEV SUV AWD | D27: plug-in | E27: 55k mi → ~2022 | F27: 35000 | G27: =0.3549+(F27-35000)/180300+0.00427*$D$3+0.19491*$F$3 | H27: =0.3716+(F27-35000)/180300+0.00427*$D$3+0.19491*$F$3 | I27: =0.3905+(F27-35000)/180300+0.00427*$D$3+0.19491*$F$3 | J27: =0.4007+(F27-35000)/126000+0.00427*$D$3+0.19491*$F$3 | K27: =0.00427*$D$3+0.19491*$F$3 | L27: =G27-K27 | M27: 1760 | N27: live listings ~55k mi, $29,500-$40,000 | O27: ✗ not listed (RAV4 Prime absent) | P27: 0.45 | Q27: 3 | R27: 0.402 | S27: 0.484 | T27: 0.499 | U27: 0.302 | V27: 54454 | W27: =IFERROR(G27*INDEX('Charts data (helper)'!$BI$119:$DZ$128,MATCH($Q$3,'Charts data (helper)'!$BH$119:$BH$128,0),MATCH($B27,'Charts data (helper)'!$BI$118:$DZ$118,0))/INDEX('Charts data (helper)'!$BI$119:$DZ$128,MATCH(0.07,'Charts data (helper)'!$BH$119:$BH$128,0),MATCH($B27,'Charts data (helper)'!$BI$118:$DZ$118,0)),G27) | X27: =RANK(W27,$W$6:$W$76,1)
A28: 23 | B28: Kia Soul | C28: SUV | D28: gas | E28: 60k mi → ~2021 | F28: 14500 | G28: =0.3024+(F28-14500)/124600+0.02537*$D$3+0.0*$F$3 | H28: =0.3195+(F28-14500)/124600+0.02537*$D$3+0.0*$F$3 | I28: =0.34+(F28-14500)/124600+0.02537*$D$3+0.0*$F$3 | J28: =0.3387+(F28-14500)/82000+0.02537*$D$3+0.0*$F$3 | K28: =0.02537*$D$3+0.0*$F$3 | L28: =G28-K28 | M28: 1640 | N28: live listings ~60k mi, $12,000-$16,500 | O28: ◑ Hyundai/Kia SCC, select yrs | P28: 0.442 | Q28: 3 | R28: 0.406 | S28: 0.494 | T28: 0.589 | U28: 0.106 | V28: 13233 | W28: =IFERROR(G28*INDEX('Charts data (helper)'!$BI$119:$DZ$128,MATCH($Q$3,'Charts data (helper)'!$BH$119:$BH$128,0),MATCH($B28,'Charts data (helper)'!$BI$118:$DZ$118,0))/INDEX('Charts data (helper)'!$BI$119:$DZ$128,MATCH(0.07,'Charts data (helper)'!$BH$119:$BH$128,0),MATCH($B28,'Charts data (helper)'!$BI$118:$DZ$118,0)),G28) | X28: =RANK(W28,$W$6:$W$76,1)
A29: 24 | B29: VW Passat | C29: Car | D29: gas | E29: 55k mi → ~2022 | F29: 14200 | G29: =0.3068+(F29-14200)/134800+0.02566*$D$3+0.0*$F$3 | H29: =0.3276+(F29-14200)/134800+0.02566*$D$3+0.0*$F$3 | I29: =0.3485+(F29-14200)/134800+0.02566*$D$3+0.0*$F$3 | J29: =0.3397+(F29-14200)/91000+0.02566*$D$3+0.0*$F$3 | K29: =0.02566*$D$3+0.0*$F$3 | L29: =G29-K29 | M29: 1720 | N29: live listings ~55k mi, $12,000-$16,000 | O29: ◑ VW community port, select yrs | P29: 0.443 | Q29: 4 | R29: 0.412 | S29: 0.507 | T29: 0.533 | U29: 0.107 | V29: 14440 | W29: =IFERROR(G29*INDEX('Charts data (helper)'!$BI$119:$DZ$128,MATCH($Q$3,'Charts data (helper)'!$BH$119:$BH$128,0),MATCH($B29,'Charts data (helper)'!$BI$118:$DZ$118,0))/INDEX('Charts data (helper)'!$BI$119:$DZ$128,MATCH(0.07,'Charts data (helper)'!$BH$119:$BH$128,0),MATCH($B29,'Charts data (helper)'!$BI$118:$DZ$118,0)),G29) | X29: =RANK(W29,$W$6:$W$76,1)
A30: 25 | B30: Buick Encore | C30: SUV | D30: gas | E30: 50k mi → ~2022 | F30: 14800 | G30: =0.3072+(F30-14800)/125500+0.02622*$D$3+0.0*$F$3 | H30: =0.3228+(F30-14800)/125500+0.02622*$D$3+0.0*$F$3 | I30: =0.3418+(F30-14800)/125500+0.02622*$D$3+0.0*$F$3 | J30: =0.3418+(F30-14800)/85000+0.02622*$D$3+0.0*$F$3 | K30: =0.02622*$D$3+0.0*$F$3 | L30: =G30-K30 | M30: 1680 | N30: live listings ~50k mi, $12,500-$17,000 | O30: ✗ not on comma list | P30: 0.451 | Q30: 4 | R30: 0.419 | S30: 0.499 | T30: 0.559 | U30: 0.109 | V30: 13640 | W30: =IFERROR(G30*INDEX('Charts data (helper)'!$BI$119:$DZ$128,MATCH($Q$3,'Charts data (helper)'!$BH$119:$BH$128,0),MATCH($B30,'Charts data (helper)'!$BI$118:$DZ$118,0))/INDEX('Charts data (helper)'!$BI$119:$DZ$128,MATCH(0.07,'Charts data (helper)'!$BH$119:$BH$128,0),MATCH($B30,'Charts data (helper)'!$BI$118:$DZ$118,0)),G30) | X30: =RANK(W30,$W$6:$W$76,1)
A31: 26 | B31: Hyundai Kona | C31: SUV | D31: gas | E31: 65k mi → ~2021 | F31: 15000 | G31: =0.3204+(F31-15000)/119600+0.02481*$D$3+0.0*$F$3 | H31: =0.3364+(F31-15000)/119600+0.02481*$D$3+0.0*$F$3 | I31: =0.3572+(F31-15000)/119600+0.02481*$D$3+0.0*$F$3 | J31: =0.349+(F31-15000)/77000+0.02481*$D$3+0.0*$F$3 | K31: =0.02481*$D$3+0.0*$F$3 | L31: =G31-K31 | M31: 1640 | N31: live listings ~65k mi, $12,500-$17,000 | O31: ◑ Hyundai/Kia SCC, select yrs | P31: 0.459 | Q31: 4 | R31: 0.423 | S31: 0.504 | T31: 0.565 | U31: 0.108 | V31: 12953 | W31: =IFERROR(G31*INDEX('Charts data (helper)'!$BI$119:$DZ$128,MATCH($Q$3,'Charts data (helper)'!$BH$119:$BH$128,0),MATCH($B31,'Charts data (helper)'!$BI$118:$DZ$118,0))/INDEX('Charts data (helper)'!$BI$119:$DZ$128,MATCH(0.07,'Charts data (helper)'!$BH$119:$BH$128,0),MATCH($B31,'Charts data (helper)'!$BI$118:$DZ$118,0)),G31) | X31: =RANK(W31,$W$6:$W$76,1)
A32: 27 | B32: Mazda CX-5 | C32: SUV | D32: gas | E32: 65k mi → ~2021 | F32: 20600 | G32: =0.3148+(F32-20600)/149500+0.02672*$D$3+0.0*$F$3 | H32: =0.3315+(F32-20600)/149500+0.02672*$D$3+0.0*$F$3 | I32: =0.3466+(F32-20600)/149500+0.02672*$D$3+0.0*$F$3 | J32: =0.3595+(F32-20600)/100000+0.02672*$D$3+0.0*$F$3 | K32: =0.02672*$D$3+0.0*$F$3 | L32: =G32-K32 | M32: 1680 | N32: live listings ~65k mi, $17,500-$23,500 | O32: ◑ supported 2022–25 (buy ~2021 OUTSIDE range — pick a 2022-2025 example instead) | P32: 0.467 | Q32: 4 | R32: 0.427 | S32: 0.505 | T32: 0.588 | U32: 0.162 | V32: 24252 | W32: =IFERROR(G32*INDEX('Charts data (helper)'!$BI$119:$DZ$128,MATCH($Q$3,'Charts data (helper)'!$BH$119:$BH$128,0),MATCH($B32,'Charts data (helper)'!$BI$118:$DZ$118,0))/INDEX('Charts data (helper)'!$BI$119:$DZ$128,MATCH(0.07,'Charts data (helper)'!$BH$119:$BH$128,0),MATCH($B32,'Charts data (helper)'!$BI$118:$DZ$118,0)),G32) | X32: =RANK(W32,$W$6:$W$76,1)
A33: 28 | B33: Toyota Highlander Hybrid | C33: SUV AWD | D33: hybrid | E33: 65k mi → ~2021 | F33: 32000 | G33: =0.3686+(F33-32000)/179400+0.01857*$D$3+0.0*$F$3 | H33: =0.3891+(F33-32000)/179400+0.01857*$D$3+0.0*$F$3 | I33: =0.411+(F33-32000)/179400+0.01857*$D$3+0.0*$F$3 | J33: =0.4302+(F33-32000)/123000+0.01857*$D$3+0.0*$F$3 | K33: =0.01857*$D$3+0.0*$F$3 | L33: =G33-K33 | M33: 1840 | N33: live listings ~65k mi, $27,000-$36,500 | O33: ◑ select Toyota TSS years | P33: 0.463 | Q33: 4 | R33: 0.425 | S33: 0.524 | T33: 0.523 | U33: 0.275 | V33: 49404 | W33: =IFERROR(G33*INDEX('Charts data (helper)'!$BI$119:$DZ$128,MATCH($Q$3,'Charts data (helper)'!$BH$119:$BH$128,0),MATCH($B33,'Charts data (helper)'!$BI$118:$DZ$118,0))/INDEX('Charts data (helper)'!$BI$119:$DZ$128,MATCH(0.07,'Charts data (helper)'!$BH$119:$BH$128,0),MATCH($B33,'Charts data (helper)'!$BI$118:$DZ$118,0)),G33) | X33: =RANK(W33,$W$6:$W$76,1)
A34: 29 | B34: Subaru Outback | C34: SUV AWD | D34: gas | E34: 75k mi → ~2020 | F34: 18800 | G34: =0.3356+(F34-18800)/135600+0.02473*$D$3+0.0*$F$3 | H34: =0.3574+(F34-18800)/135600+0.02473*$D$3+0.0*$F$3 | I34: =0.3819+(F34-18800)/135600+0.02473*$D$3+0.0*$F$3 | J34: =0.3751+(F34-18800)/87000+0.02473*$D$3+0.0*$F$3 | K34: =0.02473*$D$3+0.0*$F$3 | L34: =G34-K34 | M34: 1640 | N34: live listings ~75k mi, $15,500-$21,500 | O34: ✓ supported 2020–22 (buy ~2020 ✓) | P34: 0.477 | Q34: 4 | R34: 0.432 | S34: 0.538 | T34: 0.504 | U34: 0.142 | V34: 19276 | W34: =IFERROR(G34*INDEX('Charts data (helper)'!$BI$119:$DZ$128,MATCH($Q$3,'Charts data (helper)'!$BH$119:$BH$128,0),MATCH($B34,'Charts data (helper)'!$BI$118:$DZ$118,0))/INDEX('Charts data (helper)'!$BI$119:$DZ$128,MATCH(0.07,'Charts data (helper)'!$BH$119:$BH$128,0),MATCH($B34,'Charts data (helper)'!$BI$118:$DZ$118,0)),G34) | X34: =RANK(W34,$W$6:$W$76,1)
A35: 30 | B35: Subaru Forester | C35: SUV AWD | D35: gas | E35: 55k mi → ~2022 | F35: 22200 | G35: =0.3394+(F35-22200)/145200+0.02419*$D$3+0.0*$F$3 | H35: =0.3564+(F35-22200)/145200+0.02419*$D$3+0.0*$F$3 | I35: =0.3761+(F35-22200)/145200+0.02419*$D$3+0.0*$F$3 | J35: =0.3746+(F35-22200)/99000+0.02419*$D$3+0.0*$F$3 | K35: =0.02419*$D$3+0.0*$F$3 | L35: =G35-K35 | M35: 1680 | N35: live listings ~55k mi, $18,500-$25,500 | O35: ◑ supported 2019–21 (buy ~2022 OUTSIDE range — pick a 2019-2021 example instead) | P35: 0.479 | Q35: 4 | R35: 0.439 | S35: 0.523 | T35: 0.486 | U35: 0.173 | V35: 25066 | W35: =IFERROR(G35*INDEX('Charts data (helper)'!$BI$119:$DZ$128,MATCH($Q$3,'Charts data (helper)'!$BH$119:$BH$128,0),MATCH($B35,'Charts data (helper)'!$BI$118:$DZ$118,0))/INDEX('Charts data (helper)'!$BI$119:$DZ$128,MATCH(0.07,'Charts data (helper)'!$BH$119:$BH$128,0),MATCH($B35,'Charts data (helper)'!$BI$118:$DZ$118,0)),G35) | X35: =RANK(W35,$W$6:$W$76,1)
A36: 31 | B36: Toyota Sienna Hybrid | C36: Van | D36: hybrid | E36: 55k mi → ~2022 | F36: 35000 | G36: =0.3765+(F36-35000)/189400+0.01766*$D$3+0.0*$F$3 | H36: =0.3984+(F36-35000)/189400+0.01766*$D$3+0.0*$F$3 | I36: =0.4175+(F36-35000)/189400+0.01766*$D$3+0.0*$F$3 | J36: =0.4354+(F36-35000)/133000+0.01766*$D$3+0.0*$F$3 | K36: =0.01766*$D$3+0.0*$F$3 | L36: =G36-K36 | M36: 1840 | N36: live listings ~55k mi, $29,500-$40,000 | O36: ◑ select Toyota TSS years | P36: 0.451 | Q36: 4 | R36: 0.416 | S36: 0.525 | T36: 0.594 | U36: 0.31 | V36: 58792 | W36: =IFERROR(G36*INDEX('Charts data (helper)'!$BI$119:$DZ$128,MATCH($Q$3,'Charts data (helper)'!$BH$119:$BH$128,0),MATCH($B36,'Charts data (helper)'!$BI$118:$DZ$118,0))/INDEX('Charts data (helper)'!$BI$119:$DZ$128,MATCH(0.07,'Charts data (helper)'!$BH$119:$BH$128,0),MATCH($B36,'Charts data (helper)'!$BI$118:$DZ$118,0)),G36) | X36: =RANK(W36,$W$6:$W$76,1)
A37: 32 | B37: Toyota Tacoma | C37: Truck | D37: gas | E37: 75k mi → ~2020 | F37: 29333 | G37: =0.3169+(F37-29333)/214900+0.03009*$D$3+0.0*$F$3 | H37: =0.3359+(F37-29333)/214900+0.03009*$D$3+0.0*$F$3 | I37: =0.3547+(F37-29333)/214900+0.03009*$D$3+0.0*$F$3 | J37: =0.3699+(F37-29333)/148000+0.03009*$D$3+0.0*$F$3 | K37: =0.03009*$D$3+0.0*$F$3 | L37: =G37-K37 | M37: 1800 | N37: live listings ~75k mi, $24,500-$33,500 | O37: ✗ not supported (no Tacoma on list) | P37: 0.474 | Q37: 4 | R37: 0.44 | S37: 0.531 | T37: 0.57 | U37: 0.281 | V37: 60430 | W37: =IFERROR(G37*INDEX('Charts data (helper)'!$BI$119:$DZ$128,MATCH($Q$3,'Charts data (helper)'!$BH$119:$BH$128,0),MATCH($B37,'Charts data (helper)'!$BI$118:$DZ$118,0))/INDEX('Charts data (helper)'!$BI$119:$DZ$128,MATCH(0.07,'Charts data (helper)'!$BH$119:$BH$128,0),MATCH($B37,'Charts data (helper)'!$BI$118:$DZ$118,0)),G37) | X37: =RANK(W37,$W$6:$W$76,1)
A38: 33 | B38: Nissan Rogue | C38: SUV | D38: gas | E38: 55k mi → ~2022 | F38: 18800 | G38: =0.3443+(F38-18800)/115300+0.02592*$D$3+0.0*$F$3 | H38: =0.3648+(F38-18800)/115300+0.02592*$D$3+0.0*$F$3 | I38: =0.3873+(F38-18800)/115300+0.02592*$D$3+0.0*$F$3 | J38: =0.3805+(F38-18800)/76000+0.02592*$D$3+0.0*$F$3 | K38: =0.02592*$D$3+0.0*$F$3 | L38: =G38-K38 | M38: 1664 | N38: live listings ~55k mi, $15,500-$21,500 | O38: ◑ supported 2018–20 (buy ~2022 OUTSIDE range — pick a 2018-2020 example instead) | P38: 0.498 | Q38: 4 | R38: 0.451 | S38: 0.541 | T38: 0.527 | U38: 0.134 | V38: 15459 | W38: =IFERROR(G38*INDEX('Charts data (helper)'!$BI$119:$DZ$128,MATCH($Q$3,'Charts data (helper)'!$BH$119:$BH$128,0),MATCH($B38,'Charts data (helper)'!$BI$118:$DZ$118,0))/INDEX('Charts data (helper)'!$BI$119:$DZ$128,MATCH(0.07,'Charts data (helper)'!$BH$119:$BH$128,0),MATCH($B38,'Charts data (helper)'!$BI$118:$DZ$118,0)),G38) | X38: =RANK(W38,$W$6:$W$76,1)
A39: 34 | B39: Chevy Equinox | C39: SUV | D39: gas | E39: 55k mi → ~2022 | F39: 17200 | G39: =0.3379+(F39-17200)/120500+0.02751*$D$3+0.0*$F$3 | H39: =0.3571+(F39-17200)/120500+0.02751*$D$3+0.0*$F$3 | I39: =0.3808+(F39-17200)/120500+0.02751*$D$3+0.0*$F$3 | J39: =0.3628+(F39-17200)/80000+0.02751*$D$3+0.0*$F$3 | K39: =0.02751*$D$3+0.0*$F$3 | L39: =G39-K39 | M39: 1720 | N39: live listings ~55k mi, $14,500-$19,500 | O39: ✓ supported 2019–22 (buy ~2022 ✓) | P39: 0.498 | Q39: 5 | R39: 0.455 | S39: 0.546 | T39: 0.534 | U39: 0.125 | V39: 15003 | W39: =IFERROR(G39*INDEX('Charts data (helper)'!$BI$119:$DZ$128,MATCH($Q$3,'Charts data (helper)'!$BH$119:$BH$128,0),MATCH($B39,'Charts data (helper)'!$BI$118:$DZ$118,0))/INDEX('Charts data (helper)'!$BI$119:$DZ$128,MATCH(0.07,'Charts data (helper)'!$BH$119:$BH$128,0),MATCH($B39,'Charts data (helper)'!$BI$118:$DZ$118,0)),G39) | X39: =RANK(W39,$W$6:$W$76,1)
A40: 35 | B40: Toyota Sienna (V6) | C40: Van | D40: gas | E40: 65k mi → ~2020 | F40: 22333 | G40: =0.3065+(F40-22333)/179400+0.0342*$D$3+0.0*$F$3 | H40: =0.3217+(F40-22333)/179400+0.0342*$D$3+0.0*$F$3 | I40: =0.336+(F40-22333)/179400+0.0342*$D$3+0.0*$F$3 | J40: =0.3502+(F40-22333)/123000+0.0342*$D$3+0.0*$F$3 | K40: =0.0342*$D$3+0.0*$F$3 | L40: =G40-K40 | M40: 1720 | N40: live listings ~65k mi, $18,500-$25,500 | O40: ✗ not on list | P40: 0.483 | Q40: 5 | R40: 0.457 | S40: 0.533 | T40: 0.519 | U40: 0.192 | V40: 34480 | W40: =IFERROR(G40*INDEX('Charts data (helper)'!$BI$119:$DZ$128,MATCH($Q$3,'Charts data (helper)'!$BH$119:$BH$128,0),MATCH($B40,'Charts data (helper)'!$BI$118:$DZ$118,0))/INDEX('Charts data (helper)'!$BI$119:$DZ$128,MATCH(0.07,'Charts data (helper)'!$BH$119:$BH$128,0),MATCH($B40,'Charts data (helper)'!$BI$118:$DZ$118,0)),G40) | X40: =RANK(W40,$W$6:$W$76,1)
A41: 36 | B41: Mini Cooper | C41: Car | D41: gas | E41: 45k mi → ~2023 | F41: 18200 | G41: =0.3615+(F41-18200)/130500+0.02419*$D$3+0.0*$F$3 | H41: =0.3847+(F41-18200)/130500+0.02419*$D$3+0.0*$F$3 | I41: =0.413+(F41-18200)/130500+0.02419*$D$3+0.0*$F$3 | J41: =0.3922+(F41-18200)/90000+0.02419*$D$3+0.0*$F$3 | K41: =0.02419*$D$3+0.0*$F$3 | L41: =G41-K41 | M41: 1720 | N41: live listings ~45k mi, $15,000-$20,500 | O41: ✗ not on comma list | P41: 0.488 | Q41: 5 | R41: 0.451 | S41: 0.566 | T41: 0.528 | U41: 0.136 | V41: 17695 | W41: =IFERROR(G41*INDEX('Charts data (helper)'!$BI$119:$DZ$128,MATCH($Q$3,'Charts data (helper)'!$BH$119:$BH$128,0),MATCH($B41,'Charts data (helper)'!$BI$118:$DZ$118,0))/INDEX('Charts data (helper)'!$BI$119:$DZ$128,MATCH(0.07,'Charts data (helper)'!$BH$119:$BH$128,0),MATCH($B41,'Charts data (helper)'!$BI$118:$DZ$118,0)),G41) | X41: =RANK(W41,$W$6:$W$76,1)
A42: 37 | B42: Ford Ranger (old compact) | C42: Truck | D42: gas | E42: 55k mi → ~2011 | F42: 11500 | G42: =0.3178+(F42-11500)/159500+0.03235*$D$3+0.0*$F$3 | H42: =0.3382+(F42-11500)/159500+0.03235*$D$3+0.0*$F$3 | I42: =0.358+(F42-11500)/159500+0.03235*$D$3+0.0*$F$3 | J42: =0.3275+(F42-11500)/110000+0.03235*$D$3+0.0*$F$3 | K42: =0.03235*$D$3+0.0*$F$3 | L42: =G42-K42 | M42: 1832 | N42: live listings ~55k mi, $9,500-$13,000 | O42: ✗ not supported | P42: 0.498 | Q42: 5 | R42: 0.467 | S42: 0.547 | T42: 0.569 | U42: 0.093 | V42: 14876 | W42: =IFERROR(G42*INDEX('Charts data (helper)'!$BI$119:$DZ$128,MATCH($Q$3,'Charts data (helper)'!$BH$119:$BH$128,0),MATCH($B42,'Charts data (helper)'!$BI$118:$DZ$118,0))/INDEX('Charts data (helper)'!$BI$119:$DZ$128,MATCH(0.07,'Charts data (helper)'!$BH$119:$BH$128,0),MATCH($B42,'Charts data (helper)'!$BI$118:$DZ$118,0)),G42) | X42: =RANK(W42,$W$6:$W$76,1)
A43: 38 | B43: Fiat 500X | C43: SUV AWD | D43: gas | E43: 40k mi → ~2023 | F43: 14800 | G43: =0.3403+(F43-14800)/109500+0.02931*$D$3+0.0*$F$3 | H43: =0.3537+(F43-14800)/109500+0.02931*$D$3+0.0*$F$3 | I43: =0.3734+(F43-14800)/109500+0.02931*$D$3+0.0*$F$3 | J43: =0.3652+(F43-14800)/75000+0.02931*$D$3+0.0*$F$3 | K43: =0.02931*$D$3+0.0*$F$3 | L43: =G43-K43 | M43: 1640 | N43: live listings ~40k mi, $12,500-$17,000 | O43: ✗ not on comma list | P43: 0.51 | Q43: 5 | R43: 0.475 | S43: 0.549 | T43: 0.534 | U43: 0.104 | V43: 11368 | W43: =IFERROR(G43*INDEX('Charts data (helper)'!$BI$119:$DZ$128,MATCH($Q$3,'Charts data (helper)'!$BH$119:$BH$128,0),MATCH($B43,'Charts data (helper)'!$BI$118:$DZ$118,0))/INDEX('Charts data (helper)'!$BI$119:$DZ$128,MATCH(0.07,'Charts data (helper)'!$BH$119:$BH$128,0),MATCH($B43,'Charts data (helper)'!$BI$118:$DZ$118,0)),G43) | X43: =RANK(W43,$W$6:$W$76,1)
A44: 39 | B44: VW GTI | C44: Car | D44: gas | E44: 60k mi → ~2021 | F44: 19000 | G44: =0.3587+(F44-19000)/135000+0.0266*$D$3+0.0*$F$3 | H44: =0.3807+(F44-19000)/135000+0.0266*$D$3+0.0*$F$3 | I44: =0.4053+(F44-19000)/135000+0.0266*$D$3+0.0*$F$3 | J44: =0.3971+(F44-19000)/90000+0.0266*$D$3+0.0*$F$3 | K44: =0.0266*$D$3+0.0*$F$3 | L44: =G44-K44 | M44: 1720 | N44: live listings ~60k mi, $16,000-$21,500 | O44: ◑ VW MQB community port, select yrs | P44: 0.499 | Q44: 5 | R44: 0.464 | S44: 0.574 | T44: 0.512 | U44: 0.143 | V44: 19361 | W44: =IFERROR(G44*INDEX('Charts data (helper)'!$BI$119:$DZ$128,MATCH($Q$3,'Charts data (helper)'!$BH$119:$BH$128,0),MATCH($B44,'Charts data (helper)'!$BI$118:$DZ$118,0))/INDEX('Charts data (helper)'!$BI$119:$DZ$128,MATCH(0.07,'Charts data (helper)'!$BH$119:$BH$128,0),MATCH($B44,'Charts data (helper)'!$BI$118:$DZ$118,0)),G44) | X44: =RANK(W44,$W$6:$W$76,1)
A45: 40 | B45: Kia Sportage | C45: SUV AWD | D45: gas | E45: 75k mi → ~2020 | F45: 15667 | G45: =0.3451+(F45-15667)/109600+0.02931*$D$3+0.0*$F$3 | H45: =0.3657+(F45-15667)/109600+0.02931*$D$3+0.0*$F$3 | I45: =0.3907+(F45-15667)/109600+0.02931*$D$3+0.0*$F$3 | J45: =0.38+(F45-15667)/67000+0.02931*$D$3+0.0*$F$3 | K45: =0.02931*$D$3+0.0*$F$3 | L45: =G45-K45 | M45: 1680 | N45: live listings ~75k mi, $13,000-$18,000 | O45: ◑ Hyundai/Kia SCC, select yrs | P45: 0.514 | Q45: 5 | R45: 0.468 | S45: 0.571 | T45: 0.496 | U45: 0.11 | V45: 12048 | W45: =IFERROR(G45*INDEX('Charts data (helper)'!$BI$119:$DZ$128,MATCH($Q$3,'Charts data (helper)'!$BH$119:$BH$128,0),MATCH($B45,'Charts data (helper)'!$BI$118:$DZ$118,0))/INDEX('Charts data (helper)'!$BI$119:$DZ$128,MATCH(0.07,'Charts data (helper)'!$BH$119:$BH$128,0),MATCH($B45,'Charts data (helper)'!$BI$118:$DZ$118,0)),G45) | X45: =RANK(W45,$W$6:$W$76,1)
A46: 41 | B46: Ford Escape | C46: SUV | D46: gas | E46: 65k mi → ~2021 | F46: 15000 | G46: =0.3446+(F46-15000)/105300+0.0296*$D$3+0.0*$F$3 | H46: =0.3664+(F46-15000)/105300+0.0296*$D$3+0.0*$F$3 | I46: =0.3906+(F46-15000)/105300+0.0296*$D$3+0.0*$F$3 | J46: =0.3848+(F46-15000)/66000+0.0296*$D$3+0.0*$F$3 | K46: =0.0296*$D$3+0.0*$F$3 | L46: =G46-K46 | M46: 1720 | N46: live listings ~65k mi, $12,500-$17,000 | O46: ✓ supported 2020–24 (buy ~2021 ✓) | P46: 0.517 | Q46: 5 | R46: 0.462 | S46: 0.574 | T46: 0.557 | U46: 0.104 | V46: 10948 | W46: =IFERROR(G46*INDEX('Charts data (helper)'!$BI$119:$DZ$128,MATCH($Q$3,'Charts data (helper)'!$BH$119:$BH$128,0),MATCH($B46,'Charts data (helper)'!$BI$118:$DZ$118,0))/INDEX('Charts data (helper)'!$BI$119:$DZ$128,MATCH(0.07,'Charts data (helper)'!$BH$119:$BH$128,0),MATCH($B46,'Charts data (helper)'!$BI$118:$DZ$118,0)),G46) | X46: =RANK(W46,$W$6:$W$76,1)
A47: 42 | B47: Toyota Highlander | C47: SUV AWD | D47: gas | E47: 85k mi → ~2019 | F47: 25000 | G47: =0.3508+(F47-25000)/159400+0.02954*$D$3+0.0*$F$3 | H47: =0.3723+(F47-25000)/159400+0.02954*$D$3+0.0*$F$3 | I47: =0.394+(F47-25000)/159400+0.02954*$D$3+0.0*$F$3 | J47: =0.4075+(F47-25000)/103000+0.02954*$D$3+0.0*$F$3 | K47: =0.02954*$D$3+0.0*$F$3 | L47: =G47-K47 | M47: 1760 | N47: live listings ~85k mi, $21,000-$28,500 | O47: ◑ select Toyota TSS years | P47: 0.508 | Q47: 5 | R47: 0.467 | S47: 0.571 | T47: 0.593 | U47: 0.203 | V47: 32310 | W47: =IFERROR(G47*INDEX('Charts data (helper)'!$BI$119:$DZ$128,MATCH($Q$3,'Charts data (helper)'!$BH$119:$BH$128,0),MATCH($B47,'Charts data (helper)'!$BI$118:$DZ$118,0))/INDEX('Charts data (helper)'!$BI$119:$DZ$128,MATCH(0.07,'Charts data (helper)'!$BH$119:$BH$128,0),MATCH($B47,'Charts data (helper)'!$BI$118:$DZ$118,0)),G47) | X47: =RANK(W47,$W$6:$W$76,1)
A48: 43 | B48: Hyundai Tucson | C48: SUV | D48: gas | E48: 55k mi → ~2022 | F48: 19541 | G48: =0.3554+(F48-19541)/115300+0.03007*$D$3+0.0*$F$3 | H48: =0.3702+(F48-19541)/115300+0.03007*$D$3+0.0*$F$3 | I48: =0.3949+(F48-19541)/115300+0.03007*$D$3+0.0*$F$3 | J48: =0.3698+(F48-19541)/76000+0.03007*$D$3+0.0*$F$3 | K48: =0.03007*$D$3+0.0*$F$3 | L48: =G48-K48 | M48: 1680 | N48: live listings ~55k mi, $16,500-$22,000 | O48: ✓ supported 2021–24 (buy ~2022 ✓) | P48: 0.532 | Q48: 5 | R48: 0.491 | S48: 0.579 | T48: 0.502 | U48: 0.139 | V48: 16068 | W48: =IFERROR(G48*INDEX('Charts data (helper)'!$BI$119:$DZ$128,MATCH($Q$3,'Charts data (helper)'!$BH$119:$BH$128,0),MATCH($B48,'Charts data (helper)'!$BI$118:$DZ$118,0))/INDEX('Charts data (helper)'!$BI$119:$DZ$128,MATCH(0.07,'Charts data (helper)'!$BH$119:$BH$128,0),MATCH($B48,'Charts data (helper)'!$BI$118:$DZ$118,0)),G48) | X48: =RANK(W48,$W$6:$W$76,1)
A49: 44 | B49: Toyota 4Runner | C49: SUV AWD | D49: gas | E49: 60k mi → ~2021 | F49: 36333 | G49: =0.3343+(F49-36333)/229900+0.0343*$D$3+0.0*$F$3 | H49: =0.3541+(F49-36333)/229900+0.0343*$D$3+0.0*$F$3 | I49: =0.3712+(F49-36333)/229900+0.0343*$D$3+0.0*$F$3 | J49: =0.3918+(F49-36333)/163000+0.0343*$D$3+0.0*$F$3 | K49: =0.0343*$D$3+0.0*$F$3 | L49: =G49-K49 | M49: 1800 | N49: live listings ~60k mi, $30,500-$41,500 | O49: ✗ not on list | P49: 0.512 | Q49: 5 | R49: 0.473 | S49: 0.57 | T49: 0.508 | U49: 0.365 | V49: 83878 | W49: =IFERROR(G49*INDEX('Charts data (helper)'!$BI$119:$DZ$128,MATCH($Q$3,'Charts data (helper)'!$BH$119:$BH$128,0),MATCH($B49,'Charts data (helper)'!$BI$118:$DZ$118,0))/INDEX('Charts data (helper)'!$BI$119:$DZ$128,MATCH(0.07,'Charts data (helper)'!$BH$119:$BH$128,0),MATCH($B49,'Charts data (helper)'!$BI$118:$DZ$118,0)),G49) | X49: =RANK(W49,$W$6:$W$76,1)
A50: 45 | B50: Honda Odyssey | C50: Van | D50: gas | E50: 80k mi → ~2020 | F50: 20333 | G50: =0.348+(F50-20333)/144900+0.03191*$D$3+0.0*$F$3 | H50: =0.3704+(F50-20333)/144900+0.03191*$D$3+0.0*$F$3 | I50: =0.3935+(F50-20333)/144900+0.03191*$D$3+0.0*$F$3 | J50: =0.3934+(F50-20333)/93000+0.03191*$D$3+0.0*$F$3 | K50: =0.03191*$D$3+0.0*$F$3 | L50: =G50-K50 | M50: 1680 | N50: live listings ~80k mi, $17,000-$23,000 | O50: ◑ Honda Sensing years | P50: 0.512 | Q50: 5 | R50: 0.472 | S50: 0.58 | T50: 0.517 | U50: 0.158 | V50: 22891 | W50: =IFERROR(G50*INDEX('Charts data (helper)'!$BI$119:$DZ$128,MATCH($Q$3,'Charts data (helper)'!$BH$119:$BH$128,0),MATCH($B50,'Charts data (helper)'!$BI$118:$DZ$118,0))/INDEX('Charts data (helper)'!$BI$119:$DZ$128,MATCH(0.07,'Charts data (helper)'!$BH$119:$BH$128,0),MATCH($B50,'Charts data (helper)'!$BI$118:$DZ$118,0)),G50) | X50: =RANK(W50,$W$6:$W$76,1)
A51: 46 | B51: Kia Sorento | C51: SUV AWD | D51: gas | E51: 75k mi → ~2020 | F51: 18333 | G51: =0.3555+(F51-18333)/125200+0.03061*$D$3+0.0*$F$3 | H51: =0.3755+(F51-18333)/125200+0.03061*$D$3+0.0*$F$3 | I51: =0.4017+(F51-18333)/125200+0.03061*$D$3+0.0*$F$3 | J51: =0.3991+(F51-18333)/79000+0.03061*$D$3+0.0*$F$3 | K51: =0.03061*$D$3+0.0*$F$3 | L51: =G51-K51 | M51: 1720 | N51: live listings ~75k mi, $15,500-$21,000 | O51: ◑ Hyundai/Kia SCC, select yrs | P51: 0.524 | Q51: 5 | R51: 0.482 | S51: 0.586 | T51: 0.52 | U51: 0.135 | V51: 16841 | W51: =IFERROR(G51*INDEX('Charts data (helper)'!$BI$119:$DZ$128,MATCH($Q$3,'Charts data (helper)'!$BH$119:$BH$128,0),MATCH($B51,'Charts data (helper)'!$BI$118:$DZ$118,0))/INDEX('Charts data (helper)'!$BI$119:$DZ$128,MATCH(0.07,'Charts data (helper)'!$BH$119:$BH$128,0),MATCH($B51,'Charts data (helper)'!$BI$118:$DZ$118,0)),G51) | X51: =RANK(W51,$W$6:$W$76,1)
A52: 47 | B52: Hyundai Santa Fe | C52: SUV AWD | D52: gas | E52: 80k mi → ~2020 | F52: 16667 | G52: =0.3573+(F52-16667)/109800+0.03046*$D$3+0.0*$F$3 | H52: =0.3797+(F52-16667)/109800+0.03046*$D$3+0.0*$F$3 | I52: =0.409+(F52-16667)/109800+0.03046*$D$3+0.0*$F$3 | J52: =0.4051+(F52-16667)/66000+0.03046*$D$3+0.0*$F$3 | K52: =0.03046*$D$3+0.0*$F$3 | L52: =G52-K52 | M52: 1720 | N52: live listings ~80k mi, $14,000-$19,000 | O52: ◑ Hyundai/Kia SCC, select yrs | P52: 0.533 | Q52: 5 | R52: 0.487 | S52: 0.594 | T52: 0.502 | U52: 0.117 | V52: 12847 | W52: =IFERROR(G52*INDEX('Charts data (helper)'!$BI$119:$DZ$128,MATCH($Q$3,'Charts data (helper)'!$BH$119:$BH$128,0),MATCH($B52,'Charts data (helper)'!$BI$118:$DZ$118,0))/INDEX('Charts data (helper)'!$BI$119:$DZ$128,MATCH(0.07,'Charts data (helper)'!$BH$119:$BH$128,0),MATCH($B52,'Charts data (helper)'!$BI$118:$DZ$118,0)),G52) | X52: =RANK(W52,$W$6:$W$76,1)
A53: 48 | B53: VW Tiguan | C53: SUV AWD | D53: gas | E53: 60k mi → ~2021 | F53: 16800 | G53: =0.3577+(F53-16800)/124600+0.03065*$D$3+0.0*$F$3 | H53: =0.3778+(F53-16800)/124600+0.03065*$D$3+0.0*$F$3 | I53: =0.4046+(F53-16800)/124600+0.03065*$D$3+0.0*$F$3 | J53: =0.3917+(F53-16800)/82000+0.03065*$D$3+0.0*$F$3 | K53: =0.03065*$D$3+0.0*$F$3 | L53: =G53-K53 | M53: 1680 | N53: live listings ~60k mi, $14,000-$19,000 | O53: ◑ VW MQB community port, select yrs | P53: 0.516 | Q53: 5 | R53: 0.482 | S53: 0.59 | T53: 0.628 | U53: 0.123 | V53: 15332 | W53: =IFERROR(G53*INDEX('Charts data (helper)'!$BI$119:$DZ$128,MATCH($Q$3,'Charts data (helper)'!$BH$119:$BH$128,0),MATCH($B53,'Charts data (helper)'!$BI$118:$DZ$118,0))/INDEX('Charts data (helper)'!$BI$119:$DZ$128,MATCH(0.07,'Charts data (helper)'!$BH$119:$BH$128,0),MATCH($B53,'Charts data (helper)'!$BI$118:$DZ$118,0)),G53) | X53: =RANK(W53,$W$6:$W$76,1)
A54: 49 | B54: Chrysler Pacifica PHEV | C54: Van | D54: plug-in | E54: 65k mi → ~2021 | F54: 22000 | G54: =0.4146+(F54-22000)/110500+0.01394*$D$3+0.15233*$F$3 | H54: =0.4405+(F54-22000)/110500+0.01394*$D$3+0.15233*$F$3 | I54: =0.4727+(F54-22000)/110500+0.01394*$D$3+0.15233*$F$3 | J54: =0.4562+(F54-22000)/70000+0.01394*$D$3+0.15233*$F$3 | K54: =0.01394*$D$3+0.15233*$F$3 | L54: =G54-K54 | M54: 1760 | N54: live listings ~65k mi, $18,500-$25,000 | O54: ✗ not on list | P54: 0.549 | Q54: 6 | R54: 0.494 | S54: 0.619 | T54: 0.539 | U54: 0.155 | V54: 17101 | W54: =IFERROR(G54*INDEX('Charts data (helper)'!$BI$119:$DZ$128,MATCH($Q$3,'Charts data (helper)'!$BH$119:$BH$128,0),MATCH($B54,'Charts data (helper)'!$BI$118:$DZ$118,0))/INDEX('Charts data (helper)'!$BI$119:$DZ$128,MATCH(0.07,'Charts data (helper)'!$BH$119:$BH$128,0),MATCH($B54,'Charts data (helper)'!$BI$118:$DZ$118,0)),G54) | X54: =RANK(W54,$W$6:$W$76,1)
A55: 50 | B55: Subaru Ascent | C55: SUV AWD | D55: gas | E55: 55k mi → ~2022 | F55: 23400 | G55: =0.3635+(F55-23400)/129600+0.03305*$D$3+0.0*$F$3 | H55: =0.3825+(F55-23400)/129600+0.03305*$D$3+0.0*$F$3 | I55: =0.4015+(F55-23400)/129600+0.03305*$D$3+0.0*$F$3 | J55: =0.4041+(F55-23400)/87000+0.03305*$D$3+0.0*$F$3 | K55: =0.03305*$D$3+0.0*$F$3 | L55: =G55-K55 | M55: 1680 | N55: live listings ~55k mi, $19,500-$26,500 | O55: ✗ not on list | P55: 0.555 | Q55: 6 | R55: 0.506 | S55: 0.594 | T55: 0.545 | U55: 0.174 | V55: 22536 | W55: =IFERROR(G55*INDEX('Charts data (helper)'!$BI$119:$DZ$128,MATCH($Q$3,'Charts data (helper)'!$BH$119:$BH$128,0),MATCH($B55,'Charts data (helper)'!$BI$118:$DZ$118,0))/INDEX('Charts data (helper)'!$BI$119:$DZ$128,MATCH(0.07,'Charts data (helper)'!$BH$119:$BH$128,0),MATCH($B55,'Charts data (helper)'!$BI$118:$DZ$118,0)),G55) | X55: =RANK(W55,$W$6:$W$76,1)
A56: 51 | B56: Ford Ranger (2019+ midsize) | C56: Truck | D56: gas | E56: 55k mi → ~2022 | F56: 23000 | G56: =0.3666+(F56-23000)/145200+0.03341*$D$3+0.0*$F$3 | H56: =0.3835+(F56-23000)/145200+0.03341*$D$3+0.0*$F$3 | I56: =0.4026+(F56-23000)/145200+0.03341*$D$3+0.0*$F$3 | J56: =0.4021+(F56-23000)/99000+0.03341*$D$3+0.0*$F$3 | K56: =0.03341*$D$3+0.0*$F$3 | L56: =G56-K56 | M56: 1832 | N56: live listings ~55k mi, $19,500-$26,000 | O56: ◑ supported 2024 only; our buy 2022 = not | P56: 0.561 | Q56: 6 | R56: 0.513 | S56: 0.597 | T56: 0.512 | U56: 0.179 | V56: 25969 | W56: =IFERROR(G56*INDEX('Charts data (helper)'!$BI$119:$DZ$128,MATCH($Q$3,'Charts data (helper)'!$BH$119:$BH$128,0),MATCH($B56,'Charts data (helper)'!$BI$118:$DZ$118,0))/INDEX('Charts data (helper)'!$BI$119:$DZ$128,MATCH(0.07,'Charts data (helper)'!$BH$119:$BH$128,0),MATCH($B56,'Charts data (helper)'!$BI$118:$DZ$118,0)),G56) | X56: =RANK(W56,$W$6:$W$76,1)
A57: 52 | B57: Honda Pilot | C57: SUV AWD | D57: gas | E57: 85k mi → ~2019 | F57: 22500 | G57: =0.3558+(F57-22500)/139900+0.03551*$D$3+0.0*$F$3 | H57: =0.376+(F57-22500)/139900+0.03551*$D$3+0.0*$F$3 | I57: =0.3974+(F57-22500)/139900+0.03551*$D$3+0.0*$F$3 | J57: =0.4124+(F57-22500)/88000+0.03551*$D$3+0.0*$F$3 | K57: =0.03551*$D$3+0.0*$F$3 | L57: =G57-K57 | M57: 1680 | N57: live listings ~85k mi, $19,000-$25,500 | O57: ◑ Honda Sensing years | P57: 0.548 | Q57: 6 | R57: 0.507 | S57: 0.605 | T57: 0.522 | U57: 0.172 | V57: 24101 | W57: =IFERROR(G57*INDEX('Charts data (helper)'!$BI$119:$DZ$128,MATCH($Q$3,'Charts data (helper)'!$BH$119:$BH$128,0),MATCH($B57,'Charts data (helper)'!$BI$118:$DZ$118,0))/INDEX('Charts data (helper)'!$BI$119:$DZ$128,MATCH(0.07,'Charts data (helper)'!$BH$119:$BH$128,0),MATCH($B57,'Charts data (helper)'!$BI$118:$DZ$118,0)),G57) | X57: =RANK(W57,$W$6:$W$76,1)
A58: 53 | B58: Mini Countryman | C58: SUV AWD | D58: gas | E58: 55k mi → ~2022 | F58: 19000 | G58: =0.3948+(F58-19000)/120500+0.02857*$D$3+0.0*$F$3 | H58: =0.4193+(F58-19000)/120500+0.02857*$D$3+0.0*$F$3 | I58: =0.4504+(F58-19000)/120500+0.02857*$D$3+0.0*$F$3 | J58: =0.4305+(F58-19000)/80000+0.02857*$D$3+0.0*$F$3 | K58: =0.02857*$D$3+0.0*$F$3 | L58: =G58-K58 | M58: 1760 | N58: live listings ~55k mi, $16,000-$21,500 | O58: ✗ not on comma list | P58: 0.553 | Q58: 6 | R58: 0.509 | S58: 0.628 | T58: 0.528 | U58: 0.138 | V58: 16573 | W58: =IFERROR(G58*INDEX('Charts data (helper)'!$BI$119:$DZ$128,MATCH($Q$3,'Charts data (helper)'!$BH$119:$BH$128,0),MATCH($B58,'Charts data (helper)'!$BI$118:$DZ$118,0))/INDEX('Charts data (helper)'!$BI$119:$DZ$128,MATCH(0.07,'Charts data (helper)'!$BH$119:$BH$128,0),MATCH($B58,'Charts data (helper)'!$BI$118:$DZ$118,0)),G58) | X58: =RANK(W58,$W$6:$W$76,1)
A59: 54 | B59: Toyota Sequoia | C59: SUV AWD | D59: gas | E59: 80k mi → ~2020 | F59: 32250 | G59: =0.3402+(F59-32250)/220300+0.03966*$D$3+0.0*$F$3 | H59: =0.3623+(F59-32250)/220300+0.03966*$D$3+0.0*$F$3 | I59: =0.3815+(F59-32250)/220300+0.03966*$D$3+0.0*$F$3 | J59: =0.4035+(F59-32250)/151000+0.03966*$D$3+0.0*$F$3 | K59: =0.03966*$D$3+0.0*$F$3 | L59: =G59-K59 | M59: 1960 | N59: live listings ~80k mi, $27,000-$37,000 | O59: ✗ not on list | P59: 0.545 | Q59: 6 | R59: 0.508 | S59: 0.613 | T59: 0.579 | U59: 0.314 | V59: 69251 | W59: =IFERROR(G59*INDEX('Charts data (helper)'!$BI$119:$DZ$128,MATCH($Q$3,'Charts data (helper)'!$BH$119:$BH$128,0),MATCH($B59,'Charts data (helper)'!$BI$118:$DZ$118,0))/INDEX('Charts data (helper)'!$BI$119:$DZ$128,MATCH(0.07,'Charts data (helper)'!$BH$119:$BH$128,0),MATCH($B59,'Charts data (helper)'!$BI$118:$DZ$118,0)),G59) | X59: =RANK(W59,$W$6:$W$76,1)
A60: 55 | B60: Hyundai Palisade | C60: SUV AWD | D60: gas | E60: 45k mi → ~2023 | F60: 31000 | G60: =0.3862+(F60-31000)/155200+0.03266*$D$3+0.0*$F$3 | H60: =0.4052+(F60-31000)/155200+0.03266*$D$3+0.0*$F$3 | I60: =0.4248+(F60-31000)/155200+0.03266*$D$3+0.0*$F$3 | J60: =0.433+(F60-31000)/109000+0.03266*$D$3+0.0*$F$3 | K60: =0.03266*$D$3+0.0*$F$3 | L60: =G60-K60 | M60: 1720 | N60: live listings ~45k mi, $26,000-$35,500 | O60: ✗ not on list | P60: 0.566 | Q60: 6 | R60: 0.523 | S60: 0.617 | T60: 0.536 | U60: 0.248 | V60: 38528 | W60: =IFERROR(G60*INDEX('Charts data (helper)'!$BI$119:$DZ$128,MATCH($Q$3,'Charts data (helper)'!$BH$119:$BH$128,0),MATCH($B60,'Charts data (helper)'!$BI$118:$DZ$118,0))/INDEX('Charts data (helper)'!$BI$119:$DZ$128,MATCH(0.07,'Charts data (helper)'!$BH$119:$BH$128,0),MATCH($B60,'Charts data (helper)'!$BI$118:$DZ$118,0)),G60) | X60: =RANK(W60,$W$6:$W$76,1)
A61: 56 | B61: Chrysler Pacifica | C61: Van | D61: gas | E61: 75k mi → ~2020 | F61: 16333 | G61: =0.3725+(F61-16333)/100500+0.03539*$D$3+0.0*$F$3 | H61: =0.3996+(F61-16333)/100500+0.03539*$D$3+0.0*$F$3 | I61: =0.4324+(F61-16333)/100500+0.03539*$D$3+0.0*$F$3 | J61: =0.406+(F61-16333)/60000+0.03539*$D$3+0.0*$F$3 | K61: =0.03539*$D$3+0.0*$F$3 | L61: =G61-K61 | M61: 1680 | N61: live listings ~75k mi, $13,500-$18,500 | O61: ✗ not on list | P61: 0.581 | Q61: 6 | R61: 0.527 | S61: 0.652 | T61: 0.531 | U61: 0.112 | V61: 11224 | W61: =IFERROR(G61*INDEX('Charts data (helper)'!$BI$119:$DZ$128,MATCH($Q$3,'Charts data (helper)'!$BH$119:$BH$128,0),MATCH($B61,'Charts data (helper)'!$BI$118:$DZ$118,0))/INDEX('Charts data (helper)'!$BI$119:$DZ$128,MATCH(0.07,'Charts data (helper)'!$BH$119:$BH$128,0),MATCH($B61,'Charts data (helper)'!$BI$118:$DZ$118,0)),G61) | X61: =RANK(W61,$W$6:$W$76,1)
A62: 57 | B62: Chevy Colorado | C62: Truck | D62: gas | E62: 60k mi → ~2021 | F62: 23500 | G62: =0.3682+(F62-23500)/145400+0.03691*$D$3+0.0*$F$3 | H62: =0.3876+(F62-23500)/145400+0.03691*$D$3+0.0*$F$3 | I62: =0.4084+(F62-23500)/145400+0.03691*$D$3+0.0*$F$3 | J62: =0.4139+(F62-23500)/98000+0.03691*$D$3+0.0*$F$3 | K62: =0.03691*$D$3+0.0*$F$3 | L62: =G62-K62 | M62: 1720 | N62: live listings ~60k mi, $19,500-$27,000 | O62: ✗ not supported | P62: 0.58 | Q62: 6 | R62: 0.535 | S62: 0.627 | T62: 0.519 | U62: 0.183 | V62: 26586 | W62: =IFERROR(G62*INDEX('Charts data (helper)'!$BI$119:$DZ$128,MATCH($Q$3,'Charts data (helper)'!$BH$119:$BH$128,0),MATCH($B62,'Charts data (helper)'!$BI$118:$DZ$118,0))/INDEX('Charts data (helper)'!$BI$119:$DZ$128,MATCH(0.07,'Charts data (helper)'!$BH$119:$BH$128,0),MATCH($B62,'Charts data (helper)'!$BI$118:$DZ$118,0)),G62) | X62: =RANK(W62,$W$6:$W$76,1)
A63: 58 | B63: Kia Telluride | C63: SUV AWD | D63: gas | E63: 45k mi → ~2023 | F63: 33000 | G63: =0.3956+(F63-33000)/155200+0.03266*$D$3+0.0*$F$3 | H63: =0.4132+(F63-33000)/155200+0.03266*$D$3+0.0*$F$3 | I63: =0.4318+(F63-33000)/155200+0.03266*$D$3+0.0*$F$3 | J63: =0.4424+(F63-33000)/109000+0.03266*$D$3+0.0*$F$3 | K63: =0.03266*$D$3+0.0*$F$3 | L63: =G63-K63 | M63: 1720 | N63: live listings ~45k mi, $28,000-$37,500 | O63: ✗ not on list | P63: 0.579 | Q63: 6 | R63: 0.53 | S63: 0.624 | T63: 0.575 | U63: 0.264 | V63: 41014 | W63: =IFERROR(G63*INDEX('Charts data (helper)'!$BI$119:$DZ$128,MATCH($Q$3,'Charts data (helper)'!$BH$119:$BH$128,0),MATCH($B63,'Charts data (helper)'!$BI$118:$DZ$118,0))/INDEX('Charts data (helper)'!$BI$119:$DZ$128,MATCH(0.07,'Charts data (helper)'!$BH$119:$BH$128,0),MATCH($B63,'Charts data (helper)'!$BI$118:$DZ$118,0)),G63) | X63: =RANK(W63,$W$6:$W$76,1)
A64: 59 | B64: Mazda CX-90 | C64: SUV AWD | D64: gas | E64: 30k mi → ~2024 | F64: 38750 | G64: =0.4315+(F64-38750)/170200+0.02764*$D$3+0.0*$F$3 | H64: =0.4501+(F64-38750)/170200+0.02764*$D$3+0.0*$F$3 | I64: =0.4679+(F64-38750)/170200+0.02764*$D$3+0.0*$F$3 | J64: =0.4786+(F64-38750)/124000+0.02764*$D$3+0.0*$F$3 | K64: =0.02764*$D$3+0.0*$F$3 | L64: =G64-K64 | M64: 1720 | N64: live listings ~30k mi, $32,500-$44,500 | O64: ✗ not on list | P64: 0.569 | Q64: 6 | R64: 0.535 | S64: 0.632 | T64: 0.533 | U64: 0.324 | V64: 55217 | W64: =IFERROR(G64*INDEX('Charts data (helper)'!$BI$119:$DZ$128,MATCH($Q$3,'Charts data (helper)'!$BH$119:$BH$128,0),MATCH($B64,'Charts data (helper)'!$BI$118:$DZ$118,0))/INDEX('Charts data (helper)'!$BI$119:$DZ$128,MATCH(0.07,'Charts data (helper)'!$BH$119:$BH$128,0),MATCH($B64,'Charts data (helper)'!$BI$118:$DZ$118,0)),G64) | X64: =RANK(W64,$W$6:$W$76,1)
A65: 60 | B65: Chevy Traverse | C65: SUV AWD | D65: gas | E65: 70k mi → ~2021 | F65: 20000 | G65: =0.3875+(F65-20000)/114600+0.03586*$D$3+0.0*$F$3 | H65: =0.4127+(F65-20000)/114600+0.03586*$D$3+0.0*$F$3 | I65: =0.4424+(F65-20000)/114600+0.03586*$D$3+0.0*$F$3 | J65: =0.4272+(F65-20000)/72000+0.03586*$D$3+0.0*$F$3 | K65: =0.03586*$D$3+0.0*$F$3 | L65: =G65-K65 | M65: 1680 | N65: live listings ~70k mi, $17,000-$23,000 | O65: ✗ not on list | P65: 0.595 | Q65: 6 | R65: 0.538 | S65: 0.659 | T65: 0.547 | U65: 0.142 | V65: 16313 | W65: =IFERROR(G65*INDEX('Charts data (helper)'!$BI$119:$DZ$128,MATCH($Q$3,'Charts data (helper)'!$BH$119:$BH$128,0),MATCH($B65,'Charts data (helper)'!$BI$118:$DZ$118,0))/INDEX('Charts data (helper)'!$BI$119:$DZ$128,MATCH(0.07,'Charts data (helper)'!$BH$119:$BH$128,0),MATCH($B65,'Charts data (helper)'!$BI$118:$DZ$118,0)),G65) | X65: =RANK(W65,$W$6:$W$76,1)
A66: 61 | B66: VW Atlas | C66: SUV AWD | D66: gas | E66: 65k mi → ~2021 | F66: 21000 | G66: =0.3984+(F66-21000)/124800+0.03502*$D$3+0.0*$F$3 | H66: =0.4187+(F66-21000)/124800+0.03502*$D$3+0.0*$F$3 | I66: =0.4458+(F66-21000)/124800+0.03502*$D$3+0.0*$F$3 | J66: =0.4378+(F66-21000)/81000+0.03502*$D$3+0.0*$F$3 | K66: =0.03502*$D$3+0.0*$F$3 | L66: =G66-K66 | M66: 1760 | N66: live listings ~65k mi, $17,500-$24,000 | O66: ◑ VW MQB community port, select yrs | P66: 0.58 | Q66: 6 | R66: 0.543 | S66: 0.656 | T66: 0.516 | U66: 0.154 | V66: 19207 | W66: =IFERROR(G66*INDEX('Charts data (helper)'!$BI$119:$DZ$128,MATCH($Q$3,'Charts data (helper)'!$BH$119:$BH$128,0),MATCH($B66,'Charts data (helper)'!$BI$118:$DZ$118,0))/INDEX('Charts data (helper)'!$BI$119:$DZ$128,MATCH(0.07,'Charts data (helper)'!$BH$119:$BH$128,0),MATCH($B66,'Charts data (helper)'!$BI$118:$DZ$118,0)),G66) | X66: =RANK(W66,$W$6:$W$76,1)
A67: 62 | B67: Ford Explorer | C67: SUV AWD | D67: gas | E67: 70k mi → ~2021 | F67: 21000 | G67: =0.3961+(F67-21000)/114600+0.03586*$D$3+0.0*$F$3 | H67: =0.4218+(F67-21000)/114600+0.03586*$D$3+0.0*$F$3 | I67: =0.4507+(F67-21000)/114600+0.03586*$D$3+0.0*$F$3 | J67: =0.4437+(F67-21000)/72000+0.03586*$D$3+0.0*$F$3 | K67: =0.03586*$D$3+0.0*$F$3 | L67: =G67-K67 | M67: 1720 | N67: live listings ~70k mi, $17,500-$24,000 | O67: ✗ not on list | P67: 0.606 | Q67: 6 | R67: 0.542 | S67: 0.667 | T67: 0.592 | U67: 0.149 | V67: 17128 | W67: =IFERROR(G67*INDEX('Charts data (helper)'!$BI$119:$DZ$128,MATCH($Q$3,'Charts data (helper)'!$BH$119:$BH$128,0),MATCH($B67,'Charts data (helper)'!$BI$118:$DZ$118,0))/INDEX('Charts data (helper)'!$BI$119:$DZ$128,MATCH(0.07,'Charts data (helper)'!$BH$119:$BH$128,0),MATCH($B67,'Charts data (helper)'!$BI$118:$DZ$118,0)),G67) | X67: =RANK(W67,$W$6:$W$76,1)
A68: 63 | B68: Buick Enclave | C68: SUV AWD | D68: gas | E68: 90k mi → ~2019 | F68: 16667 | G68: =0.396+(F68-16667)/94600+0.0376*$D$3+0.0*$F$3 | H68: =0.4241+(F68-16667)/94600+0.0376*$D$3+0.0*$F$3 | I68: =0.4543+(F68-16667)/94600+0.0376*$D$3+0.0*$F$3 | J68: =0.4474+(F68-16667)/52000+0.0376*$D$3+0.0*$F$3 | K68: =0.0376*$D$3+0.0*$F$3 | L68: =G68-K68 | M68: 1800 | N68: live listings ~90k mi, $14,000-$19,000 | O68: ✗ not on comma list | P68: 0.617 | Q68: 7 | R68: 0.553 | S68: 0.684 | T68: 0.617 | U68: 0.112 | V68: 10603 | W68: =IFERROR(G68*INDEX('Charts data (helper)'!$BI$119:$DZ$128,MATCH($Q$3,'Charts data (helper)'!$BH$119:$BH$128,0),MATCH($B68,'Charts data (helper)'!$BI$118:$DZ$118,0))/INDEX('Charts data (helper)'!$BI$119:$DZ$128,MATCH(0.07,'Charts data (helper)'!$BH$119:$BH$128,0),MATCH($B68,'Charts data (helper)'!$BI$118:$DZ$118,0)),G68) | X68: =RANK(W68,$W$6:$W$76,1)
A69: 64 | B69: Volvo XC60 | C69: SUV AWD | D69: gas | E69: 65k mi → ~2021 | F69: 25200 | G69: =0.4486+(F69-25200)/135200+0.03121*$D$3+0.0*$F$3 | H69: =0.472+(F69-25200)/135200+0.03121*$D$3+0.0*$F$3 | I69: =0.4985+(F69-25200)/135200+0.03121*$D$3+0.0*$F$3 | J69: =0.5016+(F69-25200)/89000+0.03121*$D$3+0.0*$F$3 | K69: =0.03121*$D$3+0.0*$F$3 | L69: =G69-K69 | M69: 1880 | N69: live listings ~65k mi, $21,000-$28,500 | O69: ✗ not on comma list | P69: 0.605 | Q69: 7 | R69: 0.566 | S69: 0.69 | T69: 0.591 | U69: 0.19 | V69: 25732 | W69: =IFERROR(G69*INDEX('Charts data (helper)'!$BI$119:$DZ$128,MATCH($Q$3,'Charts data (helper)'!$BH$119:$BH$128,0),MATCH($B69,'Charts data (helper)'!$BI$118:$DZ$118,0))/INDEX('Charts data (helper)'!$BI$119:$DZ$128,MATCH(0.07,'Charts data (helper)'!$BH$119:$BH$128,0),MATCH($B69,'Charts data (helper)'!$BI$118:$DZ$118,0)),G69) | X69: =RANK(W69,$W$6:$W$76,1)
A70: 65 | B70: Chevy Tahoe | C70: SUV AWD | D70: gas | E70: 55k mi → ~2022 | F70: 39375 | G70: =0.4119+(F70-39375)/185500+0.04008*$D$3+0.0*$F$3 | H70: =0.4347+(F70-39375)/185500+0.04008*$D$3+0.0*$F$3 | I70: =0.4555+(F70-39375)/185500+0.04008*$D$3+0.0*$F$3 | J70: =0.4719+(F70-39375)/130000+0.04008*$D$3+0.0*$F$3 | K70: =0.04008*$D$3+0.0*$F$3 | L70: =G70-K70 | M70: 1880 | N70: live listings ~55k mi, $33,000-$45,000 | O70: ✗ not on list | P70: 0.625 | Q70: 7 | R70: 0.577 | S70: 0.685 | T70: 0.543 | U70: 0.345 | V70: 64021 | W70: =IFERROR(G70*INDEX('Charts data (helper)'!$BI$119:$DZ$128,MATCH($Q$3,'Charts data (helper)'!$BH$119:$BH$128,0),MATCH($B70,'Charts data (helper)'!$BI$118:$DZ$118,0))/INDEX('Charts data (helper)'!$BI$119:$DZ$128,MATCH(0.07,'Charts data (helper)'!$BH$119:$BH$128,0),MATCH($B70,'Charts data (helper)'!$BI$118:$DZ$118,0)),G70) | X70: =RANK(W70,$W$6:$W$76,1)
A71: 66 | B71: Jeep Grand Cherokee L | C71: SUV AWD | D71: gas | E71: 55k mi → ~2022 | F71: 28600 | G71: =0.4254+(F71-28600)/129600+0.03827*$D$3+0.0*$F$3 | H71: =0.4482+(F71-28600)/129600+0.03827*$D$3+0.0*$F$3 | I71: =0.4707+(F71-28600)/129600+0.03827*$D$3+0.0*$F$3 | J71: =0.4726+(F71-28600)/87000+0.03827*$D$3+0.0*$F$3 | K71: =0.03827*$D$3+0.0*$F$3 | L71: =G71-K71 | M71: 1760 | N71: live listings ~55k mi, $24,000-$32,500 | O71: ✗ not on list | P71: 0.641 | Q71: 7 | R71: 0.591 | S71: 0.695 | T71: 0.546 | U71: 0.213 | V71: 27544 | W71: =IFERROR(G71*INDEX('Charts data (helper)'!$BI$119:$DZ$128,MATCH($Q$3,'Charts data (helper)'!$BH$119:$BH$128,0),MATCH($B71,'Charts data (helper)'!$BI$118:$DZ$118,0))/INDEX('Charts data (helper)'!$BI$119:$DZ$128,MATCH(0.07,'Charts data (helper)'!$BH$119:$BH$128,0),MATCH($B71,'Charts data (helper)'!$BI$118:$DZ$118,0)),G71) | X71: =RANK(W71,$W$6:$W$76,1)
A72: 67 | B72: Volvo V90 Cross Country | C72: SUV AWD | D72: gas | E72: 65k mi → ~2021 | F72: 29800 | G72: =0.4834+(F72-29800)/135200+0.02871*$D$3+0.0*$F$3 | H72: =0.5082+(F72-29800)/135200+0.02871*$D$3+0.0*$F$3 | I72: =0.5358+(F72-29800)/135200+0.02871*$D$3+0.0*$F$3 | J72: =0.5423+(F72-29800)/89000+0.02871*$D$3+0.0*$F$3 | K72: =0.02871*$D$3+0.0*$F$3 | L72: =G72-K72 | M72: 1880 | N72: live listings ~65k mi, $25,000-$34,000 | O72: ✗ not on comma list | P72: 0.626 | Q72: 7 | R72: 0.584 | S72: 0.715 | T72: 0.499 | U72: 0.225 | V72: 30429 | W72: =IFERROR(G72*INDEX('Charts data (helper)'!$BI$119:$DZ$128,MATCH($Q$3,'Charts data (helper)'!$BH$119:$BH$128,0),MATCH($B72,'Charts data (helper)'!$BI$118:$DZ$118,0))/INDEX('Charts data (helper)'!$BI$119:$DZ$128,MATCH(0.07,'Charts data (helper)'!$BH$119:$BH$128,0),MATCH($B72,'Charts data (helper)'!$BI$118:$DZ$118,0)),G72) | X72: =RANK(W72,$W$6:$W$76,1)
A73: 68 | B73: Chevy Suburban | C73: SUV AWD | D73: gas | E73: 55k mi → ~2022 | F73: 42375 | G73: =0.424+(F73-42375)/189400+0.03974*$D$3+0.0*$F$3 | H73: =0.4468+(F73-42375)/189400+0.03974*$D$3+0.0*$F$3 | I73: =0.4689+(F73-42375)/189400+0.03974*$D$3+0.0*$F$3 | J73: =0.4906+(F73-42375)/133000+0.03974*$D$3+0.0*$F$3 | K73: =0.03974*$D$3+0.0*$F$3 | L73: =G73-K73 | M73: 1920 | N73: live listings ~55k mi, $36,000-$48,500 | O73: ✗ not on list | P73: 0.636 | Q73: 7 | R73: 0.589 | S73: 0.701 | T73: 0.871 | U73: 0.376 | V73: 71181 | W73: =IFERROR(G73*INDEX('Charts data (helper)'!$BI$119:$DZ$128,MATCH($Q$3,'Charts data (helper)'!$BH$119:$BH$128,0),MATCH($B73,'Charts data (helper)'!$BI$118:$DZ$118,0))/INDEX('Charts data (helper)'!$BI$119:$DZ$128,MATCH(0.07,'Charts data (helper)'!$BH$119:$BH$128,0),MATCH($B73,'Charts data (helper)'!$BI$118:$DZ$118,0)),G73) | X73: =RANK(W73,$W$6:$W$76,1)
A74: 69 | B74: Volvo XC90 | C74: SUV AWD | D74: gas | E74: 70k mi → ~2021 | F74: 30000 | G74: =0.5209+(F74-30000)/125000+0.03341*$D$3+0.0*$F$3 | H74: =0.5556+(F74-30000)/125000+0.03341*$D$3+0.0*$F$3 | I74: =0.5998+(F74-30000)/125000+0.03341*$D$3+0.0*$F$3 | J74: =0.5879+(F74-30000)/80000+0.03341*$D$3+0.0*$F$3 | K74: =0.03341*$D$3+0.0*$F$3 | L74: =G74-K74 | M74: 1920 | N74: live listings ~70k mi, $25,500-$34,500 | O74: ✗ not on comma list | P74: 0.691 | Q74: 8 | R74: 0.635 | S74: 0.811 | T74: 0.98 | U74: 0.22 | V74: 27499 | W74: =IFERROR(G74*INDEX('Charts data (helper)'!$BI$119:$DZ$128,MATCH($Q$3,'Charts data (helper)'!$BH$119:$BH$128,0),MATCH($B74,'Charts data (helper)'!$BI$118:$DZ$118,0))/INDEX('Charts data (helper)'!$BI$119:$DZ$128,MATCH(0.07,'Charts data (helper)'!$BH$119:$BH$128,0),MATCH($B74,'Charts data (helper)'!$BI$118:$DZ$118,0)),G74) | X74: =RANK(W74,$W$6:$W$76,1)
A75: 70 | B75: Porsche 996 Carrera | C75: Sport | D75: gas | E75: 55k mi → ~2004 | F75: 38833 | G75: =0.6442+(F75-38833)/153000+0.03628*$D$3+0.0*$F$3 | H75: =0.6541+(F75-38833)/153000+0.03628*$D$3+0.0*$F$3 | I75: =0.6738+(F75-38833)/153000+0.03628*$D$3+0.0*$F$3 | J75: =0.6439+(F75-38833)/105000+0.03628*$D$3+0.0*$F$3 | K75: =0.03628*$D$3+0.0*$F$3 | L75: =G75-K75 | M75: 1760 | N75: live listings ~55k mi, $33,000-$44,500 | O75: ✗ it's a 2000s Porsche | P75: 0.804 | Q75: 9 | R75: 0.821 | S75: 0.91 | T75: 0.997 | U75: 0.112 | V75: 17068 | W75: =IFERROR(G75*INDEX('Charts data (helper)'!$BI$119:$DZ$128,MATCH($Q$3,'Charts data (helper)'!$BH$119:$BH$128,0),MATCH($B75,'Charts data (helper)'!$BI$118:$DZ$118,0))/INDEX('Charts data (helper)'!$BI$119:$DZ$128,MATCH(0.07,'Charts data (helper)'!$BH$119:$BH$128,0),MATCH($B75,'Charts data (helper)'!$BI$118:$DZ$118,0)),G75) | X75: =RANK(W75,$W$6:$W$76,1)
A76: 71 | B76: Porsche 996 Turbo | C76: Sport | D76: gas | E76: 55k mi → ~2005 | F76: 60333 | G76: =0.8278+(F76-60333)/166000+0.03938*$D$3+0.0*$F$3 | H76: =0.8415+(F76-60333)/166000+0.03938*$D$3+0.0*$F$3 | I76: =0.8588+(F76-60333)/166000+0.03938*$D$3+0.0*$F$3 | J76: =0.829+(F76-60333)/115000+0.03938*$D$3+0.0*$F$3 | K76: =0.03938*$D$3+0.0*$F$3 | L76: =G76-K76 | M76: 1920 | N76: live listings ~55k mi, $51,000-$69,000 | O76: ✗ it's a 2000s Porsche | P76: 0.983 | Q76: 10 | R76: 1.014 | S76: 1.093 | T76: — | U76: 0.16 | V76: 26518 | W76: =IFERROR(G76*INDEX('Charts data (helper)'!$BI$119:$DZ$128,MATCH($Q$3,'Charts data (helper)'!$BH$119:$BH$128,0),MATCH($B76,'Charts data (helper)'!$BI$118:$DZ$118,0))/INDEX('Charts data (helper)'!$BI$119:$DZ$128,MATCH(0.07,'Charts data (helper)'!$BH$119:$BH$128,0),MATCH($B76,'Charts data (helper)'!$BI$118:$DZ$118,0)),G76) | X76: =RANK(W76,$W$6:$W$76,1)
A78: STATISTICAL SIGNIFICANCE (from the Monte-Carlo draws): "Stat. tier" groups cars that are NOT statistically distinguishable — same colour = a statistical tie, so ordering within a tier is noise, not signal. "90% band low/high" = the range your actual $/mi is 90% likely to land in (outcome spread, not estimation error). "Beats next rank (P)" = probability this car truly comes in cheaper than the one directly below it (≈50% = coin-flip tie; >85% = a real gap). The Monte-Carlo estimation error on each median is tiny (±$0.001-0.002 at N=1,100), so the uncertainty you see is real-world outcome spread, not simulation noise. OPPORTUNITY COST (a function of PURCHASE PRICE, not odometer): "Foregone mkt growth (life $)" = purchase price × ((1.07)^years − 1) — the S&P return you give up by committing that cash to the car instead of the market. Pay more, forgo more. This is a SEPARATE future-value lens, NOT a line item added to the $/mi: the headline $/mi already accounts for the time value of money by discounting at 7% (a present-value method). Both express the same fact — capital tied in a car isn't compounding in the market. | Q78: HOW TO READ COLS Q–V ↓
A82: METHOD (per your request): STEP 1 = pull verified cars.com listings across many odometers per vehicle (the 7 highest-volume models use wide multi-year pulls; others use narrower verified anchors). STEP 2 = that becomes the price-vs-odometer curve; the BUY POINT is the cost-optimal point on it, taken as the cheapest-to-buy odometer still within 1.5 cents/mile of the theoretical minimum (same $/mile, least capital). One verified price flows through everything; the Verify link is a live search centered on that exact odo/price band. P50 = median lifetime cost/mile; P90 = "bad-luck" tail (major repairs / battery). "$/mi if EOL=empirical" re-runs at raw iSeeCars retirement mileage (no maintained-survival bonus) — the pessimistic case; it hammers short-life cars (Tucson, Rogue, Escape) and barely touches the durable ones. EDIT THE PURCHASE PRICE: the yellow "Purchase $" column is live — type a real price you found and the P50/P75/P90/empirical columns AND the heat map recompute instantly. NOTE (v2b): this live edit only rescales the depreciation term (each $1 = 1/lifetime-miles per mile); it does NOT re-derive the use tax, total-loss charge, or the $6k full-coverage threshold, which in the full model also depend on price — so a big manual price change slightly under-adjusts $/mi. For an exact figure, change the price in the source and rebuild. Fixes applied vs prior version: empirical EOL + uniform 1.30 survival multiplier; probabilistic major-repair tail past 120k; real per-model insurance that DROPS to liability-only ($1176/yr, ×0.8 USAA) once the car is worth <$6k; FLORIDA flat registration $55/yr (home-of-record — NOT CA VLF/smog/ZEV); per-segment tires; EV battery as probability×cost (not flat), DC-fast-charge premium + degradation; 5% discounting; editable verified buy prices (see links).

Sheet Any-Car Calculator
A1: ANY-CAR CALCULATOR — TWO ways to use it. (1) PICK a car from the Vehicle dropdown at the top (one list of all 69), pick the Year, and type the ODOMETER and PRICE off a listing — it auto-fills everything else and shows live $/mile + rank. (2) Or type ANY off-lineup car (garage-kept 2008/90k, exotic, whatever) into a yellow row in the table below; the End-of-life reference is at the very bottom. (Built as a single dropdown, not a Make→Model cascade, because Google Sheets and Excel-for-Mac do not support dependent/INDIRECT dropdowns.) Deterministic closed-form (no P90 bands); ~$0.03-0.08/mi above the Ranking tab because it does not discount future fuel, but every car is computed identically so comparisons are fair. California energy + your USAA/Florida basis. YELLOW = edit; grey = formula.
A3: PICK A CAR ↓ (one dropdown = all 71 cars; auto-fills all but odometer & price)
A4: Vehicle | B4: Toyota RAV4 Hybrid | D4: EOL odo | E4: =IFERROR(INDEX(Lists!$D:$D,MATCH($B$4,Lists!$A:$A,0)),"?") | F4: Run $/mi | G4: =IFERROR(INDEX(Lists!$G:$G,MATCH($B$4,Lists!$A:$A,0)),"?") | H4: Scrap $ | I4: =IFERROR(INDEX(Lists!$K:$K,MATCH($B$4,Lists!$A:$A,0)),"?")
A5: Year | B5: 2023 | D5: MPG | E5: =IFERROR(INDEX(Lists!$E:$E,MATCH($B$4,Lists!$A:$A,0)),"?") | F5: Ins $/yr | G5: =IFERROR(INDEX(Lists!$H:$H,MATCH($B$4,Lists!$A:$A,0)),"?") | H5: Year rel. × | I5: =IF(ISNUMBER(SEARCH($B$5,IFERROR(INDEX(Lists!$P:$P,MATCH($B$4,Lists!$A:$A,0)),""))),1.4,IF(ISNUMBER(SEARCH($B$5,IFERROR(INDEX(Lists!$Q:$Q,MATCH($B$4,Lists!$A:$A,0)),""))),1.15,IF(ISNUMBER(SEARCH($B$5,IFERROR(INDEX(Lists!$R:$R,MATCH($B$4,Lists!$A:$A,0)),""))),0.95,1)))
A6: Odometer (mi) — from listing | B6: 40000 | D6: kWh/100 | E6: =IFERROR(INDEX(Lists!$F:$F,MATCH($B$4,Lists!$A:$A,0)),"?") | F6: Tires $/mi | G6: =IFERROR(INDEX(Lists!$I:$I,MATCH($B$4,Lists!$A:$A,0)),"?")
A7: Price $ — from listing | B7: 30444 | D7: YOUR PICK → | F7: =IFERROR(($B$7-$I$4)/($E$4-$B$6),0)+IF($E$5>0,'Ranking (hardened)'!$D$3/$E$5,0)+IF($E$6>0,($E$6/100)*'Ranking (hardened)'!$F$3,0)+$G$4*(1+MAX(0,(($B$6+$E$4)/2-100000)/100000)*0.5)*$I$5+($G$5*0.35+1176*0.65)/13000+55/13000+9*(2026-$B$5)/13000+$G$6 | G7: $/mi | H7: =COUNTIF(Lists!$L$2:$L$72,"<"&$F$7)+1 | I7: rank / 71
A8: For this MODEL (survey stats) → | C8: Stat tier | D8: =IFERROR(INDEX(Lists!$T:$T,MATCH($B$4,Lists!$A:$A,0)),"custom") | E8: 90% band $/mi | F8: =IFERROR(TEXT(INDEX(Lists!$U:$U,MATCH($B$4,Lists!$A:$A,0)),"$0.000")&" – "&TEXT(INDEX(Lists!$V:$V,MATCH($B$4,Lists!$A:$A,0)),"$0.000"),"n/a (custom)") | H8: Opp cost $/mi (on YOUR price) | I8: =IFERROR($B$7*((1+0.07)^(($E$4-$B$6)/13000)-1)/($E$4-$B$6),0)
A9: — OR type any off-lineup car into a yellow row below (or just type a name in the Vehicle box) —
A12: Vehicle | B12: Class | C12: Purchase $ | D12: Resale $ (at end) | E12: Buy odo (mi) | F12: Model year | G12: End-of-life odo (mi) | H12: MPG (gas,0=EV) | I12: kWh/ 100mi | J12: Run cost $/mi (base) | K12: Insurance full $/yr | L12: Tires $/mi | M12: Life miles | N12: Deprec. $/mi | O12: Fuel/energy $/mi | P12: Repair+maint $/mi | Q12: Insurance $/mi | R12: Registr. $/mi | S12: Age $/mi | T12: TOTAL $/mile
A13: Chevy Bolt EV | B13: EV | C13: 15643 | D13: 600 | E13: 45000 | F13: 2023 | G13: 200200 | H13: 0 | I13: 30.2 | J13: 0.045 | K13: 1660 | L13: 0.03 | M13: =G13-E13 | N13: =IFERROR((C13-D13)/M13,"") | O13: =IF(H13>0,'Ranking (hardened)'!$D$3/H13,0)+IF(I13>0,(I13/100)*'Ranking (hardened)'!$F$3,0) | P13: =J13*(1+MAX(0,((E13+G13)/2-100000)/100000)*0.5) | Q13: =(K13*0.35+650*0.65)/13000 | R13: =55/13000 | S13: =9*(2026-F13)/13000 | T13: =IFERROR(N13+O13+P13+Q13+R13+S13+L13,"")
A14: Chevy Volt | B14: PHEV | C14: 15143 | D14: 600 | E14: 55000 | F14: 2019 | G14: 200200 | H14: 210 | I14: 26 | J14: 0.065 | K14: 1440 | L14: 0.024 | M14: =G14-E14 | N14: =IFERROR((C14-D14)/M14,"") | O14: =IF(H14>0,'Ranking (hardened)'!$D$3/H14,0)+IF(I14>0,(I14/100)*'Ranking (hardened)'!$F$3,0) | P14: =J14*(1+MAX(0,((E14+G14)/2-100000)/100000)*0.5) | Q14: =(K14*0.35+650*0.65)/13000 | R14: =55/13000 | S14: =9*(2026-F14)/13000 | T14: =IFERROR(N14+O14+P14+Q14+R14+S14+L14,"")
A15: Toyota Prius (hybrid) | B15: Car | C15: 26000 | D15: 400 | E15: 40000 | F15: 2023 | G15: 249600 | H15: 50 | I15: 0 | J15: 0.045 | K15: 1800 | L15: 0.018 | M15: =G15-E15 | N15: =IFERROR((C15-D15)/M15,"") | O15: =IF(H15>0,'Ranking (hardened)'!$D$3/H15,0)+IF(I15>0,(I15/100)*'Ranking (hardened)'!$F$3,0) | P15: =J15*(1+MAX(0,((E15+G15)/2-100000)/100000)*0.5) | Q15: =(K15*0.35+650*0.65)/13000 | R15: =55/13000 | S15: =9*(2026-F15)/13000 | T15: =IFERROR(N15+O15+P15+Q15+R15+S15+L15,"")
A16: Toyota Prius Prime | B16: PHEV | C16: 15000 | D16: 600 | E16: 90000 | F16: 2019 | G16: 235300 | H16: 120 | I16: 14.4 | J16: 0.045 | K16: 1920 | L16: 0.024 | M16: =G16-E16 | N16: =IFERROR((C16-D16)/M16,"") | O16: =IF(H16>0,'Ranking (hardened)'!$D$3/H16,0)+IF(I16>0,(I16/100)*'Ranking (hardened)'!$F$3,0) | P16: =J16*(1+MAX(0,((E16+G16)/2-100000)/100000)*0.5) | Q16: =(K16*0.35+650*0.65)/13000 | R16: =55/13000 | S16: =9*(2026-F16)/13000 | T16: =IFERROR(N16+O16+P16+Q16+R16+S16+L16,"")
A17: Toyota Corolla | B17: Car | C17: 17659 | D17: 400 | E17: 55000 | F17: 2022 | G17: 249600 | H17: 31 | I17: 0 | J17: 0.045 | K17: 1920 | L17: 0.018 | M17: =G17-E17 | N17: =IFERROR((C17-D17)/M17,"") | O17: =IF(H17>0,'Ranking (hardened)'!$D$3/H17,0)+IF(I17>0,(I17/100)*'Ranking (hardened)'!$F$3,0) | P17: =J17*(1+MAX(0,((E17+G17)/2-100000)/100000)*0.5) | Q17: =(K17*0.35+650*0.65)/13000 | R17: =55/13000 | S17: =9*(2026-F17)/13000 | T17: =IFERROR(N17+O17+P17+Q17+R17+S17+L17,"")
A18: Toyota Camry Hybrid | B18: Car | C18: 16500 | D18: 400 | E18: 80000 | F18: 2020 | G18: 249600 | H18: 42 | I18: 0 | J18: 0.045 | K18: 1920 | L18: 0.018 | M18: =G18-E18 | N18: =IFERROR((C18-D18)/M18,"") | O18: =IF(H18>0,'Ranking (hardened)'!$D$3/H18,0)+IF(I18>0,(I18/100)*'Ranking (hardened)'!$F$3,0) | P18: =J18*(1+MAX(0,((E18+G18)/2-100000)/100000)*0.5) | Q18: =(K18*0.35+650*0.65)/13000 | R18: =55/13000 | S18: =9*(2026-F18)/13000 | T18: =IFERROR(N18+O18+P18+Q18+R18+S18+L18,"")
A19: Honda Civic | B19: Car | C19: 23789 | D19: 400 | E19: 35000 | F19: 2023 | G19: 235300 | H19: 32 | I19: 0 | J19: 0.045 | K19: 1840 | L19: 0.018 | M19: =G19-E19 | N19: =IFERROR((C19-D19)/M19,"") | O19: =IF(H19>0,'Ranking (hardened)'!$D$3/H19,0)+IF(I19>0,(I19/100)*'Ranking (hardened)'!$F$3,0) | P19: =J19*(1+MAX(0,((E19+G19)/2-100000)/100000)*0.5) | Q19: =(K19*0.35+650*0.65)/13000 | R19: =55/13000 | S19: =9*(2026-F19)/13000 | T19: =IFERROR(N19+O19+P19+Q19+R19+S19+L19,"")
A20: Nissan Leaf | B20: EV | C20: 11667 | D20: 600 | E20: 45000 | F20: 2023 | G20: 140400 | H20: 0 | I20: 32.4 | J20: 0.065 | K20: 1760 | L20: 0.03 | M20: =G20-E20 | N20: =IFERROR((C20-D20)/M20,"") | O20: =IF(H20>0,'Ranking (hardened)'!$D$3/H20,0)+IF(I20>0,(I20/100)*'Ranking (hardened)'!$F$3,0) | P20: =J20*(1+MAX(0,((E20+G20)/2-100000)/100000)*0.5) | Q20: =(K20*0.35+650*0.65)/13000 | R20: =55/13000 | S20: =9*(2026-F20)/13000 | T20: =IFERROR(N20+O20+P20+Q20+R20+S20+L20,"")
A21: Hyundai Elantra | B21: Car | C21: 16000 | D21: 400 | E21: 45000 | F21: 2023 | G21: 200200 | H21: 35 | I21: 0 | J21: 0.065 | K21: 1640 | L21: 0.018 | M21: =G21-E21 | N21: =IFERROR((C21-D21)/M21,"") | O21: =IF(H21>0,'Ranking (hardened)'!$D$3/H21,0)+IF(I21>0,(I21/100)*'Ranking (hardened)'!$F$3,0) | P21: =J21*(1+MAX(0,((E21+G21)/2-100000)/100000)*0.5) | Q21: =(K21*0.35+650*0.65)/13000 | R21: =55/13000 | S21: =9*(2026-F21)/13000 | T21: =IFERROR(N21+O21+P21+Q21+R21+S21+L21,"")
A22: Honda Accord | B22: Car | C22: 16143 | D22: 400 | E22: 70000 | F22: 2021 | G22: 240500 | H22: 31 | I22: 0 | J22: 0.045 | K22: 1840 | L22: 0.018 | M22: =G22-E22 | N22: =IFERROR((C22-D22)/M22,"") | O22: =IF(H22>0,'Ranking (hardened)'!$D$3/H22,0)+IF(I22>0,(I22/100)*'Ranking (hardened)'!$F$3,0) | P22: =J22*(1+MAX(0,((E22+G22)/2-100000)/100000)*0.5) | Q22: =(K22*0.35+650*0.65)/13000 | R22: =55/13000 | S22: =9*(2026-F22)/13000 | T22: =IFERROR(N22+O22+P22+Q22+R22+S22+L22,"")
A23: Kia K4 | B23: Car | C23: 20125 | D23: 400 | E23: 18000 | F23: 2025 | G23: 189800 | H23: 34 | I23: 0 | J23: 0.065 | K23: 1640 | L23: 0.018 | M23: =G23-E23 | N23: =IFERROR((C23-D23)/M23,"") | O23: =IF(H23>0,'Ranking (hardened)'!$D$3/H23,0)+IF(I23>0,(I23/100)*'Ranking (hardened)'!$F$3,0) | P23: =J23*(1+MAX(0,((E23+G23)/2-100000)/100000)*0.5) | Q23: =(K23*0.35+650*0.65)/13000 | R23: =55/13000 | S23: =9*(2026-F23)/13000 | T23: =IFERROR(N23+O23+P23+Q23+R23+S23+L23,"")
A24: Mazda3 (SkyActiv) | B24: Car | C24: 15000 | D24: 400 | E24: 65000 | F24: 2021 | G24: 210600 | H24: 30 | I24: 0 | J24: 0.045 | K24: 1720 | L24: 0.018 | M24: =G24-E24 | N24: =IFERROR((C24-D24)/M24,"") | O24: =IF(H24>0,'Ranking (hardened)'!$D$3/H24,0)+IF(I24>0,(I24/100)*'Ranking (hardened)'!$F$3,0) | P24: =J24*(1+MAX(0,((E24+G24)/2-100000)/100000)*0.5) | Q24: =(K24*0.35+650*0.65)/13000 | R24: =55/13000 | S24: =9*(2026-F24)/13000 | T24: =IFERROR(N24+O24+P24+Q24+R24+S24+L24,"")
... A87: ‹ your car here — overwrite me › | B87: (EV) | C87: 20000 | D87: 1500 | E87: 40000 | F87: 2022 | G87: 180000 | H87: 0 | I87: 28 | J87: 0.05 | K87: 2300 | L87: 0.03 | M87: =G87-E87 | N87: =IFERROR((C87-D87)/M87,"") | O87: =IF(H87>0,'Ranking (hardened)'!$D$3/H87,0)+IF(I87>0,(I87/100)*'Ranking (hardened)'!$F$3,0) | P87: =J87*(1+MAX(0,((E87+G87)/2-100000)/100000)*0.5) | Q87: =(K87*0.35+650*0.65)/13000 | R87: =55/13000 | S87: =9*(2026-F87)/13000 | T87: =IFERROR(N87+O87+P87+Q87+R87+S87+L87,"")
A89: HOW EACH COLUMN WORKS — TOTAL $/mi = Depreciation + Fuel/energy + Repair&maint + Insurance + Registration + Age + Tires. Depreciation = (Purchase $ − RESALE $) ÷ life miles — this is why the Resale column matters: a normal car is scrap (~$500-1500) at end, but a cared-for enthusiast car (e.g. the 996) RETAINS most of its value, so its depreciation nearly vanishes and MAINTENANCE becomes the main cost. Put a resale ABOVE purchase to model slight appreciation (depreciation goes negative — a credit). Fuel = gas price ÷ MPG (and/or kWh/100 × electricity). Repair&maint = your base $/mi, rising +50% as average odometer passes 100k (set high for exotics). Insurance = lifetime blend (≈35% full + 65% liability). Age = small calendar-age surcharge ($9/yr of age ÷ annual miles) — separates a 2008/90k from a 2019/90k. TO ADD A CAR: copy a yellow row; type real price / RESALE / odometer / year / MPG (or kWh) / EOL, and a base run-cost (Toyota ≈0.045, mid ≈0.065, domestic/older ≈0.085, exotic ≈0.30). EOL = realistic end-of-life odometer (Toyota big SUV ~330k, econobox ~200-260k). The 996 now shows maintenance — not depreciation — as its dominant cost, per its value retention; its $/mi is high mainly because you drive it few miles, spreading fixed costs (insurance, upkeep) thin.
A97: END-OF-LIFE REFERENCE — typical odometer at which each class is RETIRED (empirical, ~iSeeCars), and the "maintained/non-crashed" figure this model actually uses (≈×1.30). Fill the End-of-life column from here instead of guessing; a garage-kept, dealer-serviced example earns the higher end, a neglected one the lower.
A98: Category (examples) | G98: Typical retirement (empirical) | J98: "Maintained" EOL (used here) | M98: Notes
A99: Toyota/Lexus car & crossover — Corolla, Camry, RAV4, Highlander, Prius | G99: 195–210k | J99: 255–275k | M99: hybrids the same; traction battery ~$2k once
A100: Toyota truck & body-on-frame — Tacoma, 4Runner, Sequoia | G100: 245–260k | J100: 320–340k | M100: the durability champions
A101: Honda — Civic, Accord, CR-V, Pilot, Odyssey | G101: 180–190k | J101: 235–245k | M101: watch older automatics/Odyssey trans
A102: Mazda — 3, CX-5, CX-90 | G102: 165–170k | J102: 215–220k | M102: solid; slightly behind Toyota/Honda
A103: Hyundai / Kia — Tucson, Telluride, Palisade | G103: 150–175k | J103: 195–230k | M103: newer models, thinner long-term data
A104: Subaru — Outback, Forester, Ascent | G104: 150–165k | J104: 195–215k | M104: CVT + head-gasket (older) history
A105: Domestic car/crossover — Equinox, Escape, Traverse, Explorer | G105: 150–160k | J105: 195–210k | M105: transmission is the usual life-limiter
A106: Domestic truck/big SUV — Tahoe, Suburban, Colorado, Ranger | G106: 160–215k | J106: 210–280k | M106: V8s go far; thirsty
A107: Volkswagen — Golf/GTI, Tiguan, Atlas | G107: 155–180k | J107: 200–235k | M107: turbo/coolant upkeep matters
A108: Volvo — XC60, XC90, V90 Cross Country | G108: 180–190k | J108: 235–250k | M108: reaches it, but repairs are pricey (~$800/yr)
A109: EV, liquid-cooled — Bolt, Model 3, ID.4 | G109: 150–175k | J109: battery-limited | M109: pack health, not the motor, sets EOL
... A111: German sport / exotic, driven modestly — 996 | G111: 150–180k | J111: (few miles/yr) | M111: maintenance, not mileage, ends it

Sheet Plot
A1: LAYER 4 — PLOT. X-axis = $/mile (P50). Pick the Y-axis from the yellow dropdown (B3) and BOTH charts update. Hover any point for the vehicle. Top chart colours by fuel, bottom by body style. The backing table lives on the "Plot data (helper)" tab.
A3: Y-axis → | B3: P90 $/mi (bad-luck) | C3: =" ↕ Y-AXIS = "&$B$3&" (units: "&IFERROR(INDEX('Plot data (helper)'!$D$4:$S$4,1,MATCH($B$3,'Plot data (helper)'!$D$5:$S$5,0)),"?")&")"
A4: KEY — colour: grey=gas · green=hybrid · blue=electric · purple=plug-in (top) / by body style (bottom). Hover a point for make·model·body·year.
A38: SAME POINTS, COLOURED BY BODY STYLE (Sheets ignores marker shapes on import) →

Sheet Charts
A1: LAYER 4 — CHARTS. Nine views a $/mile ranking cannot show. Charts 1-8 follow the 10 yellow dropdowns (A4:A13); chart 9 is the whole top-25 field. 1) Payback 2) Cost breakdown 3) Cheap vs risky 4) Annual-mileage 5) Space per dollar 6) Buy odometer 7) Gas price 8) Discount rate 9) Uncertainty bands (what we actually know). Backing data is on the "Charts data (helper)" tab.
A3: SELECT UP TO 10 CARS TO COMPARE (yellow dropdowns — default = current top 10) →
A4: Chevy Bolt EV
A5: Chevy Volt
A6: Toyota Prius (hybrid)
A7: Toyota Prius Prime
A8: Toyota Corolla
A9: Toyota Camry Hybrid
A10: Honda Civic
A11: Nissan Leaf
A12: Hyundai Elantra
A13: Honda Accord
A230: CHART 9 — each bar is a car's 90% cost range (P05→P95); the light/dark boundary is the median. Bars that overlap left-to-right are statistically indistinguishable — that overlap is the gap in what the model can tell you.

Sheet Beyond $ per mile
A1: BEYOND $/MILE — the adversarial review flagged that ranking on expected $/mile alone hides capital, risk, utility-per-dollar and pollution. These are the other quantifiable metrics to weigh (California base prices; a snapshot, not live). Greener = better in each column. $/mile is NOT the whole story: a car can win on $/mile yet tie up more cash, carry a fatter bad-luck tail, or cost far more per kid-seat. Use this to pick the metric that matches YOUR priority.
A3: Vehicle | B3: $/mi (P50) | C3: Bad-luck tail (P90−P50) | D3: Up-front capital | E3: 5yr / 75k-mi $/mi | F3: Seats | G3: $ per seat-mile | H3: Max cargo (cu ft) | I3: $/mi per cu-ft | J3: +$1/gal → Δ$/mi | K3: CO₂ g/mi
A4: Chevy Bolt EV | B4: 0.315 | C4: 0.056 | D4: 15643 | E4: 0.381 | F4: 5 | G4: 0.0631 | H4: 57 | I4: 0.00553 | J4: 0 | K4: 76
A5: Chevy Volt | B5: 0.335 | C5: 0.035 | D5: 15143 | E5: 0.387 | F5: 5 | G5: 0.0671 | H5: 30 | I5: 0.01118 | J5: 0.003 | K5: 107
A6: Toyota Prius (hybrid) | B6: 0.353 | C6: 0.025 | D6: 26000 | E6: 0.484 | F6: 5 | G6: 0.0706 | H6: 50 | I6: 0.00706 | J6: 0.012 | K6: 178
A7: Toyota Prius Prime | B7: 0.364 | C7: 0.038 | D7: 15000 | E7: 0.431 | F7: 5 | G7: 0.0728 | H7: 20 | I7: 0.01821 | J7: 0.006 | K7: 110
A8: Toyota Corolla | B8: 0.368 | C8: 0.025 | D8: 17659 | E8: 0.472 | F8: 5 | G8: 0.0737 | H8: 13 | I8: 0.02833 | J8: 0.02 | K8: 287
A9: Toyota Camry Hybrid | B9: 0.368 | C9: 0.032 | D9: 16500 | E9: 0.45 | F9: 5 | G9: 0.0737 | H9: 15 | I9: 0.02456 | J9: 0.016 | K9: 212
A10: Honda Civic | B10: 0.385 | C10: 0.024 | D10: 23789 | E10: 0.509 | F10: 5 | G10: 0.077 | H10: 15 | I10: 0.02567 | J10: 0.019 | K10: 278
A11: Nissan Leaf | B11: 0.386 | C11: 0.067 | D11: 11667 | E11: 0.403 | F11: 5 | G11: 0.0771 | H11: 30 | I11: 0.01286 | J11: 0 | K11: 81
A12: Hyundai Elantra | B12: 0.39 | C12: 0.033 | D12: 16000 | E12: 0.466 | F12: 5 | G12: 0.078 | H12: 14 | I12: 0.02785 | J12: 0.02 | K12: 254
A13: Honda Accord | B13: 0.39 | C13: 0.027 | D13: 16143 | E13: 0.478 | F13: 5 | G13: 0.078 | H13: 17 | I13: 0.02293 | J13: 0.021 | K13: 287
A14: Kia K4 | B14: 0.396 | C14: 0.029 | D14: 20125 | E14: 0.488 | F14: 5 | G14: 0.0792 | H14: 15 | I14: 0.02639 | J14: 0.019 | K14: 261
A15: Mazda3 (SkyActiv) | B15: 0.396 | C15: 0.035 | D15: 15000 | E15: 0.491 | F15: 5 | G15: 0.0792 | H15: 20 | I15: 0.01981 | J15: 0.023 | K15: 296
... A74: Porsche 996 Turbo | B74: 1.043 | C74: 0.031 | D74: 60333 | E74: 1.102 | F74: 2 | G74: 0.5213 | H74: 5 | I74: 0.20852 | J74: 0.039 | K74: 523
A76: WHAT EACH METRIC REVEALS (and why it matters beyond $/mile): BAD-LUCK TAIL (P90−P50) = how much a rough-luck outcome costs above the median — Corolla/Camry are tight (~3¢), Mazda3/Leaf/Bolt are wide (~7-8¢); pick low tail if you can't absorb a surprise. UP-FRONT CAPITAL = cash tied up and exposed to total-loss/theft; a car that wins $/mile by a penny while costing $12k more up front is not obviously better. 5yr / 75k-mi $/mi = cost if you SELL after 5 years instead of driving to death — this penalizes front-loaded depreciation (new EVs/PHEVs) that the drive-to-death frame rewards, and is what most buyers actually face. $ PER SEAT-MILE = $/mile ÷ seats — a Sienna at ~$0.50/mi over 8 seats ($0.063/seat-mi) hauls a family cheaper per person than a Corolla at $0.42/mi over 5 ($0.085/seat-mi); the right lens when you need room for 4 kids. MAX CARGO + $/mi-per-cu-ft = space and space-efficiency. +$1/gal→Δ$/mi = fuel-price exposure (EVs ~0, trucks/3-row gas ~$0.05); pick low if you fear gas spikes. CO₂ g/mi = climate cost. NOT SHOWN because they need per-person or external data: personalized insurance quote (varies by driver/ZIP), IIHS/NHTSA safety ratings (get the specific trim/year), and resale liquidity/days-to-sell.

Sheet Year Reliability
A1: YEAR RELIABILITY — different model-YEARS of the same car differ (redesigns, bad-engine/transmission years). A YEAR-RELIABILITY MULTIPLIER now scales the repair cost across the WHOLE model — landmine years x1.40, first-year-of-generation x1.15, verified sweet-spot years x0.95 — so the Ranking, the Sweet-spot heat map (by the year each odometer implies), the buy-point optimizer, AND the Any-Car Calculator all respond to model-year. This tab lists the years behind those multipliers for all 70 vehicles. "Sweet-spot years" = buy with confidence; "Avoid" = known trouble (verify the recall was completed for recall-based ones). Sourced from iSeeCars / RepairPal / CarComplaints / Auto Reliability Index, 2026.
A3: Vehicle | B3: Sweet-spot years | C3: Years to AVOID | D3: The specific issue in the bad years
A4: Toyota Corolla | B4: 2016-2019, 2021+ | C4: 2009-2010, 2014, 2020, 2023 | D4: 2009-10 excess oil (2ZR); 2014 new-CVT teething; 2020 & 2023 dip vs the model's usual excellence (still fine cars).
A5: Toyota Camry | B5: 2015-2017, 2020-2022 | C5: 2007-2009, 2018 | D5: 2007-09 EXCESSIVE OIL CONSUMPTION (2AZ engine) — the big one; 2018 = first year of the current generation.
A6: Toyota Camry Hybrid | B6: 2020-2022, 2013-2014 | C6: 2007-2009, 2018 | D6: Same 2AZ oil issue in 07-09; 2018 first-year-of-generation niggles.
A7: Toyota Prius | B7: 2013-2015, 2018-2019 | C7: 2010-2011, 2016 | D7: 2010-11 unintended-accel era + some inverter failures; 2016 = first year of gen-4.
A8: Honda Civic | B8: 2013-2015, 2018-2022 | C8: 2001-2002, 2006-2008, 2016 | D8: 2001-02 auto-trans failure; 2006-08 engine block cracking (1.8L); 2016 = first year 10th gen (A/C, early bugs).
A9: Honda Accord | B9: 2011-2012, 2016-2017, 2020+ | C9: 2003, 2008-2010, 2018 | D9: 2003 transmission failure; 2008-10 excess oil + early brakes; 2018 = 1.5T OIL-DILUTION first year.
A10: Mazda3 | B10: 2013, 2016-2018, 2021+ | C10: 2004-2006, 2010, 2014-2015, 2019 | D10: Premature rust, clutch (manual), infotainment/brake bugs; first-year-of-gen dips (2010, 2014, 2019).
A11: Hyundai Elantra | B11: 2018-2020, 2021+ | C11: 2011-2013, 2017 | D11: Engine/brake complaints; verify any GDI engine recall was completed on the older ones.
A12: Hyundai Sonata | B12: 2020+, 2018-2019 (recall-verified) | C12: 2011-2015 | D12: THETA II 2.0/2.4 GDI rod-bearing failure + oil consumption (recalled) — CONFIRM the recall was done before buying.
A13: VW Passat (US) | B13: 2016-2019 | C13: 2012 | D13: 2012 = first NMS-generation teething; watch timing-chain tensioner & water pump on the 1.8T. (Thinner year data than the Japanese models.)
A14: Toyota RAV4 | B14: 2016-2018, 2021+ | C14: 2013-2015, 2019 | D14: 2013-15 TORQUE-CONVERTER SHUDDER / low-speed vibration; 2019 = first year of gen (fuel-fill + transmission complaints).
... A71: Volvo V90 Cross Country | B71: 2019-2022 | C71: 2017 | D71: 2017 = first model year; otherwise a lovely wagon that's costly to fix.
A73: HOW TO USE: find the car + year on your listing here first. A "sweet-spot" year is a confident buy; an "avoid" year isn't necessarily a no — but budget for the named repair, and for any recall-based issue (Theta II engines, Pacifica battery, Telluride) CONFIRM in writing that the recall work was completed (free at the dealer; check the VIN at the manufacturer recall site). Rule of thumb this table keeps proving: the FIRST year of a new generation and the KNOWN-bad-engine years (Theta II 2011-2015 Hyundai/Kia, Subaru EJ25 head gaskets, Honda 1.5T oil dilution 2017-2018) are where the landmines cluster.

Sheet Scenarios by state
A1: MEDIAN $/mile UNDER 3 ENERGY-PRICE SCENARIOS (leaving California)
A3: Vehicle | B3: Energy | C3: $/mi California | D3: $/mi US avg | E3: $/mi cheap state
A4: Chevy Bolt EV | B4: electric | C4: 0.31529265 | D4: 0.2829626 | E4: 0.2700758
A5: Chevy Volt | B5: plug-in | C5: 0.33544227 | D5: 0.30241903 | E5: 0.28850675
A6: Toyota Prius (hybrid) | B6: hybrid | C6: 0.35302818 | D6: 0.33361245 | E6: 0.32314379
A7: Toyota Prius Prime | B7: plug-in | C7: 0.36419503 | D7: 0.33952021 | E7: 0.32837404
A8: Toyota Corolla | B8: gas | C8: 0.36828198 | D8: 0.33593784 | E8: 0.31849836
A9: Toyota Camry Hybrid | B9: hybrid | C9: 0.36836686 | D9: 0.34314573 | E9: 0.32954688
A10: Honda Civic | B10: gas | C10: 0.38509217 | D10: 0.35414288 | E10: 0.33745548
A11: Nissan Leaf | B11: electric | C11: 0.38573301 | D11: 0.34593482 | E11: 0.33007121
A12: Hyundai Elantra | B12: gas | C12: 0.38984661 | D12: 0.35858909 | E12: 0.3417355
A13: Honda Accord | B13: gas | C13: 0.38985817 | D13: 0.35575589 | E13: 0.33736845
A14: Kia K4 | B14: gas | C14: 0.39582348 | D14: 0.36481984 | E14: 0.34810315
A15: Mazda3 (SkyActiv) | B15: gas | C15: 0.3961843 | D15: 0.35891509 | E15: 0.3388201
... A74: Porsche 996 Turbo | B74: gas | C74: 1.0425927 | D74: 0.97977967 | E74: 0.94591182

Sheet Model & Method
A1: MODEL & METHOD — a full overview of how every variable feeds the cost-per-mile, then the adversarial-review log
A3: PART 1 — MODEL OVERVIEW: how each variable enters the $/mile
A4: Element | B4: How it works in the model | C4: Source / notes
A5: FRAMING — 'drive to death' $/mile | B5: $/mile = (every lifetime cost, in today's dollars) ÷ (miles you drive from purchase to end-of-life). Costs are summed over the whole life, then divided by miles. Lower = cheaper to own per mile. This ranks vehicles on true lifetime cost, not sticker price. | C5: The headline number on the Ranking tab.
A6: THE COST EQUATION | B6: $/mi = Depreciation + Fuel/energy + Maintenance&repair + Major-repair tail + Insurance + Registration + Tires + EV-battery reserve — each discounted to present value, then ÷ miles. | C6: Every term below is one piece of this sum.
A7: ODOMETER = the master variable | B7: The buy ODOMETER drives almost everything: it reads the purchase PRICE off each car's price-vs-odometer curve, sets how many miles remain to end-of-life (the denominator), and — divided by 13,000 mi/yr — sets the car's AGE that the repair curve climbs with. Move the odometer and the whole cost moves. | C7: Each car is bought at a model-chosen cost-optimal odometer, capped to keep ≥35% of life left.
A8: MODEL YEAR — now drives repair cost (3 ways) | B8: (1) YEAR-RELIABILITY MULTIPLIER (new): each model has known good/bad model-years, and a multiplier now SCALES the repair portion of $/mi — landmine years (bad engine/transmission, e.g. Theta-II 2011-15 Hyundai/Kia, Subaru head-gasket, Honda 1.5T oil-dilution) ×1.40, first-year-of-generation/minor ×1.15, verified sweet-spot years ×0.95, everything else ×1.00. In the RANKING & HEAT-MAP the year is read from the odometer (≈2026 − odo÷13,000, clamped to production years), so buying at an odometer that IMPLIES a bad year now costs more — the sweet-spot shifts to avoid landmine years, and the optimizer already steers away from them. In the ANY-CAR CALCULATOR you pick the year directly and see the exact 'Year rel. ×' it applies. (2) CALENDAR AGE: a small time-based surcharge (~$0.0007/mi per year of age) that separates a garage-kept 2008/90k from a 2019/90k at the SAME odometer. (3) BOUNDS: first production year greys out impossible old heat-map cells; last year caps the label. | C8: Good/bad years + the specific failure mode per model are on the Year Reliability tab (sources: iSeeCars / RepairPal / CarComplaints / ARI).
A9: PURCHASE PRICE & DEPRECIATION | B9: Price = the car's verified price-by-odometer curve at the buy point. Depreciation = purchase price − resale value, ÷ miles. Normal cars resell at scrap (~$400–800); 'Sport'/collector cars (996) RETAIN most value, so their depreciation nearly vanishes and maintenance dominates. | C9: 7 core models wide-verified from cars.com; the rest are market-estimate curves with live verify links. Editable on the Ranking tab.
A10: END-OF-LIFE (EOL) = the denominator | B10: Miles driven before retirement = iSeeCars EMPIRICAL retirement mileage × 1.30 ('maintained / non-crashed' bonus). Sets how many miles the costs spread over. Sport cars instead use a realistic ~70k-mi ownership. | C10: The single biggest lever. The '$/mi if EOL=empirical' column shows the pessimistic no-bonus case.
A11: FUEL / ENERGY | B11: gallons/mile = 1 ÷ MPG (× gas $); for EV/PHEV add kWh/mile × electricity $, with +8% lifetime degradation and a DC-fast-charge premium. Discounted over life. | C11: Gas & electricity are EDITABLE yellow cells (Ranking D3 / F3). MPG from EPA.
A12: MAINTENANCE & REPAIR | B12: A scheduled+unscheduled cost that RISES with the car's age (odometer÷13k), scaled by reliability TIER — low (Toyota/Honda/Mazda) → mid (Kia/Hyundai/Subaru/VW/GM) → high (Fiat/Mini/Volvo/Chrysler). Plus a PROBABILISTIC major-repair tail past 120k mi (random events, ~$3.2–6k each, likelier for worse tiers). | C12: CarEdge/RepairPal-style curves + iSeeCars severe-repair rates.
A13: INSURANCE — your USAA / Florida basis | B13: Per-model full-coverage premium × 0.8 (USAA active-duty discount), dropping to liability-only ($1176/yr) once the car is worth <$6k. ÷ miles. | C13: Set for YOU. Premium is driven by GARAGING ZIP (Fresno), not FL registration — give your real USAA annual premium and it can be pinned exactly.
A14: REGISTRATION — Florida | B14: Flat ~$55/yr (Florida home-of-record) — NOT California's value-based VLF + smog + $118 EV road fee. | C14: Because you're active-duty, FL-registered, driving in CA.
A15: TIRES | B15: Per-mile by segment: car $0.018, SUV $0.022–0.024, truck/EV $0.030, exotic $0.05. | C15: Flat per-mile average.
... A19: THE TABS | B19: Ranking = the answer (editable prices + energy). Any-Car Calculator = pick from a dropdown OR type any car → live $/mi + rank. Sweet-spot heat map = $/mi vs odometer with verify links. Beyond $/mile = capital, tail risk, 5yr cost, $/seat-mile, cargo, CO₂. Scenarios by state = leaving California. Lists = the dropdown source (helper). | C19: 70 vehicles across 18 makes.
A21: PART 2 — ADVERSARIAL REVIEW: what was flagged, and the fix
A22: Review finding | B22: Fix applied in this version | C22: Residual limitation
A23: EOL flattered Toyota (hand-set per brand) | B23: Base EOL = iSeeCars EMPIRICAL retirement mileage; ONE uniform 1.30 'maintained/non-crashed' multiplier applied to all. Both scenarios shown (P50 column vs '$/mi if EOL=empirical'). | C23: EOL is still the biggest lever; the ×1.30 multiplier is a judgment. If you distrust it, read the empirical column.
A24: Smooth repair plateau hid the tail | B24: Added a PROBABILISTIC major-repair stream past 120k (Poisson events, lognormal ~$3.2-3.9k, rate rising with mileage & reliability tier). Surfaced as the P90 'bad-luck' column. | C24: Rare catastrophic events are hard to calibrate; P90 is indicative, not a guarantee.
A25: Insurance was a flat 4-bucket guess | B25: Real per-model published full-coverage premiums (~$2.0-3.1k/yr), and it DROPS to liability-only ($1176/yr ×0.8 USAA) once the car is worth <$6k — realistic for a car driven to death. | C25: Not a personalized Fresno quote; premium is set by GARAGING ZIP (Fresno), not the FL registration — give me your real USAA number to set it exactly.
A26: Fragile 'optimal buy odometer' | B26: An optimizer DOES pick each buy odometer — it scans the verified price curve and takes the highest-mileage point still within 1.5¢/mi of the cost-optimal plateau (so timing barely matters across a wide band). Real listings in the Verify links. | C26: The plateau is flat, so the exact buy point is not critical; a different entry mileage shifts results only modestly.
A27: EVs got a free pass (charging/battery/degradation) | B27: Battery = probability × cost (EV 30% / Leaf 55% of a $8-14k pack; hybrid/PHEV lower); +DC-fast-charge premium on ~15% of miles; +8% life-average efficiency loss; real EV insurance. NOTE: assumes ~85% home charging at the CA EV rate — if you have no home charger, EV $/mi rises sharply (see I-22). | C27: Result vs pre-EV version: EV ranking is inherently battery- and home-charging-assumption-sensitive.
A28: No time value of money | B28: All cash flows discounted at 5% real (purchase at t0, scrap & future repairs/insurance/energy discounted). | C28: Discount rate is a choice; higher rate penalizes expensive front-loaded buys (EV/PHEV) more.
A29: Tires flat for everything | B29: Per-segment: car $0.018/mi, SUV $0.022-0.024, truck $0.030, EV/Tesla $0.030. | C29: Still an average; performance tires or heavy towing cost more.
A30: Registration wrong form | B30: Switched to FLORIDA flat $55/yr (your home-of-record) — NOT California's VLF (~0.65% of value) + smog + $118 ZEV fee. No CA VLF/ZEV/smog is charged anywhere in the model. | C30: FL registration is also ~right in dollars; omits FL's one-time ~$225 initial-registration + ~$77 title fee (small per-mile).
A31: Only expected cost, no variance | B31: Full Monte-Carlo (N=1,100): P50 median, P75, and P90 tail reported per vehicle. | C31: Distributions overlap across the top ~10 vehicles — treat the top tier as a statistical tie.
A32: Survivorship bias in high-mile prices | B32: Buy points kept at moderate mileage with real listings; not sent to extreme-odometer survivor prices. | C32: Asking prices still run above wholesale; a ~5-15% haircut would raise all $/mile slightly & evenly.
A33: REVIEW-2: buy odometer could snap to a survivorship extreme | B33: _optbuy now capped so a vehicle keeps >=~35% of empirical life left (fixes Mazda3 pinning at 125k just because it's cheap). | C33: Buy points are now more comparable across cars, but still model-chosen, not your specific listing.
... A38: REVIEW-3: within-model YEAR reliability now DRIVES the numbers | B38: You were right — reliability varies by model-year. Built a YEAR-RELIABILITY MULTIPLIER (landmine years ×1.40, first-year/minor ×1.15, verified-good ×0.95) that scales the repair cost, and wired it into the Ranking, Sweet-spot heat map (by implied year per odometer), the buy-point optimizer, AND the Any-Car Calculator (live off the year you pick). The Year Reliability tab lists the good/bad years + failure mode per model. | C38: Multipliers are a calibrated judgment (~2-3¢/mi for a bad year), not a per-VIN guarantee; for recall-based issues confirm the recall was done. Passat/exotics have thinner year data.
A40: NET EFFECT / HONEST CONCLUSION: the ROBUST finding is the ordering by class — electric/hybrid/efficient-sedan < gas SUV < 3-row SUV < truck < exotic — because it is driven by fuel economy and depreciation scale, which are large and directionally certain. But DO NOT crown a single #1: the top ~10 (Prius, Bolt, Volt, Camry Hybrid, Prius Prime, Corolla, Camry, Civic, Accord, Mazda3) sit within a ~5-cent band that is inside their own P90-P50 bad-luck spread — that is a statistical TIE, and which one leads flips on three fragile assumptions: (1) the empirical-EOL x1.30 "maintained survival" multiplier (the single biggest lever — see the "$/mi if EOL=empirical" column, which moves cars +5-17c unevenly), (2) each car's model-chosen buy odometer, and (3) the EV battery-replacement probabilities. For YOUR family use-case the durable answer is: cheapest-to-drive = a hybrid/efficient sedan (Prius-class, ~$0.39-0.44); best space-per-dollar = the "Beyond $/mile" tab's $/seat-mile column favors the Sienna Hybrid & Highlander Hybrid; the RAV4 Hybrid remains the best compact AWD SUV. Treat everything inside +-$0.05/mi as equal and choose on space, risk tolerance, and fit.

Sheet Assumptions
A1: ASSUMPTIONS INVENTORY (the single source of truth) — every number the $/mile model sets on purpose (EXPLICIT, Part 1) and everything baked in that was never said out loud (IMPLICIT, Part 2), plus status (Part 3), the v1→v2 revision log (Part 4) and per-vehicle inputs (Part 5). The model is running v2 (explicit-cost layer ON: real resale, capital cost, calendar-age repairs, purchase tax, total-loss, repair hassle + per-make cost, revised EOL). Explicit tables are generated straight from the model dicts, so they stay in sync. Implicit list notes which vehicle each favors (↑) / penalizes (↓).
A3: THE FORMULA
A4: $/mile = [ (price − discounted resale) + Σ discounted(base maint×yr_mult + major-repair tail×yr_mult + insurance + registration) + lifetime tires + EV battery reserve ] ÷ lifetime miles + (gal/mi×gas$ + kWh/mi×elec$)×avg-discount-factor. Lifetime miles = empirical-EOL×1.30 − buy odometer. All future costs discounted 5%/yr. Monte-Carlo N=1,100 → P50/P75/P90.
A5: PART 1 — EXPLICIT: global constants
A6: Constant | B6: Value | C6: Notes
A7: Annual mileage (MPY) | B7: 13,000 mi/yr | C7: converts odometer↔age↔year everywhere
A8: Real discount rate | B8: 7%/yr | C8: future costs discounted; purchase at t0
A9: Gas price | B9: $5.455/gal | C9: California; editable cell Ranking!D3
A10: Electricity price | B10: $0.32/kWh | C10: California; editable cell Ranking!F3
A11: Fuel/elec escalation | B11: 0%/yr | C11: held CONSTANT for the whole life (implicit I-9/I-10)
A12: Monte-Carlo draws | B12: 1,100 | C12: P50 = ranking; P75, P90 reported
A13: Insurance multiplier | B13: ×0.8 | C13: USAA active-duty vs standard full-coverage
A14: Liability floor | B14: $1176/yr | C14: once car value < threshold
A15: Full-coverage threshold | B15: $6,000 | C15: above=full, below=liability
A16: Registration | B16: $55/yr flat | C16: Florida home-of-record (not CA VLF+smog+ZEV)
A17: EOL maintained multiplier | B17: ×1.30 | C17: applied to every empirical retirement mileage
... A19: Age surcharge (calc only) | B19: $9/yr-age ÷ 13,000 ≈ $0.0007/mi/yr | C19: separates 2008/90k from 2019/90k
A20: PART 1 — EXPLICIT: reliability tiers (major-repair tail, per event, past 120k mi)
A21: Tier | B21: Annual prob (past 120k) | C21: Median $/event | D21: ×1.13 effective
A22: low | B22: 0.05/yr | C22: $3,200 | D22: $3,616
A23: mid | B23: 0.10/yr | C23: $3,600 | D23: $4,068
A24: high | B24: 0.14/yr | C24: $3,900 | D24: $4,407
A25: sport | B25: 0.20/yr | C25: $6,000 | D25: $6,780
A26: (rate escalates: prob × (1 + (odo−120,000)/100,000); below 120k the tail = $0)
A27: PART 1 — EXPLICIT: tires / scrap / battery / energy
A28: Item | B28: Values
A29: Tires $/mi (by class) | B29: Car 0.018 · SUV 0.022 · SUV AWD 0.024 · Truck 0.03 · EV 0.03 · EV SUV 0.03 · PHEV 0.024 · PHEV SUV AWD 0.026 · Van 0.02 · Sport 0.05
A30: End-of-life resale (scrap $) | B30: Car $400 · SUV $450 · SUV AWD $500 · Truck $800 · EV $600 · EV SUV $700 · PHEV $600 · PHEV SUV AWD $800 · Van $500 · Sport $3000 (Sport = price×0.60–1.0 retention)
A31: EV/PHEV battery reserve | B31: hybrid 15%×$2,500 · PHEV 22%×$4,000 · EV 30%×$12,000 (Tesla $14,000) · Leaf 55%×$8,000; discounted to ~65% of life
A32: Energy modeling | B32: EV kWh/mi ×1.08 degrade; elec price ×1.09 EV / ×1.06 PHEV (DCFC); PHEV utility factor RAV4 Prime 0.75 / Volt 0.80 / Prius Prime 0.55
A33: Year-reliability multiplier | B33: landmine ×1.40 · first-year/minor ×1.15 · sweet-spot ×0.95 · else ×1.00 (repair only)
A34: PART 2 — IMPLICIT: baked in, never stated (↑ favors / ↓ penalizes)
A35: # | B35: Implicit assumption | C35: Favors ↑ / Penalizes ↓
A36: I-1 | B36: Everyone drives 13,000 mi/yr; mileage is the only thing that ages a car | C36: Couples year↔odo; ↓ the low-mileage-old-car case. Neutral across cars.
A37: I-2 | B37: You drive it to end-of-life (never sell mid-life) | C37: ↑ durable cheap-to-run (Toyota); a 5-yr frame looks different.
A38: I-3 | B38: Resale = scrap (~$400–800); you extract ZERO value at the end | C38: ↓ value-retainers (Tacoma, 4Runner, Toyotas); ↑ hard depreciators. BIGGEST hidden lever.
A39: I-4 | B39: Opportunity cost of tied-up capital = $0 | C39: ↑ expensive/near-new cars (Tesla, RAV4 Prime, 3-rows). Drives the near-new sweet-spot skew.
A40: I-5 | B40: Repair hassle/downtime/towing/rental/missed-work = $0 | C40: ↑ cheap-but-flaky (Fiat, old Ranger, high-mile survivors).
A41: I-6 | B41: Safety not in the number | C41: ↑ old cheap vehicles (2002 Ranger, Fiat 500). Real omission for a family.
A42: I-7 | B42: Capability/fit/utility = $0 (AWD, tow, 3rd row, cargo) | C42: ↑ small cheap cars; ↓ trucks/SUVs/vans. Corolla & Sienna "tie" that shouldn't.
A43: I-8 | B43: Calendar age doesn't drive repair frequency (only mileage) | C43: ↑ old low-mile vehicles (old Ranger, garage queens). Calc age surcharge only half-fixes it.
A44: I-9 | B44: Fuel price constant for 15–18 yrs (0% escalation) | C44: Under-penalizes thirsty vehicles (trucks, V8 SUVs, 996) if gas rises.
A45: I-10 | B45: Electricity price constant too | C45: Mirror of I-9 for EVs.
A46: I-11 | B46: Insurance = national-ish per-model × 0.80, drops to liability <$6k | C46: Crude; slightly ↓ cheap cars in the window they're worth >$6k.
... A57: I-22 | B57: All EVs charge at home cheaply (85% home/15% DCFC) | C57: ↑ EVs for anyone without a home plug.
A58: PART 3 — STATUS: what v2 fixed, and what is still open
A59: Item | B59: Status | C59: Detail
A60: Resale = scrap (I-3) | B60: FIXED v2 | C60: now the real high-mileage market value (price curve at EOL), not $500 scrap
A61: EOL ceilings / ×1.30 (item 4) | B61: REVISED v2 | C61: per-model maintained EOL from iSeeCars 2024 longevity study + high-mileage owner-reported data (CarComplaints, model forums) — see revision log below
A62: Opportunity cost of capital (I-4) | B62: ADDED v2a, REMOVED v2b | C62: Was +5%/yr on book value — but that DOUBLE-COUNTED: discounting the resale already prices the capital carry. Removed in v2b. Capital cost is still correctly captured via 5% discounting of the future resale.
A63: Calendar-age repairs (I-8) | B63: PARTIAL — not truly fixed | C63: The 2%/yr-past-8-yrs escalator keys off age = odometer÷13,000, i.e. still mileage-derived. A garage-kept 2008/90k is treated as ~7 yrs old, not ~18. Real calendar age is NOT yet a state variable. The Ranger case is still under-aged.
A64: Purchase tax + total-loss (I-12/I-13) | B64: FIXED v2 | C64: +7% use-tax on purchase + 1.5%/yr crash/theft on book value
A65: Repair hassle + per-make cost (I-5) | B65: FIXED v2 | C65: $600 per unplanned major repair + per-make repair multiplier (Volvo 1.40 … Toyota 1.0)
A66: Fuel escalation (I-9) | B66: TOGGLE | C66: scenario only (FUEL_ESC config); OFF by default — real gas ~flat historically
A67: Safety & capability (I-6/I-7) | B67: OPEN | C67: belong as side columns, not folded into $/mi (capability partly in Beyond tab seats/cargo)
A68: ×1.30 multiplier still in code | B68: OPEN | C68: backed out numerically in v2; cleaner long-term = store maintained EOL directly & delete the multiplier
A69: Reliability decisiveness | B69: CHOICE | C69: Fiat 500 still ~#3 on P50 MEDIAN; rank on P75 if reliability should be decisive (one line)
A70: Insurance generic (I-11) | B70: OPEN | C70: replace with your real USAA quotes when available
A71: PART 4 — REVISION LOG (v1 → v2). Keep old numbers; never delete.
A72: Change | B72: v1 (old) | C72: v2 (new)
A73: Resale | B73: flat scrap $400–800 | C73: real high-mileage market value = price curve at EOL odometer (floored at scrap)
A74: Opportunity cost of capital | B74: $0 | C74: +5%/yr on tied-up book value
A75: Calendar-age repairs | B75: mileage only | C75: × (1 + 2%/yr past 8 yrs old)
A76: Purchase tax | B76: $0 | C76: +7% use-tax on purchase
A77: Total-loss risk | B77: $0 | C77: +1.5%/yr crash/theft on book value
A78: Repair hassle | B78: $0 | C78: +$600 per unplanned major repair
A79: Repair cost by make | B79: flat by tier | C79: ×1.15–1.40 (Volvo 1.40, Mini 1.35, VW/Tesla/Porsche/Fiat 1.15–1.30)
A80: Fuel escalation | B80: 0%/yr (kept default) | C80: scenario: gas +2%/yr, elec +0.5%/yr (FUEL_ESC toggle, OFF default)
A81: EOL ceilings | B81: base × uniform 1.30 (Tacoma 318k, Sequoia 331k, Fiat 195k; CR-V 221k under-rated) | C81: revised per-model maintained (Tacoma 290, Sequoia 300, Fiat 160; CR-V 240, RAV4 240) — iSeeCars + owner-reported longevity
A82: Comparison kept | B82: — | C82: "v1 $/mi (old model)" column on the Ranking tab
A83: PART 4b — v2b AUDIT FIXES (adversarial review, Jul 2026). Old v2a behaviour kept in the "why it was wrong" column.
A84: Fix | B84: Was (v2a) | C84: Now (v2b) — and why
A85: Capital double-count | B85: +5%/yr opportunity cost on book value, ON TOP of discounted depreciation | C85: REMOVED. Proof: buy $10k / sell $10k after 10yr @5% → depreciation term = 10000−10000/1.05^10 = $3,861, which EXACTLY equals Σ 5%·val/1.05^t = $3,861. Discounting already prices the capital carry; charging both counts it twice.
A86: End-of-life resale | B86: np.interp CLAMPED to the last price-table point → a 244k-mi Sienna Hybrid valued at $23k, a 250k Corolla at $6.5k | C86: EXTRAPOLATE the last segment down past the table, floored at scrap. Fixes ~61 of 68 vehicles; also re-derives every pinned buy point + heat map, which read this.
A87: Energy discount factor | B87: dfac summed floor(T) yearly terms ÷ ceil(T) → dropped the final partial year, understating energy 6–14% (worst for short-lived cheap cars) | C87: Length-weighted average discount factor; each partial year weighted by its own length.
A88: Liability floor | B88: $650/yr, silently ×0.80 = $520 effective (a state-minimum figure). Created a huge cliff at the $6k full-cov threshold that handed cheap cars (Fiat) a fake 5¢/mi edge | C88: $1,176/yr (Insurify 2026 national liability-only avg) ×0.80 = ~$941. The cliff now correctly reflects dropping only collision+comp.
A89: Total-loss overcharge | B89: 1.5%/yr on FULL book value even while full coverage is carried — but the insurer pays ACV, so your real exposure is the deductible | C89: v2b: charge 1.5%/yr × deductible ($750) while worth >$6k (full cov); × full book value below (liability-only, you eat the loss). Was ~20× too high on expensive cars.
A90: Fiat bad-year not forced | B90: odometer÷13k clock labelled the $6-9k Fiat 500 a ~2019 (a "good" year) → ×0.95 discount | C90: v2b: Fiat 500 forced to ×1.40. Its affordable examples ARE the 2012-2015 landmine years (its own verify link returns those); no 500 model year is reliable.
A91: RANKING IMPACT (v2a → v2b final) | B91: Bolt 1 · Volt 2 · Fiat 3 · Leaf 4 · Prius Prime 5 · Mazda3 6 · Prius 7 · Corolla 8 · Camry Hyb 9 | C91: Bolt 1 · Volt 2 · Prius 3 · Prius Prime 4 · Camry Hyb 5 · Corolla 6 · Leaf 7 · Civic 8 · Elantra 9 · Accord 10 · Mazda3 11 (−5) · RAV4 Hyb 12 · … FIAT 500 → 18 (−15) · Sienna Hyb 31 · Tacoma 36 · 4Runner 50
A92: STILL OPEN after v2b | C92: MPY=13,000 is user-confirmed, not odometer-measured (biggest single lever). Reliability ranks on P50 median, not P75. Total-loss still does not truncate life on a loss. EOL dispersion σ=0.12 is uniform across makes. Calendar age (I-8) still keyed to mileage. Home-charging assumed for EVs.
A93: PART 4c — CONSTANTS PREVIOUSLY DOCUMENTED NOWHERE (now disclosed; several are judgement calls, not sourced pulls)
A94: Constant / choice | B94: Value | C94: Note
A95: Monte-Carlo seed | B95: rng=default_rng(42) | C95: P50/P75/P90 are one fixed-seed realisation, stable to ~±0.004
A96: End-of-life dispersion | B96: lognormal σ=0.12 | C96: SAME for every vehicle — reliability tier drives repair RATE, not EOL spread. So P90 cannot express "this Fiat gets junked early".
A97: Major-repair cost spread | B97: lognormal σ=0.5 | C97: per event, past 120k
A98: Insurance noise | B98: normal(1, 0.08) | C98: per year
A99: Battery cost spread | B99: lognormal σ=0.40 / 0.40 / 0.35 | C99: hybrid / PHEV / EV
A100: Energy variance | B100: NONE | C100: energy computed outside the Monte Carlo — gas-price/mpg risk contributes 0 to P90
A101: Buy-odo optimiser caps | B101: min(1.3·EOL−40k, 160,000, 0.65·EOL) | C101: hard 160k cap; the 0.65 is 50% of maintained EOL, not "35% of empirical life"
A102: Per-make repair mult | B102: Volvo 1.40 · Mini 1.35 · Porsche 1.30 · VW/Tesla 1.25 · Fiat 1.15 · dom 1.05 | C102: judgement estimates, not a sourced table
A103: Reliability tiers | B103: prob {.05,.10,.14,.20} · median {$3.2k,$3.6k,$3.9k,$6k} | C103: judgement calibration
A104: Any-Car Calculator | B104: separate simpler cost model | C104: RUNBASE {.045,.065,.085,.32}; omits total-loss/capital/tax/hassle/battery/discounting — a quick estimator, not the full engine
A105: Maintenance-curve sharing | B105: 42 of 70 cars share a curve | C105: e.g. Elantra=Sorento, Highlander=Sequoia, CX-90=Suburban. Simplification.
A106: PART 5 — PER-VEHICLE INPUTS (EOL shown as v1 → v2 maintained ceiling)
A107: Vehicle | B107: Maintained EOL (k mi): v1 → v2 | C107: MPG (or kWh/100) | D107: tier · insurance $/yr · years
A108: Toyota Sequoia | B108: 332k → 300k | C108: 15 mpg | D108: low · $1,960 · 2008-2026
A109: Toyota Tacoma | B109: 318k → 290k | C109: 20 mpg | D109: low · $1,800 · 2005-2026
A110: Toyota 4Runner | B110: 318k → 290k | C110: 17 mpg | D110: low · $1,800 · 2010-2026
A111: Toyota Camry | B111: 260k → 255k | C111: 30 mpg | D111: low · $1,840 · 2009-2026
A112: Toyota Corolla | B112: 254k → 250k | C112: 31 mpg | D112: low · $1,920 · 2009-2026
...

Sheet Lists
A1: Full | B1: Make | C1: Model | D1: EOL | E1: MPG | F1: kWh100 | G1: Run | H1: InsUSAA | I1: Tires | J1: Price | K1: Scrap | L1: Total | N1: MAKES | O1: YEARS | P1: BadYears | Q1: CautionYears | R1: GoodYears | T1: Tier | U1: P05 | V1: P95 | W1: OppPM
A2: Buick Enclave | B2: Buick | C2: Enclave | D2: 184600 | E2: 21 | F2: 0 | G2: 0.065 | H2: 1800 | I2: 0.024 | J2: 16667 | K2: 500 | L2: 0.618 | N2: Buick | O2: 2026 | P2: 2008,2009,2010,2011,2012,2013 | Q2: 2018 | R2: 2019,2020,2021 | T2: 7 | U2: 0.553 | V2: 0.684 | W2: 0.112
A3: Buick Encore | B3: Buick | C3: Encore | D3: 175500 | E3: 28 | F3: 0 | G3: 0.065 | H3: 1680 | I3: 0.022 | J3: 14800 | K3: 450 | L3: 0.485 | N3: Chevy | O3: 2025 | Q3: 2013,2014 | R3: 2017,2018,2019,2020 | T3: 4 | U3: 0.419 | V3: 0.499 | W3: 0.109
A4: Chevy Bolt EV | B4: Chevy | C4: Bolt EV | D4: 200200 | E4: 0 | F4: 30.2 | G4: 0.045 | H4: 1660 | I4: 0.03 | J4: 15643 | K4: 600 | L4: 0.3546 | N4: Chrysler | O4: 2024 | Q4: 2017,2018,2019,2020,2021,2022 | R4: 2023 | T4: 1 | U4: 0.289 | V4: 0.389 | W4: 0.125
A5: Chevy Colorado | B5: Chevy | C5: Colorado | D5: 205400 | E5: 19 | F5: 0 | G5: 0.065 | H5: 1720 | I5: 0.03 | J5: 23500 | K5: 800 | L5: 0.6316 | N5: Fiat | O5: 2023 | Q5: 2015,2016 | R5: 2019,2020,2021,2022 | T5: 6 | U5: 0.535 | V5: 0.627 | W5: 0.183
A6: Chevy Equinox | B6: Chevy | C6: Equinox | D6: 175500 | E6: 27 | F6: 0 | G6: 0.085 | H6: 1720 | I6: 0.022 | J6: 17200 | K6: 450 | L6: 0.5358 | N6: Ford | O6: 2022 | P6: 2010,2011,2012,2013 | Q6: 2018,2019,2020 | R6: 2016,2017,2021,2022 | T6: 5 | U6: 0.455 | V6: 0.546 | W6: 0.125
A7: Chevy Suburban | B7: Chevy | C7: Suburban | D7: 244400 | E7: 16 | F7: 0 | G7: 0.065 | H7: 1920 | I7: 0.024 | J7: 42375 | K7: 500 | L7: 0.7543 | N7: Honda | O7: 2021 | Q7: 2015,2021 | R7: 2017,2018,2019,2020,2022 | T7: 7 | U7: 0.589 | V7: 0.701 | W7: 0.376
A8: Chevy Tahoe | B8: Chevy | C8: Tahoe | D8: 240500 | E8: 16 | F8: 0 | G8: 0.065 | H8: 1880 | I8: 0.024 | J8: 39375 | K8: 500 | L8: 0.7411 | N8: Hyundai | O8: 2020 | Q8: 2015,2021 | R8: 2017,2018,2019,2020,2022 | T8: 7 | U8: 0.577 | V8: 0.685 | W8: 0.345
A9: Chevy Traverse | B9: Chevy | C9: Traverse | D9: 184600 | E9: 21 | F9: 0 | G9: 0.085 | H9: 1680 | I9: 0.024 | J9: 20000 | K9: 500 | L9: 0.6311 | N9: Jeep | O9: 2019 | P9: 2009,2010,2011,2012,2013,2014,2015 | Q9: 2018 | R9: 2019,2020,2021,2022 | T9: 6 | U9: 0.538 | V9: 0.659 | W9: 0.142
A10: Chevy Volt | B10: Chevy | C10: Volt | D10: 200200 | E10: 210 | F10: 26 | G10: 0.065 | H10: 1440 | I10: 0.024 | J10: 15143 | K10: 600 | L10: 0.384 | N10: Kia | O10: 2018 | Q10: 2011,2012 | R10: 2013,2014,2015,2016,2017,2018,2019 | T10: 1 | U10: 0.307 | V10: 0.385 | W10: 0.118
A11: Chrysler Pacifica | B11: Chrysler | C11: Pacifica | D11: 175500 | E11: 22 | F11: 0 | G11: 0.085 | H11: 1680 | I11: 0.02 | J11: 16333 | K11: 500 | L11: 0.6026 | N11: Mazda | O11: 2017 | P11: 2017,2018 | R11: 2019,2020,2022 | T11: 6 | U11: 0.527 | V11: 0.652 | W11: 0.112
A12: Chrysler Pacifica PHEV | B12: Chrysler | C12: Pacifica PHEV | D12: 175500 | E12: 54.5 | F12: 18.9 | G12: 0.085 | H12: 1760 | I12: 0.02 | J12: 22000 | K12: 500 | L12: 0.5516 | N12: Mini | O12: 2016 | P12: 2017,2018 | R12: 2021,2022 | T12: 6 | U12: 0.494 | V12: 0.619 | W12: 0.155
A13: Fiat 500 | B13: Fiat | C13: 500 | D13: 159900 | E13: 33 | F13: 0 | G13: 0.085 | H13: 1600 | I13: 0.018 | J13: 10200 | K13: 400 | L13: 0.4687 | N13: Nissan | O13: 2015 | P13: 2012,2013 | Q13: 2014,2015 | R13: 2017,2018,2019 | T13: 3 | U13: 0.409 | V13: 0.496 | W13: 0.074
A14: Fiat 500X | B14: Fiat | C14: 500X | D14: 149500 | E14: 26 | F14: 0 | G14: 0.085 | H14: 1640 | I14: 0.024 | J14: 14800 | K14: 500 | L14: 0.5324 | N14: Porsche | O14: 2014 | P14: 2016 | Q14: 2017,2018 | R14: 2019,2020 | T14: 5 | U14: 0.475 | V14: 0.549 | W14: 0.104
A15: Ford Escape | B15: Ford | C15: Escape | D15: 170300 | E15: 26 | F15: 0 | G15: 0.085 | H15: 1720 | I15: 0.022 | J15: 15000 | K15: 450 | L15: 0.5444 | N15: Subaru | O15: 2013 | P15: 2013,2014 | Q15: 2020 | R15: 2017,2018,2019,2021,2022 | T15: 5 | U15: 0.462 | V15: 0.574 | W15: 0.104
A16: Ford Explorer | B16: Ford | C16: Explorer | D16: 184600 | E16: 21 | F16: 0 | G16: 0.085 | H16: 1720 | I16: 0.024 | J16: 21000 | K16: 500 | L16: 0.6409 | N16: Tesla | O16: 2012 | P16: 2011,2012,2013 | Q16: 2016,2020 | R16: 2018,2019,2021,2022 | T16: 6 | U16: 0.542 | V16: 0.667 | W16: 0.149
A17: Ford Ranger (2019+ midsize) | B17: Ford | C17: Ranger (2019+ midsize) | D17: 200200 | E17: 21 | F17: 0 | G17: 0.065 | H17: 1832 | I17: 0.03 | J17: 23000 | K17: 800 | L17: 0.6017 | N17: Toyota | O17: 2011 | Q17: 2019 | R17: 2021,2022,2023 | T17: 6 | U17: 0.513 | V17: 0.597 | W17: 0.179
A18: Ford Ranger (old compact) | B18: Ford | C18: Ranger (old compact) | D18: 214500 | E18: 21 | F18: 0 | G18: 0.065 | H18: 1832 | I18: 0.03 | J18: 11500 | K18: 800 | L18: 0.5601 | N18: VW | O18: 2010 | P18: 1999,2001,2011 | Q18: 2002,2004,2005,2006 | R18: 2008,2009,2010 | T18: 5 | U18: 0.467 | V18: 0.547 | W18: 0.093
A19: Honda Accord | B19: Honda | C19: Accord | D19: 240500 | E19: 31 | F19: 0 | G19: 0.045 | H19: 1840 | I19: 0.018 | J19: 16143 | K19: 400 | L19: 0.4306 | N19: Volvo | O19: 2009 | P19: 2003,2008,2009,2010 | Q19: 2018 | R19: 2011,2012,2016,2017,2020,2021,2022 | T19: 2 | U19: 0.355 | V19: 0.425 | W19: 0.135
A20: Honda CR-V | B20: Honda | C20: CR-V | D20: 240500 | E20: 28 | F20: 0 | G20: 0.045 | H20: 1680 | I20: 0.022 | J20: 20500 | K20: 450 | L20: 0.4792 | O20: 2008 | P20: 2015,2017,2018 | Q20: 2011 | R20: 2016,2019,2020,2021 | T20: 3 | U20: 0.4 | V20: 0.48 | W20: 0.169
A21: Honda Civic | B21: Honda | C21: Civic | D21: 235300 | E21: 32 | F21: 0 | G21: 0.045 | H21: 1840 | I21: 0.018 | J21: 23789 | K21: 400 | L21: 0.4465 | O21: 2007 | P21: 2001,2002,2006,2007,2008 | Q21: 2016 | R21: 2013,2014,2015,2018,2019,2020,2021,2022 | T21: 2 | U21: 0.357 | V21: 0.417 | W21: 0.218
A22: Honda Odyssey | B22: Honda | C22: Odyssey | D22: 224900 | E22: 22 | F22: 0 | G22: 0.065 | H22: 1680 | I22: 0.02 | J22: 20333 | K22: 500 | L22: 0.5689 | O22: 2006 | P22: 1999,2000,2001,2002,2003,2004 | Q22: 2011,2014,2018 | R22: 2013,2015,2016,2017,2020 | T22: 5 | U22: 0.472 | V22: 0.58 | W22: 0.158
A23: Honda Pilot | B23: Honda | C23: Pilot | D23: 224900 | E23: 20 | F23: 0 | G23: 0.045 | H23: 1680 | I23: 0.024 | J23: 22500 | K23: 500 | L23: 0.5953 | O23: 2005 | P23: 2016 | Q23: 2003,2005 | R23: 2012,2013,2014,2015,2018,2019 | T23: 6 | U23: 0.507 | V23: 0.605 | W23: 0.172
A24: Hyundai Elantra | B24: Hyundai | C24: Elantra | D24: 200200 | E24: 35 | F24: 0 | G24: 0.065 | H24: 1640 | I24: 0.018 | J24: 16000 | K24: 400 | L24: 0.4297 | Q24: 2011,2012,2013,2017 | R24: 2018,2019,2020,2021 | T24: 2 | U24: 0.357 | V24: 0.432 | W24: 0.128
A25: Hyundai Kona | B25: Hyundai | C25: Kona | D25: 184600 | E25: 30 | F25: 0 | G25: 0.065 | H25: 1640 | I25: 0.022 | J25: 15000 | K25: 450 | L25: 0.4792 | Q25: 2018 | R25: 2020,2021,2022 | T25: 4 | U25: 0.423 | V25: 0.504 | W25: 0.108
A26: Hyundai Palisade | B26: Hyundai | C26: Palisade | D26: 200200 | E26: 21 | F26: 0 | G26: 0.065 | H26: 1720 | I26: 0.024 | J26: 31000 | K26: 500 | L26: 0.6341 | Q26: 2020 | R26: 2022,2023,2024 | T26: 6 | U26: 0.523 | V26: 0.617 | W26: 0.248
A27: Hyundai Santa Fe | B27: Hyundai | C27: Santa Fe | D27: 189800 | E27: 25 | F27: 0 | G27: 0.065 | H27: 1720 | I27: 0.024 | J27: 16667 | K27: 500 | L27: 0.5492 | P27: 2013,2014 | Q27: 2019 | R27: 2020,2021,2022 | T27: 5 | U27: 0.487 | V27: 0.594 | W27: 0.117
A28: Hyundai Sonata | B28: Hyundai | C28: Sonata | D28: 195000 | E28: 32 | F28: 0 | G28: 0.065 | H28: 1720 | I28: 0.018 | J28: 15333 | K28: 400 | L28: 0.4558 | P28: 2011,2012,2013,2014,2015 | R28: 2018,2019,2020,2021 | T28: 3 | U28: 0.387 | V28: 0.478 | W28: 0.116
A29: Hyundai Tucson | B29: Hyundai | C29: Tucson | D29: 170300 | E29: 25 | F29: 0 | G29: 0.085 | H29: 1680 | I29: 0.022 | J29: 19541 | K29: 450 | L29: 0.5764 | P29: 2011,2012,2013 | Q29: 2016 | R29: 2019,2020,2021,2022 | T29: 5 | U29: 0.491 | V29: 0.579 | W29: 0.139
A30: Jeep Grand Cherokee L | B30: Jeep | C30: Grand Cherokee L | D30: 184600 | E30: 19 | F30: 0 | G30: 0.085 | H30: 1760 | I30: 0.024 | J30: 28600 | K30: 500 | L30: 0.7036 | Q30: 2021 | R30: 2022,2023 | T30: 7 | U30: 0.591 | V30: 0.695 | W30: 0.213
A31: Kia K4 | B31: Kia | C31: K4 | D31: 189800 | E31: 34 | F31: 0 | G31: 0.065 | H31: 1640 | I31: 0.018 | J31: 20125 | K31: 400 | L31: 0.451 | Q31: 2025 | R31: 2026 | T31: 2 | U31: 0.369 | V31: 0.436 | W31: 0.169
A32: Kia Niro (hybrid) | B32: Kia | C32: Niro (hybrid) | D32: 205400 | E32: 49 | F32: 0 | G32: 0.065 | H32: 1680 | I32: 0.022 | J32: 17000 | K32: 450 | L32: 0.4092 | Q32: 2017 | R32: 2018,2019,2020,2021 | T32: 3 | U32: 0.367 | V32: 0.46 | W32: 0.13
A33: Kia Sorento | B33: Kia | C33: Sorento | D33: 200200 | E33: 24 | F33: 0 | G33: 0.065 | H33: 1720 | I33: 0.024 | J33: 18333 | K33: 500 | L33: 0.5543 | P33: 2012,2013,2014 | Q33: 2016 | R33: 2019,2020,2021,2022 | T33: 5 | U33: 0.482 | V33: 0.586 | W33: 0.135
A34: Kia Soul | B34: Kia | C34: Soul | D34: 184600 | E34: 29 | F34: 0 | G34: 0.065 | H34: 1640 | I34: 0.022 | J34: 14500 | K34: 450 | L34: 0.4758 | P34: 2012,2013,2014 | Q34: 2020 | R34: 2017,2018,2019,2021,2022 | T34: 3 | U34: 0.406 | V34: 0.494 | W34: 0.106
A35: Kia Sportage | B35: Kia | C35: Sportage | D35: 184600 | E35: 26 | F35: 0 | G35: 0.065 | H35: 1680 | I35: 0.024 | J35: 15667 | K35: 500 | L35: 0.5293 | P35: 2011,2012,2013 | Q35: 2017 | R35: 2019,2020,2021,2023 | T35: 5 | U35: 0.468 | V35: 0.571 | W35: 0.11
A36: Kia Telluride | B36: Kia | C36: Telluride | D36: 200200 | E36: 21 | F36: 0 | G36: 0.065 | H36: 1720 | I36: 0.024 | J36: 33000 | K36: 500 | L36: 0.647 | P36: 2020,2021 | R36: 2022,2023,2024 | T36: 6 | U36: 0.53 | V36: 0.624 | W36: 0.264
A37: Mazda CX-5 | B37: Mazda | C37: CX-5 | D37: 214500 | E37: 26 | F37: 0 | G37: 0.045 | H37: 1680 | I37: 0.022 | J37: 20600 | K37: 450 | L37: 0.5033 | Q37: 2014,2016 | R37: 2013,2017,2020,2021 | T37: 4 | U37: 0.427 | V37: 0.505 | W37: 0.162
A38: Mazda CX-90 | B38: Mazda | C38: CX-90 | D38: 200200 | E38: 24 | F38: 0 | G38: 0.065 | H38: 1720 | I38: 0.024 | J38: 38750 | K38: 500 | L38: 0.6408 | Q38: 2024 | R38: 2025 | T38: 6 | U38: 0.535 | V38: 0.632 | W38: 0.324
A39: Mazda3 (SkyActiv) | B39: Mazda | C39: Mazda3 (SkyActiv) | D39: 210600 | E39: 30 | F39: 0 | G39: 0.045 | H39: 1720 | I39: 0.018 | J39: 15000 | K39: 400 | L39: 0.4374 | Q39: 2004,2005,2006,2010,2014,2015,2019 | R39: 2013,2016,2017,2018,2021,2022 | T39: 2 | U39: 0.364 | V39: 0.441 | W39: 0.117
A40: Mini Cooper | B40: Mini | C40: Cooper | D40: 175500 | E40: 30 | F40: 0 | G40: 0.085 | H40: 1720 | I40: 0.018 | J40: 18200 | K40: 400 | L40: 0.5107 | Q40: 2014 | R40: 2016,2017,2018,2019 | T40: 5 | U40: 0.451 | V40: 0.566 | W40: 0.136
A41: Mini Countryman | B41: Mini | C41: Countryman | D41: 175500 | E41: 26 | F41: 0 | G41: 0.085 | H41: 1760 | I41: 0.024 | J41: 19000 | K41: 500 | L41: 0.5657 | P41: 2011,2012,2013 | Q41: 2017 | R41: 2018,2019,2020 | T41: 6 | U41: 0.509 | V41: 0.628 | W41: 0.138
A42: Nissan Leaf | B42: Nissan | C42: Leaf | D42: 140400 | E42: 0 | F42: 32.4 | G42: 0.065 | H42: 1760 | I42: 0.03 | J42: 11667 | K42: 600 | L42: 0.4009 | P42: 2011,2012,2013,2014,2015,2016 | Q42: 2017,2018 | R42: 2019,2020,2021,2022 | T42: 2 | U42: 0.339 | V42: 0.473 | W42: 0.079
A43: Nissan Rogue | B43: Nissan | C43: Rogue | D43: 170300 | E43: 29 | F43: 0 | G43: 0.085 | H43: 1664 | I43: 0.022 | J43: 18800 | K43: 450 | L43: 0.5394 | P43: 2013,2014,2015,2016,2017,2018,2019 | Q43: 2011,2012,2020 | R43: 2021,2022 | T43: 4 | U43: 0.451 | V43: 0.541 | W43: 0.134
A44: Porsche 996 Carrera | B44: Porsche | C44: 996 Carrera | D44: 125000 | E44: 19 | F44: 0 | G44: 0.32 | H44: 1760 | I44: 0.05 | J44: 38833 | K44: 34950 | L44: 0.7959 | Q44: 1999,2000,2001 | R44: 2002,2003,2004 | T44: 9 | U44: 0.821 | V44: 0.91 | W44: 0.112
A45: Porsche 996 Turbo | B45: Porsche | C45: 996 Turbo | D45: 125000 | E45: 17 | F45: 0 | G45: 0.32 | H45: 1920 | I45: 0.05 | J45: 60333 | K45: 54300 | L45: 0.864 | R45: 2001,2002,2003,2004,2005 | T45: 10 | U45: 1.014 | V45: 1.093 | W45: 0.16
A46: Subaru Ascent | B46: Subaru | C46: Ascent | D46: 184600 | E46: 22 | F46: 0 | G46: 0.065 | H46: 1680 | I46: 0.024 | J46: 23400 | K46: 500 | L46: 0.6012 | P46: 2019 | Q46: 2020 | R46: 2022,2023,2024 | T46: 6 | U46: 0.506 | V46: 0.594 | W46: 0.174
A47: Subaru Forester | B47: Subaru | C47: Forester | D47: 200200 | E47: 29 | F47: 0 | G47: 0.065 | H47: 1680 | I47: 0.024 | J47: 22200 | K47: 500 | L47: 0.5166 | P47: 2011,2012,2013,2014,2015,2016 | R47: 2019,2020,2021,2022 | T47: 4 | U47: 0.439 | V47: 0.523 | W47: 0.173
A48: Subaru Outback | B48: Subaru | C48: Outback | D48: 210600 | E48: 29 | F48: 0 | G48: 0.065 | H48: 1640 | I48: 0.024 | J48: 18800 | K48: 500 | L48: 0.5071 | P48: 2010,2011,2012,2013,2014,2015 | R48: 2020,2021,2022 | T48: 4 | U48: 0.432 | V48: 0.538 | W48: 0.142
A49: Tesla Model 3 | B49: Tesla | C49: Model 3 | D49: 230100 | E49: 0 | F49: 25.9 | G49: 0.065 | H49: 2480 | I49: 0.03 | J49: 21500 | K49: 600 | L49: 0.4184 | Q49: 2018 | R49: 2019,2020,2021,2022,2023 | T49: 3 | U49: 0.367 | V49: 0.503 | W49: 0.18
A50: Toyota 4Runner | B50: Toyota | C50: 4Runner | D50: 289900 | E50: 17 | F50: 0 | G50: 0.045 | H50: 1800 | I50: 0.024 | J50: 36333 | K50: 500 | L50: 0.6482 | R50: 2010,2011,2012,2013,2014,2015,2016,2017,2018,2019,2020,2021,2022,2023,2024 | T50: 5 | U50: 0.473 | V50: 0.57 | W50: 0.365
A51: Toyota Camry | B51: Toyota | C51: Camry | D51: 254800 | E51: 30 | F51: 0 | G51: 0.045 | H51: 1840 | I51: 0.018 | J51: 22400 | K51: 400 | L51: 0.4535 | P51: 2007,2008,2009 | Q51: 2018 | R51: 2015,2016,2017,2020,2021,2022 | T51: 2 | U51: 0.363 | V51: 0.436 | W51: 0.205
A52: Toyota Camry Hybrid | B52: Toyota | C52: Camry Hybrid | D52: 249600 | E52: 42 | F52: 0 | G52: 0.045 | H52: 1920 | I52: 0.018 | J52: 16500 | K52: 400 | L52: 0.392 | P52: 2007,2008,2009 | Q52: 2018 | R52: 2013,2014,2020,2021,2022 | T52: 2 | U52: 0.335 | V52: 0.411 | W52: 0.138
A53: Toyota Corolla | B53: Toyota | C53: Corolla | D53: 249600 | E53: 31 | F53: 0 | G53: 0.045 | H53: 1920 | I53: 0.018 | J53: 17659 | K53: 400 | L53: 0.4278 | Q53: 2009,2010,2014,2020,2023 | R53: 2016,2017,2018,2019,2021,2022 | T53: 2 | U53: 0.339 | V53: 0.402 | W53: 0.159
A54: Toyota Highlander | B54: Toyota | C54: Highlander | D54: 244400 | E54: 23 | F54: 0 | G54: 0.045 | H54: 1760 | I54: 0.024 | J54: 25000 | K54: 500 | L54: 0.5604 | Q54: 2015,2020 | R54: 2013,2014,2017,2018,2019,2021,2022 | T54: 5 | U54: 0.467 | V54: 0.571 | W54: 0.203
A55: Toyota Highlander Hybrid | B55: Toyota | C55: Highlander Hybrid | D55: 244400 | E55: 35 | F55: 0 | G55: 0.045 | H55: 1840 | I55: 0.024 | J55: 32000 | K55: 500 | L55: 0.4996 | Q55: 2015,2020 | R55: 2013,2014,2017,2018,2019,2021,2022 | T55: 4 | U55: 0.425 | V55: 0.524 | W55: 0.275
A56: Toyota Prius (hybrid) | B56: Toyota | C56: Prius (hybrid) | D56: 249600 | E56: 50 | F56: 0 | G56: 0.045 | H56: 1800 | I56: 0.018 | J56: 26000 | K56: 400 | L56: 0.3916 | Q56: 2010,2011,2016 | R56: 2013,2014,2015,2018,2019 | T56: 1 | U56: 0.321 | V56: 0.387 | W56: 0.245
A57: Toyota Prius Prime | B57: Toyota | C57: Prius Prime | D57: 235300 | E57: 120 | F57: 14.4 | G57: 0.045 | H57: 1920 | I57: 0.024 | J57: 15000 | K57: 600 | L57: 0.3641 | Q57: 2017 | R57: 2018,2019,2020,2021,2022 | T57: 2 | U57: 0.33 | V57: 0.415 | W57: 0.117
A58: Toyota RAV4 | B58: Toyota | C58: RAV4 | D58: 240500 | E58: 28 | F58: 0 | G58: 0.045 | H58: 1720 | I58: 0.022 | J58: 20600 | K58: 450 | L58: 0.4881 | P58: 2013,2014,2015 | Q58: 2019 | R58: 2016,2017,2018,2021,2022 | T58: 3 | U58: 0.396 | V58: 0.477 | W58: 0.168
A59: Toyota RAV4 Hybrid | B59: Toyota | C59: RAV4 Hybrid | D59: 244400 | E59: 40 | F59: 0 | G59: 0.045 | H59: 1800 | I59: 0.024 | J59: 30444 | K59: 500 | L59: 0.4486 | Q59: 2019 | R59: 2017,2018,2021,2022 | T59: 2 | U59: 0.359 | V59: 0.437 | W59: 0.283
A60: Toyota RAV4 Prime | B60: Toyota | C60: RAV4 Prime | D60: 235300 | E60: 152 | F60: 28.4 | G60: 0.045 | H60: 1760 | I60: 0.026 | J60: 35000 | K60: 800 | L60: 0.4817 | Q60: 2021 | R60: 2022,2023 | T60: 3 | U60: 0.402 | V60: 0.484 | W60: 0.302
A61: Toyota Sequoia | B61: Toyota | C61: Sequoia | D61: 300300 | E61: 15 | F61: 0 | G61: 0.045 | H61: 1960 | I61: 0.024 | J61: 32250 | K61: 500 | L61: 0.6875 | Q61: 2008 | R61: 2010,2011,2012,2013,2014,2015,2016,2017,2018,2019,2020,2021,2022 | T61: 6 | U61: 0.508 | V61: 0.613 | W61: 0.314
A62: Toyota Sienna (V6) | B62: Toyota | C62: Sienna (V6) | D62: 244400 | E62: 19 | F62: 0 | G62: 0.045 | H62: 1720 | I62: 0.02 | J62: 22333 | K62: 500 | L62: 0.5733 | Q62: 2011,2017 | R62: 2015,2016 | T62: 5 | U62: 0.457 | V62: 0.533 | W62: 0.192
A63: Toyota Sienna Hybrid | B63: Toyota | C63: Sienna Hybrid | D63: 244400 | E63: 36 | F63: 0 | G63: 0.045 | H63: 1840 | I63: 0.02 | J63: 35000 | K63: 500 | L63: 0.4961 | R63: 2021,2022,2023,2024,2025 | T63: 4 | U63: 0.416 | V63: 0.525 | W63: 0.31
A64: Toyota Tacoma | B64: Toyota | C64: Tacoma | D64: 289900 | E64: 20 | F64: 0 | G64: 0.045 | H64: 1800 | I64: 0.03 | J64: 29333 | K64: 800 | L64: 0.5852 | Q64: 2016 | R64: 2012,2013,2014,2015,2018,2019,2020,2021,2022 | T64: 4 | U64: 0.44 | V64: 0.531 | W64: 0.281
A65: VW Atlas | B65: VW | C65: Atlas | D65: 189800 | E65: 21 | F65: 0 | G65: 0.065 | H65: 1760 | I65: 0.024 | J65: 21000 | K65: 500 | L65: 0.6058 | Q65: 2018,2019 | R65: 2021,2022,2023 | T65: 6 | U65: 0.543 | V65: 0.656 | W65: 0.154
A66: VW GTI | B66: VW | C66: GTI | D66: 195000 | E66: 27 | F66: 0 | G66: 0.065 | H66: 1720 | I66: 0.018 | J66: 19000 | K66: 400 | L66: 0.5183 | P66: 2010,2011,2012 | Q66: 2015 | R66: 2016,2017,2018,2019 | T66: 5 | U66: 0.464 | V66: 0.574 | W66: 0.143
A67: VW ID.4 (AWD avail) | B67: VW | C67: ID.4 (AWD avail) | D67: 195000 | E67: 0 | F67: 36.7 | G67: 0.085 | H67: 1920 | I67: 0.03 | J67: 22500 | K67: 700 | L67: 0.4721 | Q67: 2021,2022 | R67: 2023,2024 | T67: 3 | U67: 0.389 | V67: 0.529 | W67: 0.177
A68: VW Passat | B68: VW | C68: Passat | D68: 189800 | E68: 28 | F68: 0 | G68: 0.065 | H68: 1720 | I68: 0.018 | J68: 14200 | K68: 400 | L68: 0.4733 | Q68: 2012 | R68: 2016,2017,2018,2019 | T68: 4 | U68: 0.412 | V68: 0.507 | W68: 0.107
A69: VW Tiguan | B69: VW | C69: Tiguan | D69: 184600 | E69: 24 | F69: 0 | G69: 0.065 | H69: 1680 | I69: 0.024 | J69: 16800 | K69: 500 | L69: 0.5362 | P69: 2009,2010,2011 | Q69: 2018 | R69: 2019,2020,2021,2022 | T69: 5 | U69: 0.482 | V69: 0.59 | W69: 0.123
A70: Volvo V90 Cross Country | B70: Volvo | C70: V90 Cross Country | D70: 200200 | E70: 25 | F70: 0 | G70: 0.065 | H70: 1880 | I70: 0.024 | J70: 29800 | K70: 500 | L70: 0.6215 | Q70: 2017 | R70: 2019,2020,2021,2022 | T70: 7 | U70: 0.584 | V70: 0.715 | W70: 0.225
A71: Volvo XC60 | B71: Volvo | C71: XC60 | D71: 200200 | E71: 23 | F71: 0 | G71: 0.065 | H71: 1880 | I71: 0.024 | J71: 25200 | K71: 500 | L71: 0.6065 | Q71: 2018 | R71: 2020,2021,2022 | T71: 7 | U71: 0.566 | V71: 0.69 | W71: 0.19
A72: Volvo XC90 | B72: Volvo | C72: XC90 | D72: 195000 | E72: 22 | F72: 0 | G72: 0.085 | H72: 1920 | I72: 0.024 | J72: 30000 | K72: 500 | L72: 0.6937 | P72: 2016 | Q72: 2017 | R72: 2019,2020,2021,2022 | T72: 8 | U72: 0.635 | V72: 0.811 | W72: 0.22

Sheet Plot data (helper)
A1: PLOT DATA (helper) — backing table for the Plot tab. Edit the model on the Ranking tab, not here.
D4: $ per mile | E4: $ per mile | F4: $ per mile | G4: $ per mile (P90−P50) | H4: $ per mile | I4: $ per mile | J4: $ per mile | K4: $ per mile | L4: $ per mile per +$1/gal | M4: dollars (total) | N4: dollars (total) | O4: $ per year | P4: $ per seat-mile | Q4: seats (count) | R4: cubic feet | S4: grams CO₂ per mile | U4: chart plumbing — one column per vehicle, feeds the Plot scatter. Do not edit, hide, or delete.
A5: Vehicle | B5: fuel | C5: $/mi (x) | D5: P75 $/mi | E5: P90 $/mi (bad-luck) | F5: EOL=empirical $/mi | G5: Bad-luck spread (P90-P50) | H5: 75k-mi (~5.8yr) $/mi | I5: v1 $/mi (old model) | J5: Energy $/mi | K5: Non-energy $/mi | L5: +$1/gal → Δ$/mi | M5: Purchase $ | N5: Up-front capital $ | O5: Insurance $/yr | P5: $ per seat-mile | Q5: Seats | R5: Max cargo (cu ft) | S5: CO2 g/mi | T5: Y (selected) | U5: Chevy Bolt EV | V5: Chevy Volt | W5: Toyota Prius (hybrid) | X5: Toyota Prius Prime | Y5: Toyota Corolla | Z5: Toyota Camry Hybrid | AA5: Honda Civic | AB5: Nissan Leaf | AC5: Hyundai Elantra | AD5: Honda Accord | AE5: Kia K4 | AF5: Mazda3 (SkyActiv) | AG5: Toyota Camry | AH5: Toyota RAV4 Hybrid | AI5: Kia Niro (hybrid) | AJ5: Tesla Model 3 | AK5: Hyundai Sonata | AL5: Toyota RAV4 | AM5: Fiat 500 | AN5: Honda CR-V | AO5: VW ID.4 (AWD avail) | AP5: Toyota RAV4 Prime | AQ5: Kia Soul | AR5: VW Passat | AS5: Buick Encore | AT5: Hyundai Kona | AU5: Mazda CX-5 | AV5: Toyota Highlander Hybrid | AW5: Subaru Outback | AX5: Subaru Forester | AY5: Toyota Sienna Hybrid | AZ5: Toyota Tacoma | BA5: Nissan Rogue | BB5: Chevy Equinox | BC5: Toyota Sienna (V6) | BD5: Mini Cooper | BE5: Ford Ranger (old compact) | BF5: Fiat 500X | BG5: VW GTI | BH5: Kia Sportage | BI5: Ford Escape | BJ5: Toyota Highlander | BK5: Hyundai Tucson | BL5: Toyota 4Runner | BM5: Honda Odyssey | BN5: Kia Sorento | BO5: Hyundai Santa Fe | BP5: VW Tiguan | BQ5: Chrysler Pacifica PHEV | BR5: Subaru Ascent | BS5: Ford Ranger (2019+ midsize) | BT5: Honda Pilot | BU5: Mini Countryman | BV5: Toyota Sequoia | BW5: Hyundai Palisade | BX5: Chrysler Pacifica | BY5: Chevy Colorado | BZ5: Kia Telluride | CA5: Mazda CX-90 | CB5: Chevy Traverse | CC5: VW Atlas | CD5: Ford Explorer | CE5: Buick Enclave | CF5: Volvo XC60 | CG5: Chevy Tahoe | CH5: Jeep Grand Cherokee L | CI5: Volvo V90 Cross Country | CJ5: Chevy Suburban | CK5: Volvo XC90 | CL5: Porsche 996 Carrera | CM5: Porsche 996 Turbo | CO5: sedan | CP5: hatch | CQ5: SUV | CR5: truck | CS5: van | CT5: sport
A6: Chevy Bolt EV | B6: ev | C6: 0.315 | D6: 0.342 | E6: 0.372 | F6: 0.335 | G6: 0.056 | H6: 0.381 | I6: 0.338 | J6: 0.072 | K6: 0.243 | L6: 0 | M6: 15643 | N6: 16738 | O6: 1660 | P6: 0.0631 | Q6: 5 | R6: 57 | S6: 76 | T6: =IFERROR(INDEX($D6:$S6,1,MATCH(Plot!$B$3,$D$5:$S$5,0)),NA()) | U6: =$T$6 | CP6: =$T$6
A7: Chevy Volt | B7: phev | C7: 0.335 | D7: 0.353 | E7: 0.37 | F7: 0.359 | G7: 0.035 | H7: 0.387 | I7: 0.35 | J7: 0.08 | K7: 0.255 | L7: 0.003 | M7: 15143 | N7: 16203 | O7: 1440 | P7: 0.0671 | Q7: 5 | R7: 30 | S7: 107 | T7: =IFERROR(INDEX($D7:$S7,1,MATCH(Plot!$B$3,$D$5:$S$5,0)),NA()) | V7: =$T$7 | CP7: =$T$7
A8: Toyota Prius (hybrid) | B8: hybrid | C8: 0.353 | D8: 0.366 | E8: 0.378 | F8: 0.39 | G8: 0.025 | H8: 0.484 | I8: 0.348 | J8: 0.066 | K8: 0.287 | L8: 0.012 | M8: 26000 | N8: 27820 | O8: 1800 | P8: 0.0706 | Q8: 5 | R8: 50 | S8: 178 | T8: =IFERROR(INDEX($D8:$S8,1,MATCH(Plot!$B$3,$D$5:$S$5,0)),NA()) | W8: =$T$8 | CP8: =$T$8
A9: Toyota Prius Prime | B9: phev | C9: 0.364 | D9: 0.382 | E9: 0.402 | F9: 0.402 | G9: 0.038 | H9: 0.431 | I9: 0.37 | J9: 0.066 | K9: 0.298 | L9: 0.006 | M9: 15000 | N9: 16050 | O9: 1920 | P9: 0.0728 | Q9: 5 | R9: 20 | S9: 110 | T9: =IFERROR(INDEX($D9:$S9,1,MATCH(Plot!$B$3,$D$5:$S$5,0)),NA()) | X9: =$T$9 | CP9: =$T$9
A10: Toyota Corolla | B10: gas | C10: 0.368 | D10: 0.381 | E10: 0.393 | F10: 0.397 | G10: 0.025 | H10: 0.472 | I10: 0.364 | J10: 0.111 | K10: 0.258 | L10: 0.02 | M10: 17659 | N10: 18895 | O10: 1920 | P10: 0.0737 | Q10: 5 | R10: 13 | S10: 287 | T10: =IFERROR(INDEX($D10:$S10,1,MATCH(Plot!$B$3,$D$5:$S$5,0)),NA()) | Y10: =$T$10 | CO10: =$T$10
A11: Toyota Camry Hybrid | B11: hybrid | C11: 0.368 | D11: 0.384 | E11: 0.4 | F11: 0.402 | G11: 0.032 | H11: 0.45 | I11: 0.367 | J11: 0.086 | K11: 0.282 | L11: 0.016 | M11: 16500 | N11: 17655 | O11: 1920 | P11: 0.0737 | Q11: 5 | R11: 15 | S11: 212 | T11: =IFERROR(INDEX($D11:$S11,1,MATCH(Plot!$B$3,$D$5:$S$5,0)),NA()) | Z11: =$T$11 | CO11: =$T$11
A12: Honda Civic | B12: gas | C12: 0.385 | D12: 0.397 | E12: 0.409 | F12: 0.42 | G12: 0.024 | H12: 0.509 | I12: 0.38 | J12: 0.106 | K12: 0.279 | L12: 0.019 | M12: 23789 | N12: 25455 | O12: 1840 | P12: 0.077 | Q12: 5 | R12: 15 | S12: 278 | T12: =IFERROR(INDEX($D12:$S12,1,MATCH(Plot!$B$3,$D$5:$S$5,0)),NA()) | AA12: =$T$12 | CO12: =$T$12
A13: Nissan Leaf | B13: ev | C13: 0.386 | D13: 0.422 | E13: 0.453 | F13: 0.42 | G13: 0.067 | H13: 0.403 | I13: 0.419 | J13: 0.089 | K13: 0.297 | L13: 0 | M13: 11667 | N13: 12483 | O13: 1760 | P13: 0.0771 | Q13: 5 | R13: 30 | S13: 81 | T13: =IFERROR(INDEX($D13:$S13,1,MATCH(Plot!$B$3,$D$5:$S$5,0)),NA()) | AB13: =$T$13 | CP13: =$T$13
A14: Hyundai Elantra | B14: gas | C14: 0.39 | D14: 0.406 | E14: 0.422 | F14: 0.419 | G14: 0.033 | H14: 0.466 | I14: 0.385 | J14: 0.107 | K14: 0.283 | L14: 0.02 | M14: 16000 | N14: 17120 | O14: 1640 | P14: 0.078 | Q14: 5 | R14: 14 | S14: 254 | T14: =IFERROR(INDEX($D14:$S14,1,MATCH(Plot!$B$3,$D$5:$S$5,0)),NA()) | AC14: =$T$14 | CO14: =$T$14
A15: Honda Accord | B15: gas | C15: 0.39 | D15: 0.404 | E15: 0.417 | F15: 0.421 | G15: 0.027 | H15: 0.478 | I15: 0.386 | J15: 0.117 | K15: 0.273 | L15: 0.021 | M15: 16143 | N15: 17273 | O15: 1840 | P15: 0.078 | Q15: 5 | R15: 17 | S15: 287 | T15: =IFERROR(INDEX($D15:$S15,1,MATCH(Plot!$B$3,$D$5:$S$5,0)),NA()) | AD15: =$T$15 | CO15: =$T$15
A16: Kia K4 | B16: gas | C16: 0.396 | D16: 0.41 | E16: 0.425 | F16: 0.423 | G16: 0.029 | H16: 0.488 | I16: 0.391 | J16: 0.106 | K16: 0.29 | L16: 0.019 | M16: 20125 | N16: 21534 | O16: 1640 | P16: 0.0792 | Q16: 5 | R16: 15 | S16: 261 | T16: =IFERROR(INDEX($D16:$S16,1,MATCH(Plot!$B$3,$D$5:$S$5,0)),NA()) | AE16: =$T$16 | CO16: =$T$16
A17: Mazda3 (SkyActiv) | B17: gas | C17: 0.396 | D17: 0.414 | E17: 0.432 | F17: 0.441 | G17: 0.035 | H17: 0.491 | I17: 0.395 | J17: 0.127 | K17: 0.269 | L17: 0.023 | M17: 15000 | N17: 16050 | O17: 1720 | P17: 0.0792 | Q17: 5 | R17: 20 | S17: 296 | T17: =IFERROR(INDEX($D17:$S17,1,MATCH(Plot!$B$3,$D$5:$S$5,0)),NA()) | AF17: =$T$17 | CP17: =$T$17
A18: Toyota Camry | B18: gas | C18: 0.397 | D18: 0.41 | E18: 0.424 | F18: 0.435 | G18: 0.027 | H18: 0.535 | I18: 0.388 | J18: 0.113 | K18: 0.284 | L18: 0.021 | M18: 22400 | N18: 23968 | O18: 1840 | P18: 0.0794 | Q18: 5 | R18: 15 | S18: 296 | T18: =IFERROR(INDEX($D18:$S18,1,MATCH(Plot!$B$3,$D$5:$S$5,0)),NA()) | AG18: =$T$18 | CO18: =$T$18
A19: Toyota RAV4 Hybrid | B19: hybrid | C19: 0.398 | D19: 0.414 | E19: 0.428 | F19: 0.438 | G19: 0.029 | H19: 0.535 | I19: 0.395 | J19: 0.084 | K19: 0.314 | L19: 0.015 | M19: 30444 | N19: 32576 | O19: 1800 | P19: 0.0796 | Q19: 5 | R19: 69 | S19: 222 | T19: =IFERROR(INDEX($D19:$S19,1,MATCH(Plot!$B$3,$D$5:$S$5,0)),NA()) | AH19: =$T$19 | CQ19: =$T$19
A20: Kia Niro (hybrid) | B20: hybrid | C20: 0.402 | D20: 0.422 | E20: 0.443 | F20: 0.438 | G20: 0.041 | H20: 0.47 | I20: 0.399 | J20: 0.079 | K20: 0.323 | L20: 0.014 | M20: 17000 | N20: 18190 | O20: 1680 | P20: 0.0804 | Q20: 5 | R20: 54 | S20: 181 | T20: =IFERROR(INDEX($D20:$S20,1,MATCH(Plot!$B$3,$D$5:$S$5,0)),NA()) | AI20: =$T$20 | CQ20: =$T$20
A21: Tesla Model 3 | B21: ev | C21: 0.413 | D21: 0.443 | E21: 0.477 | F21: 0.448 | G21: 0.064 | H21: 0.512 | I21: 0.416 | J21: 0.06 | K21: 0.353 | L21: 0 | M21: 21500 | N21: 23005 | O21: 2480 | P21: 0.0826 | Q21: 5 | R21: 23 | S21: 65 | T21: =IFERROR(INDEX($D21:$S21,1,MATCH(Plot!$B$3,$D$5:$S$5,0)),NA()) | AJ21: =$T$21 | CO21: =$T$21
A22: Hyundai Sonata | B22: gas | C22: 0.422 | D22: 0.441 | E22: 0.461 | F22: 0.458 | G22: 0.038 | H22: 0.495 | I22: 0.423 | J22: 0.122 | K22: 0.3 | L22: 0.022 | M22: 15333 | N22: 16407 | O22: 1720 | P22: 0.0845 | Q22: 5 | R22: 16 | S22: 278 | T22: =IFERROR(INDEX($D22:$S22,1,MATCH(Plot!$B$3,$D$5:$S$5,0)),NA()) | AK22: =$T$22 | CO22: =$T$22
A23: Toyota RAV4 | B23: gas | C23: 0.431 | D23: 0.447 | E23: 0.464 | F23: 0.468 | G23: 0.033 | H23: 0.526 | I23: 0.432 | J23: 0.132 | K23: 0.299 | L23: 0.024 | M23: 20600 | N23: 22042 | O23: 1720 | P23: 0.0862 | Q23: 5 | R23: 69 | S23: 317 | T23: =IFERROR(INDEX($D23:$S23,1,MATCH(Plot!$B$3,$D$5:$S$5,0)),NA()) | AL23: =$T$23 | CQ23: =$T$23
A24: Fiat 500 | B24: gas | C24: 0.434 | D24: 0.454 | E24: 0.483 | F24: 0.451 | G24: 0.048 | H24: 0.469 | I24: 0.435 | J24: 0.123 | K24: 0.312 | L24: 0.023 | M24: 10200 | N24: 10914 | O24: 1600 | P24: 0.1086 | Q24: 4 | R24: 30 | S24: 269 | T24: =IFERROR(INDEX($D24:$S24,1,MATCH(Plot!$B$3,$D$5:$S$5,0)),NA()) | AM24: =$T$24 | CP24: =$T$24
A25: Honda CR-V | B25: gas | C25: 0.438 | D25: 0.454 | E25: 0.469 | F25: 0.473 | G25: 0.032 | H25: 0.541 | I25: 0.432 | J25: 0.131 | K25: 0.307 | L25: 0.024 | M25: 20500 | N25: 21935 | O25: 1680 | P25: 0.0875 | Q25: 5 | R25: 76 | S25: 317 | T25: =IFERROR(INDEX($D25:$S25,1,MATCH(Plot!$B$3,$D$5:$S$5,0)),NA()) | AN25: =$T$25 | CQ25: =$T$25
A26: VW ID.4 (AWD avail) | B26: ev | C26: 0.438 | D26: 0.47 | E26: 0.503 | F26: 0.464 | G26: 0.066 | H26: 0.508 | I26: 0.449 | J26: 0.089 | K26: 0.349 | L26: 0 | M26: 22500 | N26: 24075 | O26: 1920 | P26: 0.0875 | Q26: 5 | R26: 64 | S26: 92 | T26: =IFERROR(INDEX($D26:$S26,1,MATCH(Plot!$B$3,$D$5:$S$5,0)),NA()) | AO26: =$T$26 | CQ26: =$T$26
A27: Toyota RAV4 Prime | B27: phev | C27: 0.441 | D27: 0.457 | E27: 0.476 | F27: 0.486 | G27: 0.036 | H27: 0.56 | I27: 0.45 | J27: 0.086 | K27: 0.355 | L27: 0.004 | M27: 35000 | N27: 37450 | O27: 1760 | P27: 0.0881 | Q27: 5 | R27: 63 | S27: 129 | T27: =IFERROR(INDEX($D27:$S27,1,MATCH(Plot!$B$3,$D$5:$S$5,0)),NA()) | AP27: =$T$27 | CQ27: =$T$27
A28: Kia Soul | B28: gas | C28: 0.441 | D28: 0.458 | E28: 0.478 | F28: 0.477 | G28: 0.038 | H28: 0.503 | I28: 0.442 | J28: 0.138 | K28: 0.302 | L28: 0.025 | M28: 14500 | N28: 15515 | O28: 1640 | P28: 0.0881 | Q28: 5 | R28: 62 | S28: 306 | T28: =IFERROR(INDEX($D28:$S28,1,MATCH(Plot!$B$3,$D$5:$S$5,0)),NA()) | AQ28: =$T$28 | CQ28: =$T$28
A29: VW Passat | B29: gas | C29: 0.447 | D29: 0.468 | E29: 0.488 | F29: 0.48 | G29: 0.042 | H29: 0.516 | I29: 0.443 | J29: 0.14 | K29: 0.307 | L29: 0.026 | M29: 14200 | N29: 15194 | O29: 1720 | P29: 0.0894 | Q29: 5 | R29: 16 | S29: 317 | T29: =IFERROR(INDEX($D29:$S29,1,MATCH(Plot!$B$3,$D$5:$S$5,0)),NA()) | AR29: =$T$29 | CO29: =$T$29
A30: Buick Encore | B30: gas | C30: 0.45 | D30: 0.466 | E30: 0.485 | F30: 0.485 | G30: 0.035 | H30: 0.511 | I30: 0.451 | J30: 0.143 | K30: 0.307 | L30: 0.026 | M30: 14800 | N30: 15836 | O30: 1680 | P30: 0.0901 | Q30: 5 | R30: 48 | S30: 317 | T30: =IFERROR(INDEX($D30:$S30,1,MATCH(Plot!$B$3,$D$5:$S$5,0)),NA()) | AS30: =$T$30 | CQ30: =$T$30
A31: Hyundai Kona | B31: gas | C31: 0.456 | D31: 0.472 | E31: 0.493 | F31: 0.484 | G31: 0.037 | H31: 0.504 | I31: 0.459 | J31: 0.135 | K31: 0.32 | L31: 0.025 | M31: 15000 | N31: 16050 | O31: 1640 | P31: 0.0912 | Q31: 5 | R31: 45 | S31: 296 | T31: =IFERROR(INDEX($D31:$S31,1,MATCH(Plot!$B$3,$D$5:$S$5,0)),NA()) | AT31: =$T$31 | CQ31: =$T$31
A32: Mazda CX-5 | B32: gas | C32: 0.461 | D32: 0.477 | E32: 0.492 | F32: 0.505 | G32: 0.032 | H32: 0.565 | I32: 0.467 | J32: 0.146 | K32: 0.315 | L32: 0.027 | M32: 20600 | N32: 22042 | O32: 1680 | P32: 0.0921 | Q32: 5 | R32: 59 | S32: 342 | T32: =IFERROR(INDEX($D32:$S32,1,MATCH(Plot!$B$3,$D$5:$S$5,0)),NA()) | AU32: =$T$32 | CQ32: =$T$32
A33: Toyota Highlander Hybrid | B33: hybrid | C33: 0.47 | D33: 0.49 | E33: 0.512 | F33: 0.531 | G33: 0.042 | H33: 0.629 | I33: 0.463 | J33: 0.101 | K33: 0.369 | L33: 0.019 | M33: 32000 | N33: 34240 | O33: 1840 | P33: 0.0671 | Q33: 7 | R33: 84 | S33: 254 | T33: =IFERROR(INDEX($D33:$S33,1,MATCH(Plot!$B$3,$D$5:$S$5,0)),NA()) | AV33: =$T$33 | CQ33: =$T$33
A34: Subaru Outback | B34: gas | C34: 0.471 | D34: 0.492 | E34: 0.517 | F34: 0.51 | G34: 0.046 | H34: 0.549 | I34: 0.477 | J34: 0.135 | K34: 0.336 | L34: 0.025 | M34: 18800 | N34: 20116 | O34: 1640 | P34: 0.0941 | Q34: 5 | R34: 76 | S34: 306 | T34: =IFERROR(INDEX($D34:$S34,1,MATCH(Plot!$B$3,$D$5:$S$5,0)),NA()) | AW34: =$T$34 | CQ34: =$T$34
A35: Subaru Forester | B35: gas | C35: 0.471 | D35: 0.488 | E35: 0.508 | F35: 0.507 | G35: 0.037 | H35: 0.551 | I35: 0.479 | J35: 0.132 | K35: 0.339 | L35: 0.024 | M35: 22200 | N35: 23754 | O35: 1680 | P35: 0.0943 | Q35: 5 | R35: 76 | S35: 306 | T35: =IFERROR(INDEX($D35:$S35,1,MATCH(Plot!$B$3,$D$5:$S$5,0)),NA()) | AX35: =$T$35 | CQ35: =$T$35
A36: Toyota Sienna Hybrid | B36: hybrid | C36: 0.473 | D36: 0.495 | E36: 0.514 | F36: 0.532 | G36: 0.041 | H36: 0.616 | I36: 0.451 | J36: 0.096 | K36: 0.377 | L36: 0.018 | M36: 35000 | N36: 37450 | O36: 1840 | P36: 0.0591 | Q36: 8 | R36: 101 | S36: 247 | T36: =IFERROR(INDEX($D36:$S36,1,MATCH(Plot!$B$3,$D$5:$S$5,0)),NA()) | AY36: =$T$36 | CS36: =$T$36
A37: Toyota Tacoma | B37: gas | C37: 0.481 | D37: 0.5 | E37: 0.519 | F37: 0.534 | G37: 0.038 | H37: 0.684 | I37: 0.474 | J37: 0.164 | K37: 0.317 | L37: 0.03 | M37: 29333 | N37: 31387 | O37: 1800 | P37: 0.0962 | Q37: 5 | R37: 40 | S37: 444 | T37: =IFERROR(INDEX($D37:$S37,1,MATCH(Plot!$B$3,$D$5:$S$5,0)),NA()) | AZ37: =$T$37 | CR37: =$T$37
A38: Nissan Rogue | B38: gas | C38: 0.486 | D38: 0.506 | E38: 0.529 | F38: 0.522 | G38: 0.043 | H38: 0.536 | I38: 0.498 | J38: 0.141 | K38: 0.344 | L38: 0.026 | M38: 18800 | N38: 20116 | O38: 1664 | P38: 0.0972 | Q38: 5 | R38: 74 | S38: 306 | T38: =IFERROR(INDEX($D38:$S38,1,MATCH(Plot!$B$3,$D$5:$S$5,0)),NA()) | BA38: =$T$38 | CQ38: =$T$38
A39: Chevy Equinox | B39: gas | C39: 0.488 | D39: 0.507 | E39: 0.531 | F39: 0.513 | G39: 0.043 | H39: 0.535 | I39: 0.498 | J39: 0.15 | K39: 0.338 | L39: 0.028 | M39: 17200 | N39: 18404 | O39: 1720 | P39: 0.0976 | Q39: 5 | R39: 64 | S39: 329 | T39: =IFERROR(INDEX($D39:$S39,1,MATCH(Plot!$B$3,$D$5:$S$5,0)),NA()) | BB39: =$T$39 | CQ39: =$T$39
A40: Toyota Sienna (V6) | B40: gas | C40: 0.493 | D40: 0.508 | E40: 0.523 | F40: 0.537 | G40: 0.029 | H40: 0.639 | I40: 0.483 | J40: 0.187 | K40: 0.306 | L40: 0.034 | M40: 22333 | N40: 23897 | O40: 1720 | P40: 0.0616 | Q40: 8 | R40: 101 | S40: 468 | T40: =IFERROR(INDEX($D40:$S40,1,MATCH(Plot!$B$3,$D$5:$S$5,0)),NA()) | BC40: =$T$40 | CS40: =$T$40
A41: Mini Cooper | B41: gas | C41: 0.493 | D41: 0.517 | E41: 0.545 | F41: 0.524 | G41: 0.052 | H41: 0.554 | I41: 0.488 | J41: 0.132 | K41: 0.362 | L41: 0.024 | M41: 18200 | N41: 19474 | O41: 1720 | P41: 0.1234 | Q41: 4 | R41: 34 | S41: 296 | T41: =IFERROR(INDEX($D41:$S41,1,MATCH(Plot!$B$3,$D$5:$S$5,0)),NA()) | BD41: =$T$41 | CP41: =$T$41
A42: Ford Ranger (old compact) | B42: gas | C42: 0.494 | D42: 0.515 | E42: 0.534 | F42: 0.504 | G42: 0.04 | H42: 0.555 | I42: 0.498 | J42: 0.176 | K42: 0.318 | L42: 0.032 | M42: 11500 | N42: 12305 | O42: 1832 | P42: 0.0989 | Q42: 5 | R42: 35 | S42: 423 | T42: =IFERROR(INDEX($D42:$S42,1,MATCH(Plot!$B$3,$D$5:$S$5,0)),NA()) | BE42: =$T$42 | CR42: =$T$42
A43: Fiat 500X | B43: gas | C43: 0.5 | D43: 0.514 | E43: 0.533 | F43: 0.525 | G43: 0.033 | H43: 0.538 | I43: 0.51 | J43: 0.16 | K43: 0.34 | L43: 0.029 | M43: 14800 | N43: 15836 | O43: 1640 | P43: 0.1 | Q43: 5 | R43: 50 | S43: 342 | T43: =IFERROR(INDEX($D43:$S43,1,MATCH(Plot!$B$3,$D$5:$S$5,0)),NA()) | BF43: =$T$43 | CQ43: =$T$43
A44: VW GTI | B44: gas | C44: 0.504 | D44: 0.526 | E44: 0.55 | F44: 0.542 | G44: 0.047 | H44: 0.585 | I44: 0.499 | J44: 0.145 | K44: 0.359 | L44: 0.027 | M44: 19000 | N44: 20330 | O44: 1720 | P44: 0.1008 | Q44: 5 | R44: 53 | S44: 329 | T44: =IFERROR(INDEX($D44:$S44,1,MATCH(Plot!$B$3,$D$5:$S$5,0)),NA()) | BG44: =$T$44 | CP44: =$T$44
A45: Kia Sportage | B45: gas | C45: 0.505 | D45: 0.526 | E45: 0.551 | F45: 0.54 | G45: 0.046 | H45: 0.551 | I45: 0.514 | J45: 0.16 | K45: 0.345 | L45: 0.029 | M45: 15667 | N45: 16763 | O45: 1680 | P45: 0.101 | Q45: 5 | R45: 60 | S45: 342 | T45: =IFERROR(INDEX($D45:$S45,1,MATCH(Plot!$B$3,$D$5:$S$5,0)),NA()) | BH45: =$T$45 | CQ45: =$T$45
A46: Ford Escape | B46: gas | C46: 0.506 | D46: 0.528 | E46: 0.552 | F46: 0.546 | G46: 0.046 | H46: 0.55 | I46: 0.517 | J46: 0.161 | K46: 0.345 | L46: 0.03 | M46: 15000 | N46: 16050 | O46: 1720 | P46: 0.1012 | Q46: 5 | R46: 65 | S46: 342 | T46: =IFERROR(INDEX($D46:$S46,1,MATCH(Plot!$B$3,$D$5:$S$5,0)),NA()) | BI46: =$T$46 | CQ46: =$T$46
A47: Toyota Highlander | B47: gas | C47: 0.512 | D47: 0.533 | E47: 0.555 | F47: 0.569 | G47: 0.043 | H47: 0.646 | I47: 0.508 | J47: 0.161 | K47: 0.351 | L47: 0.03 | M47: 25000 | N47: 26750 | O47: 1760 | P47: 0.0731 | Q47: 7 | R47: 84 | S47: 386 | T47: =IFERROR(INDEX($D47:$S47,1,MATCH(Plot!$B$3,$D$5:$S$5,0)),NA()) | BJ47: =$T$47 | CQ47: =$T$47
A48: Hyundai Tucson | B48: gas | C48: 0.519 | D48: 0.534 | E48: 0.559 | F48: 0.534 | G48: 0.04 | H48: 0.555 | I48: 0.532 | J48: 0.164 | K48: 0.355 | L48: 0.03 | M48: 19541 | N48: 20908 | O48: 1680 | P48: 0.1039 | Q48: 5 | R48: 74 | S48: 355 | T48: =IFERROR(INDEX($D48:$S48,1,MATCH(Plot!$B$3,$D$5:$S$5,0)),NA()) | BK48: =$T$48 | CQ48: =$T$48
A49: Toyota 4Runner | B49: gas | C49: 0.521 | D49: 0.541 | E49: 0.558 | F49: 0.579 | G49: 0.037 | H49: 0.766 | I49: 0.512 | J49: 0.187 | K49: 0.334 | L49: 0.034 | M49: 36333 | N49: 38877 | O49: 1800 | P49: 0.0745 | Q49: 7 | R49: 89 | S49: 523 | T49: =IFERROR(INDEX($D49:$S49,1,MATCH(Plot!$B$3,$D$5:$S$5,0)),NA()) | BL49: =$T$49 | CQ49: =$T$49
A50: Honda Odyssey | B50: gas | C50: 0.522 | D50: 0.544 | E50: 0.568 | F50: 0.568 | G50: 0.046 | H50: 0.623 | I50: 0.512 | J50: 0.174 | K50: 0.348 | L50: 0.032 | M50: 20333 | N50: 21757 | O50: 1680 | P50: 0.0653 | Q50: 8 | R50: 144 | S50: 404 | T50: =IFERROR(INDEX($D50:$S50,1,MATCH(Plot!$B$3,$D$5:$S$5,0)),NA()) | BM50: =$T$50 | CS50: =$T$50
A51: Kia Sorento | B51: gas | C51: 0.522 | D51: 0.542 | E51: 0.569 | F51: 0.566 | G51: 0.046 | H51: 0.596 | I51: 0.524 | J51: 0.167 | K51: 0.355 | L51: 0.031 | M51: 18333 | N51: 19617 | O51: 1720 | P51: 0.0746 | Q51: 7 | R51: 75 | S51: 370 | T51: =IFERROR(INDEX($D51:$S51,1,MATCH(Plot!$B$3,$D$5:$S$5,0)),NA()) | BN51: =$T$51 | CQ51: =$T$51
A52: Hyundai Santa Fe | B52: gas | C52: 0.524 | D52: 0.546 | E52: 0.575 | F52: 0.571 | G52: 0.052 | H52: 0.577 | I52: 0.533 | J52: 0.166 | K52: 0.357 | L52: 0.03 | M52: 16667 | N52: 17833 | O52: 1720 | P52: 0.1047 | Q52: 5 | R52: 72 | S52: 355 | T52: =IFERROR(INDEX($D52:$S52,1,MATCH(Plot!$B$3,$D$5:$S$5,0)),NA()) | BO52: =$T$52 | CQ52: =$T$52
A53: VW Tiguan | B53: gas | C53: 0.525 | D53: 0.545 | E53: 0.572 | F53: 0.559 | G53: 0.047 | H53: 0.575 | I53: 0.516 | J53: 0.167 | K53: 0.358 | L53: 0.031 | M53: 16800 | N53: 17976 | O53: 1680 | P53: 0.105 | Q53: 5 | R53: 74 | S53: 370 | T53: =IFERROR(INDEX($D53:$S53,1,MATCH(Plot!$B$3,$D$5:$S$5,0)),NA()) | BP53: =$T$53 | CQ53: =$T$53
